Workbook
Name EV_make_and_model: EV_DB[Make & Model]
Name ICE_make_and_model: ICE_DB[Make + Model]
Name Unique_chargers: Charger_DB[Charger type]

Sheet TCO Dashboard
B2: Cells Highlighted in Green are INPUT Cells
B5: 1. Enter Duty Dycle Requirements | E5: 2. Review EV Recommendations | J5: 3. Review ICE vehicles
B6: Duty cycle | E6: Make & Model | F6: Type | G6: Price | H6: Battery Size | J6: Make & Model | K6: price | L6: Payload (lbs) | M6: Fuel type
B7: Required daily distance (km) | C7: 200 | E7: {=IFERROR(INDEX(_xlfn._xlws.FILTER(EV_DB[Make & Model], (EV_DB[Category]=C9) * (EV_DB[Range (km)]>=C7) * (EV_DB[Max Payload, lbs.]>=C8) * (EV_DB[Refrigerated Unit]=C10) * ((EV_DB[Range (km)]<>"") * (EV_DB[Max Payload, lbs.]<>"")), "No EV Matches Your Duty Cycle"), _xlfn.SEQUENCE(10,1)), "")} -> Ram Electric 1500 Large Battery | F7: {=IFERROR(INDEX(_xlfn._xlws.FILTER(EV_DB[Type/Use Case], (EV_DB[Category]=C9) * (EV_DB[Range (km)]>=C7) * (EV_DB[Max Payload, lbs.]>=C8) * (EV_DB[Refrigerated Unit]=C10) * ((EV_DB[Range (km)]<>"") * (EV_DB[Max Payload, lbs.]<>"")), "No EV Matches Your Duty Cycle"), _xlfn.SEQUENCE(10,1)), "")} -> Pick-up truck | G7: {=IFERROR(INDEX(_xlfn._xlws.FILTER(EV_DB[Cost, $MSRP CAD], (EV_DB[Category]=C9) * (EV_DB[Range (km)]>=C7) * (EV_DB[Max Payload, lbs.]>=C8) * (EV_DB[Refrigerated Unit]=C10) * ((EV_DB[Range (km)]<>"") * (EV_DB[Max Payload, lbs.]<>"")), "No EV Matches Your Duty Cycle"), _xlfn.SEQUENCE(10,1)), "")} -> 81085 | H7: {=IFERROR(INDEX(_xlfn._xlws.FILTER(EV_DB[Battery Size, kWh], (EV_DB[Category]=C9) * (EV_DB[Range (km)]>=C7) * (EV_DB[Max Payload, lbs.]>=C8) * (EV_DB[Refrigerated Unit]=C10) * ((EV_DB[Range (km)]<>"") * (EV_DB[Max Payload, lbs.]<>"")), "No EV Matches Your Duty Cycle"), _xlfn.SEQUENCE(10,1)), "")} -> 229kwh | J7: {=IFERROR(INDEX(_xlfn._xlws.FILTER(ICE_DB[Make + Model], (ICE_DB[Category]=C9) * (ICE_DB[Payload (lbs)]>=C8) * (ICE_DB[Payload (lbs)]<>""), "No ICE vehicle in our database matches Your Duty Cycle"), _xlfn.SEQUENCE(10,1)), "")} -> Ford Transit | K7: {=IFERROR(INDEX(_xlfn._xlws.FILTER(ICE_DB[Purchase price ($ CAD)], (ICE_DB[Category]=C9) * (ICE_DB[Payload (lbs)]>=C8) * (ICE_DB[Payload (lbs)]<>""), "No ICE vehicle in our database matches Your Duty Cycle"), _xlfn.SEQUENCE(10,1)), "")} -> 68580 | L7: {=IFERROR(INDEX(_xlfn._xlws.FILTER(ICE_DB[Payload (lbs)], (ICE_DB[Category]=C9) * (ICE_DB[Payload (lbs)]>=C8) * (ICE_DB[Payload (lbs)]<>""), "No ICE vehicle in our database matches Your Duty Cycle"), _xlfn.SEQUENCE(10,1)), "")} -> 3148 | M7: {=IFERROR(INDEX(_xlfn._xlws.FILTER(ICE_DB[Fuel type], (ICE_DB[Category]=C9) * (ICE_DB[Payload (lbs)]>=C8) * (ICE_DB[Payload (lbs)]<>""), "No ICE vehicle in our database matches Your Duty Cycle"), _xlfn.SEQUENCE(10,1)), "")} -> Diesel
B8: Maximum payload (lbs) | C8: 500 | E8: GMC GMC Sierra EV Denali Edition 1 | F8: Pick-up truck | G8: 92290 | H8: 205kwh | J8: Ford Transit High Roof Refrigerated | K8: 71000 | L8: 4000 | M8: Gasoline
B9: Category | C9: Light Duty | E9: Chevrolet Silverado EV 3WT Max Range | F9: Pick-up truck | G9: 85833 | H9: 205kwh | J9: Mercedes Sprinter Cargo Van Low Roof | K9: 59980 | L9: 3780 | M9: Gasoline
B10: Refrigeration required? | C10: No | E10: Chevrolet Silverado EV LT E4WD | F10: Pick-up truck | G10: 95833 | H10: 170kwh | J10: Mercedes Sprinter Cargo Van High Roof | K10: 67400 | L10: 4210 | M10: Diesel
E11: Ford F 150 Lightning | F11: Pick-up truck | G11: 62890 | H11: 98 kWh | J11: Ford F-150 | K11: 54000 | L11: 3325 | M11: Gasoline
E12: Ford F 150 Lightning Flash and Lariat | F12: Pick-up truck | G12: 79090 | H12: 131 kWh | J12: Chevy Silverado 1500 WT | K12: 61000 | L12: 2270 | M12: Gasoline
E13: Mercedes-Benz eSprinter (2500) | F13: Delivery van | G13: 99500 | H13: 113 kWh | J13: Chevrolet Express 2500 Cargo Van | K13: 56033 | L13: 3496 | M13: Gasoline
E14: RAM ProMaster Van | F14: Cargo van | G14: 119000 | H14: 110kWh | J14: Ram ProMaster Van | K14: 80000 | L14: 4820 | M14: Gasoline
E15: Rivian R1T Dual | F15: Pick-up truck | G15: 77900 | H15: 135 kWh | J15: Isuzu NPR | K15: 60000 | L15: 8800 | M15: Gasoline
E16: Ford E-Transit | F16: Cargo, delivery, work van | G16: 68705 | H16: 68 kWh | J16: Ford Escape | K16: 36954 | L16: 1013 | M16: Gasoline
B18: 4. Select vehicles & charger to perform TCO with | E18: 5. Operational inputs | G18: Default values | I18: 6. Financing inputs | L18: Default values
B19: Select EV: | C19: Chevrolet Silverado EV LT E4WD | E19: Province | F19: ON | I19: ICE vehicle down payment as % of MSRP | K19: 0.05 | L19: 0.05
B20: Select charger: | C20: L2 7.2kW | E20: Annual vehicle KM's travelled | F20: 30000 | G20: 30000 | I20: ICE vehicle loan interest rate (APR) | K20: 0.07 | L20: 0.07
B21: Select ICE vehicle: | C21: Ford F-150 | E21: How many EV vehicles can share one charger? | F21: 1 | G21: 2 | I21: ICE vehicle loan term (years) | K21: 7 | L21: 7
I22: EV down payment as % of MSRP | K22: 0.05 | L22: 0.05
I23: EV loan interest rate | K23: 0.07 | L23: 0.07
I24: EV loan term (years) | K24: 7 | L24: 7
B26: 7. Optional manual overrides
C27: ICE | D27: Override | E27: EV | F27: Override
B28: Annual Maintenance costs | C28: 0 | D28: FALSE | E28: 0 | F28: FALSE
B29: Vehicle purchase price | C29: 0 | D29: FALSE | E29: 0 | F29: FALSE | H29: Add: | J29: Notes for shares charging hub
B30: Fuel/ energy costs ($/L , $/kWh) | C30: 0 | D30: FALSE | E30: 0 | F30: FALSE | H30: km's travelled | J30: % of charging that will be done by charging hub | K30: reduce energy cost and infrastructure by %
B31: Charger infrastructure cost | C31: 0 | D31: FALSE | E31: 0 | F31: FALSE | H31: $kWh | J31: Reduced charger to truck ratios. A lower number of chargers per unit of kWh. A benefit of economies of scale
B32: Additional Vehicle Rebate | C32: 0 | D32: FALSE | E32: 0 | F32: FALSE | H32: CFR price ranges | J32: Leasing scenario needs to be built
B33: Additional Charging Infrastructure Rebate | C33: 0 | D33: FALSE | E33: 0 | F33: FALSE | J33: Also need to acknowledge that depot infrastructure will
B36: Scenario 1: Purchase Upfront
P38: Average Cost per KM - ICE
P39: ='Cost analysis - purchase'!P12/('TCO Dashboard'!F20*10) -> 0.56165841
P40: Average Cost per KM - EV
P41: ='Cost analysis - purchase'!AC12/('TCO Dashboard'!F20*10) -> 0.48312364
P42: Total Savings- 7 years
P43: ='Cost analysis - purchase'!P12-'Cost analysis - purchase'!AC12 -> 23560.431
Q48: ICE | R48: EV
P49: Average daily km | Q49: =C7 -> 200 | R49: =C7 -> 200
P50: Average Annual km | Q50: =F20 -> 30000 | R50: =F20 -> 30000
P52: Vehicle cost (MSRP) | Q52: ='Cost analysis - purchase'!B6 -> 54000 | R52: ='Cost analysis - purchase'!B7 -> 95833
P53: Available funding for vehicle | Q53: ='Cost analysis - purchase'!B51 -> 0 | R53: ='Cost analysis - purchase'!B50 -> 10000
P54: Annual Insurance | Q54: ='Cost analysis - purchase'!O4 -> 1620 | R54: ='Cost analysis - purchase'!AB4 -> 3833.32
P55: Residual Value | Q55: ='Cost analysis - purchase'!N30 -> -18838.618 | R55: ='Cost analysis - purchase'!AC30 -> -33432.617
P56: Vehicle Cost Year 1 | Q56: =Q52-Q53+Q54 -> 55620 | R56: =R52-R53+R54 -> 89666.32
P58: EV charger Cost | Q58: 0 | R58: ='Cost analysis - purchase'!B37*'Cost analysis - purchase'!B38 -> 15214.072
P59: Available funding for charging infrastructure | Q59: 0 | R59: ='Cost analysis - purchase'!B52 -> 0
P60: EV charger annual maintenance (% of total costs) | Q60: 0 | R60: 4
P61: Residual Value | Q61: 0 | R61: ='Cost analysis - purchase'!AA12 -> -1521.4323
P62: Charger Infrastructure Cost Year 1 | Q62: 0 | R62: =R58-R59 -> 15214.072
P64: Energy cost ($/l) / ($/kWh): | Q64: ='Cost analysis - purchase'!B9 -> 1.459 | R64: ='Cost analysis - purchase'!B10 -> 0.1784
P65: Consumption (l/km) / (kWh/km) | Q65: ='Cost analysis - purchase'!B20 -> 0.119 | R65: 0.4
P66: Annual consumption (l) / (kWh): | Q66: =Q65*Q50 -> 3570 | R66: =R65*R50 -> 12000
P67: Energy Cost Year 1 | Q67: =Q64*Q66 -> 5208.63 | R67: =R66*R64 -> 2140.8
P69: Maintenance & Tires Cost ($/km) | Q69: ='Cost analysis - purchase'!B14 -> 0.35 | R69: ='Cost analysis - purchase'!B15 -> 0.18
P70: Maintenance & Tires cost year 1 | Q70: =Q69*Q50 -> 10500 | R70: =R69*R50 -> 5400
P72: Charger utilization (hrs/day) | R72: 6
P73: CFR credit value ($/ credit) | R73: 120
P74: LCFS & plugin BC credits (Only BC) | R74: ='Cost analysis - purchase'!B43 -> 0
P75: LCFS/CFR Revenue Year 1 | Q75: 0 | R75: ='Cost analysis - purchase'!U4 -> -1820.3388
P77: Total Vehicle Cost | Q77: =SUM('Cost analysis - purchase'!I12+'Cost analysis - purchase'!M12+'Cost analysis - purchase'!O12) -> 48028.837 | R77: =SUM('Cost analysis - purchase'!S12+'Cost analysis - purchase'!Z12+'Cost analysis - purchase'!AB12,'Cost analysis - purchase'!T12) -> 81944.376
P78: Total Energy Cost | Q78: =SUM('Cost analysis - purchase'!J12) -> 42408.709 | R78: =SUM('Cost analysis - purchase'!V12) -> 12630.925
P79: Total charging Infrastructure Installation + maintenance Cost | Q79: 0 | R79: =SUM('Cost analysis - purchase'!X12,'Cost analysis - purchase'!Y12)+'Cost analysis - purchase'!AA12 -> 17973.999
P80: Total Vehicle Maintenance & Tires Cost | Q80: =SUM('Cost analysis - purchase'!L12) -> 78059.976 | R80: ='Cost analysis - purchase'!W12 -> 40145.13
P81: Total Credit Revenues | Q81: 0 | R81: =SUM('Cost analysis - purchase'!U12) -> -7757.3392
P82: Total Cost of Ownership | Q82: =SUM(Q77:Q81) -> 168497.52 | R82: =SUM(R77:R81) -> 144937.09
B88: Scenario 2: Finance Vehicles + Purchase chargers upfront
P90: Average Cost per KM - ICE
P91: ='Cost analysis - purchase'!Q30/('TCO Dashboard'!F20*10) -> 0.60235814
P92: Average Cost per KM - EV
P93: ='Cost analysis - purchase'!AF30/('TCO Dashboard'!F20*10) -> 0.54642669
P94: Total Savings - 7 years
P95: ='Cost analysis - purchase'!Q30-'Cost analysis - purchase'!AF30 -> 16779.437
Q97: ICE | R97: EV
P98: Average daily km | Q98: =C7 -> 200 | R98: =C7 -> 200
P99: Average Annual km | Q99: =F20 -> 30000 | R99: =F20 -> 30000
P101: Vehicle cost (MSRP) | Q101: ='Cost analysis - purchase'!B6 -> 54000 | R101: ='Cost analysis - purchase'!B7 -> 95833
P102: Down Payment | Q102: ='Cost analysis - purchase'!I22 -> 2700 | R102: ='Cost analysis - purchase'!T22 -> 4791.65
P103: Monthly Payments | Q103: ='Cost analysis - purchase'!J22/12 -> 774.25448 | R103: ='Cost analysis - purchase'!U22/12 -> 1223.1312
P104: Available funding for vehicle | Q104: ='Cost analysis - purchase'!B51 -> 0 | R104: ='Cost analysis - purchase'!B50 -> 10000
P105: Annual Insurance | Q105: ='Cost analysis - purchase'!O4 -> 1620 | R105: ='Cost analysis - purchase'!AB4 -> 3833.32
P106: Residual Value | Q106: ='Cost analysis - purchase'!N30 -> -18838.618 | R106: ='Cost analysis - purchase'!AC30 -> -33432.617
P107: Vehicle Cost Year 1 | Q107: =Q102+Q105+(Q103*12) -> 13611.054 | R107: =R102+R105+(R103*12) -> 23302.544
P109: EV charger Cost | Q109: 0 | R109: ='Cost analysis - purchase'!B37*'Cost analysis - purchase'!B38 -> 15214.072
P110: Available funding for charging infrastructure | Q110: 0 | R110: ='Cost analysis - purchase'!B52 -> 0
P111: EV charger annual maintenance (% of total costs) | Q111: 0 | R111: ='Cost analysis - purchase'!B17 -> 0.04
P112: Residual Value | Q112: 0 | R112: ='Cost analysis - purchase'!AD30 -> -1521.4323
P113: Charger Infrastructure Cost Year 1 | Q113: 0 | R113: =R109-R110+(R111*R109) -> 15822.634
P115: Energy cost ($/l) / ($/kWh): | Q115: ='Cost analysis - purchase'!B9 -> 1.459 | R115: ='Cost analysis - purchase'!B10 -> 0.1784
P116: Consumption (l/km) / (kWh/km) | Q116: ='Cost analysis - purchase'!B20 -> 0.119 | R116: ='Cost analysis - purchase'!B19 -> 0.308
P117: Annual consumption (l) / (kWh): | Q117: =Q116*Q99 -> 3570 | R117: =R116*R99 -> 9240
P118: Energy Cost Year 1 | Q118: =Q115*Q117 -> 5208.63 | R118: =R117*R115 -> 1648.416
P120: Maintenance & Tires Cost ($/km) | Q120: ='Cost analysis - purchase'!B14 -> 0.35 | R120: ='Cost analysis - purchase'!B15 -> 0.18
P121: Maintenance & Tires cost year 1 | Q121: =Q120*Q99 -> 10500 | R121: =R120*R99 -> 5400
P123: Charger utilization (hrs/day) | R123: 6
P124: CFR credit value ($/ credit) | R124: 120
P125: LCFS & plugin BC credits (Only BC) | R125: ='Cost analysis - purchase'!B43 -> 0
P126: LCFS/CFR Revenue Year 1 | Q126: 0 | R126: ='Cost analysis - purchase'!W22 -> -1820.3388
P128: Total Vehicle Cost | Q128: =SUM('Cost analysis - purchase'!I30,'Cost analysis - purchase'!J30,'Cost analysis - purchase'!N30,'Cost analysis - purchase'!P30) -> 60238.758 | R128: =SUM('Cost analysis - purchase'!T30,'Cost analysis - purchase'!U30,'Cost analysis - purchase'!AC30,'Cost analysis - purchase'!AE30) -> 100935.29
P129: Total Energy Cost | Q129: =SUM('Cost analysis - purchase'!K30) -> 42408.709 | R129: ='Cost analysis - purchase'!X30 -> 12630.925
P130: Total charging Infrastructure Installation + maintenance Cost | Q130: 0 | R130: =SUM('Cost analysis - purchase'!Z30,'Cost analysis - purchase'!AB30)+'Cost analysis - purchase'!AD30 -> 17973.999
P131: Total Vehicle Maintenance & Tires Cost | Q131: ='Cost analysis - purchase'!M30 -> 78059.976 | R131: ='Cost analysis - purchase'!Y30 -> 40145.13
...

Sheet Cost analysis - purchase
A1: Present value | B1: Value | C1: Unit | D1: Source | E1: Notes | F1: From input tab | H1: Scenario 1: Purchase Upfront
A2: Discount rate | B2: =0.04 -> 0.04 | C2: % | D2: Input | E2: - | F2: calculated data | H2: Year | I2: ICE - Purchase cost | J2: ICE - Fuel cost | K2: ICE - Carbon tax | L2: ICE - Tires & Maintenance cost | M2: ICE - salvage value | O2: ICE - vehicle insurance | P2: ICE - Total cost | Q2: ICE - Cumulative Total Cost | R2: ICE- depreciation | S2: EV - Purchase cost | T2: EV - Vehicle + chargers Total rebate | U2: EV - CFR/LCFS | V2: EV - Charging cost | W2: EV - Tires & Maintenance Cost | X2: EV - Charging infrastructure cost | Y2: EV - Charger infrastructure maintenance | Z2: EV - Salvage value | AA2: EV - Charger Salvage value | AB2: EV- vehicle insurance | AC2: EV -Total cost | AD2: EV - Cumulative Total Cost | AE2: EV - depreciation | AF2: Chargers - depreciation | AG2: Discount Factor | AH2: Cumulative Savings | AI2: ICE -Total discounted cost | AJ2: EV - Total discounted cost
H3: 0 | J3: 0 | L3: 0 | P3: =SUM(I3:O3) -> 0 | Q3: =P3 -> 0 | R3: 0 | V3: 0 | W3: 0 | AC3: =SUM(S3:AB3) -> 0 | AD3: =AC3 -> 0 | AE3: 0 | AF3: 0 | AH3: =MAX(Q3-AD3,0) -> 0 | AI3: =AG3*P3 -> 0 | AJ3: =AG3*AC3 -> 0
H4: 1 | I4: =B6 -> 54000 | J4: =(B$20*B$21)*B$9 -> 5208.63 | K4: =B20*B21*B40 -> 0 | L4: =B14*B21 -> 10500 | O4: =B55*B6 -> 1620 | P4: =SUM(I4:O4) -> 71328.63 | Q4: =Q3+P4 -> 71328.63 | R4: =($I$4-SUM($R$3:R3))*B$25 -> 8100 | S4: =B7 -> 95833 | T4: =-(B50+B52) -> -10000 | U4: =-B41-B43 -> -1820.3388 | V4: =(B$19*B$10)*B$21 -> 1648.416 | W4: =B$15*B$21 -> 5400 | X4: =B37*B38 -> 15214.072 | Y4: =X4*B17 -> 608.56286 | AB4: =B7*B54 -> 3833.32 | AC4: =SUM(S4:AB4) -> 110717.03 | AD4: =AC4 -> 110717.03 | AE4: =($S$4)*B$26 -> 14374.95 | AF4: =0.5*($B$37)*IF('TCO Dashboard'!C20 = 'Charger database'!A6,B$28,B$27) -> 2282.1107 | AG4: =1/(1+$B$2)^H4 -> 0.96153846 | AH4: =MAX(Q4-AD4,0) -> 0 | AI4: =AG4*P4 -> 68585.221 | AJ4: =AG4*AC4 -> 106458.68
A5: Purchase prices | B5: Value | C5: Unit | D5: Source | E5: Notes | H5: 2 | I5: 0 | J5: =J4*(1+B$11) -> 5469.0615 | K5: =B20*B21*B40 -> 0 | L5: =L4*(1+B$16) -> 10710 | O5: =B55*B6 -> 1620 | P5: =SUM(I5:O5) -> 17799.061 | Q5: =Q4+P5 -> 89127.692 | R5: =($I$4-SUM($R$3:R4))*B$25 -> 6885 | S5: 0 | T5: 0 | U5: =U4-(U4*B$48) -> -1674.7117 | V5: =V4*(1+B$12) -> 1697.8685 | W5: =W4*(1+B$16) -> 5508 | X5: 0 | Y5: =Y4+(1.02) -> 609.58286 | AB5: =B7*B54 -> 3833.32 | AC5: =SUM(S5:AB5) -> 9974.0596 | AD5: =AD4+AC5 -> 120691.09 | AE5: =($S$4-SUM($AE$4:AE4))*B$26 -> 12218.708 | AF5: =($B$37-SUM($AF4:AF$4))*IF('TCO Dashboard'!C$20 = 'Charger database'!A$6,B$28,B$27) -> 3879.5883 | AG5: =1/(1+$B$2)^H5 -> 0.92455621 | AH5: =MAX(Q5-AD5,0) -> 0 | AI5: =AG5*P5 -> 16456.233 | AJ5: =AG5*AC5 -> 9221.5788
A6: Chosen ICE vehicle MSRP | B6: =IF('TCO Dashboard'!D29 = TRUE, 'TCO Dashboard'!C29,_xlfn.XLOOKUP('TCO Dashboard'!C21,ICE_DB[Make + Model],ICE_DB[Purchase price ($ CAD)])) -> 54000 | C6: $ (CAD) | D6: ICE database | E6: - | H6: 3 | I6: 0 | J6: =J5*(1+B$11) -> 5742.5146 | K6: =B20*B21*B40 -> 0 | L6: =L5*(1+B$16) -> 10924.2 | O6: =B55*B6 -> 1620 | P6: =SUM(I6:O6) -> 18286.715 | Q6: =Q5+P6 -> 107414.41 | R6: =($I$4-SUM($R$3:R5))*B$25 -> 5852.25 | S6: 0 | T6: 0 | U6: =U5-(U5*B$48) -> -1540.7348 | V6: =V5*(1+B$12) -> 1748.8045 | W6: =W5*(1+B$16) -> 5618.16 | X6: 0 | Y6: =Y5+(1.02) -> 610.60286 | AB6: =B7*B54 -> 3833.32 | AC6: =SUM(S6:AB6) -> 10270.153 | AD6: =AD5+AC6 -> 130961.24 | AE6: =($S$4-SUM($AE$4:AE5))*B$26 -> 10385.901 | AF6: =($B$37-SUM($AF$4:AF5))*IF('TCO Dashboard'!C$20 = 'Charger database'!A$6,B$28,B$27) -> 2715.7118 | AG6: =1/(1+$B$2)^H6 -> 0.88899636 | AH6: =MAX(Q6-AD6,0) -> 0 | AI6: =AG6*P6 -> 16256.823 | AJ6: =AG6*AC6 -> 9130.1283
A7: Chosen EV MSRP | B7: =IF('TCO Dashboard'!F29 = TRUE, 'TCO Dashboard'!E29,_xlfn.XLOOKUP('TCO Dashboard'!C19,EV_DB[Make & Model],EV_DB[Cost, $MSRP CAD])) -> 95833 | C7: $(CAD) | D7: EV database | E7: - | H7: 4 | I7: 0 | J7: =J6*(1+B$11) -> 6029.6403 | K7: =B20*B21*B40 -> 0 | L7: =L6*(1+B$16) -> 11142.684 | O7: =B55*B6 -> 1620 | P7: =SUM(I7:O7) -> 18792.324 | Q7: =Q6+P7 -> 126206.73 | R7: =($I$4-SUM($R$3:R6))*B$25 -> 4974.4125 | S7: 0 | T7: 0 | U7: =U6-(U6*B$48) -> -1417.476 | V7: =V6*(1+B$12) -> 1801.2687 | W7: =W6*(1+B$16) -> 5730.5232 | X7: 0 | Y7: =Y6+(1.02) -> 611.62286 | AB7: =B7*B54 -> 3833.32 | AC7: =SUM(S7:AB7) -> 10559.259 | AD7: =AD6+AC7 -> 141520.5 | AE7: =($S$4-SUM($AE$4:AE6))*B$26 -> 8828.0162 | AF7: =($B$37-SUM($AF$4:AF6))*IF('TCO Dashboard'!C$20 = 'Charger database'!A$6,B$28,B$27) -> 1900.9982 | AG7: =1/(1+$B$2)^H7 -> 0.85480419 | AH7: =MAX(Q7-AD7,0) -> 0 | AI7: =AG7*P7 -> 16063.758 | AJ7: =AG7*AC7 -> 9026.0986
A8: Fuel + electricity rates | B8: Value | C8: Unit | D8: Source | E8: Notes | H8: 5 | I8: 0 | J8: =J7*(1+B$11) -> 6331.1223 | K8: =B20*B21*B40 -> 0 | L8: =L7*(1+B$16) -> 11365.538 | O8: =B55*B6 -> 1620 | P8: =SUM(I8:O8) -> 19316.66 | Q8: =Q7+P8 -> 145523.39 | R8: =($I$4-SUM($R$3:R7))*B$25 -> 4228.2506 | S8: 0 | T8: 0 | U8: =U7-(U7*B$48) -> -1304.0779 | V8: =V7*(1+B$12) -> 1855.3067 | W8: =W7*(1+B$16) -> 5845.1337 | X8: 0 | Y8: =Y7+(1.02) -> 612.64286 | AB8: =B7*B54 -> 3833.32 | AC8: =SUM(S8:AB8) -> 10842.325 | AD8: =AD7+AC8 -> 152362.83 | AE8: =($S$4-SUM($AE$4:AE7))*B$26 -> 7503.8137 | AF8: =($B$37-SUM($AF$4:AF7))*IF('TCO Dashboard'!C$20 = 'Charger database'!A$6,B$28,B$27) -> 1330.6988 | AG8: =1/(1+$B$2)^H8 -> 0.82192711 | AH8: =MAX(Q8-AD8,0) -> 0 | AI8: =AG8*P8 -> 15876.886 | AJ8: =AG8*AC8 -> 8911.6011
A9: Diesel/ petrol cost ($/L) | B9: 1.459 | C9: $/L | E9: - | H9: 6 | I9: 0 | J9: =J8*(1+B$11) -> 6647.6784 | K9: =B20*B21*B40 -> 0 | L9: =L8*(1+B$16) -> 11592.848 | O9: =B55*B6 -> 1620 | P9: =SUM(I9:O9) -> 19860.527 | Q9: =Q8+P9 -> 165383.92 | R9: =($I$4-SUM($R$3:R8))*B$25 -> 3594.013 | S9: 0 | T9: 0 | U9: 0 | V9: =V8*(1+B$12) -> 1910.9659 | W9: =W8*(1+B$16) -> 5962.0363 | X9: 0 | Y9: =Y8+(1.02) -> 613.66286 | AB9: =B7*B54 -> 3833.32 | AC9: =SUM(S9:AB9) -> 12319.985 | AD9: =AD8+AC9 -> 164682.81 | AE9: =($S$4-SUM($AE$4:AE8))*B$26 -> 6378.2417 | AF9: =($B$37-SUM($AF$4:AF8))*IF('TCO Dashboard'!C$20 = 'Charger database'!A$6,B$28,B$27) -> 931.48914 | AG9: =1/(1+$B$2)^H9 -> 0.79031453 | AH9: =MAX(Q9-AD9,0) -> 701.10406 | AI9: =AG9*P9 -> 15696.063 | AJ9: =AG9*AC9 -> 9736.6632
A10: Energy charge($/kWh) | B10: =IF( 'TCO Dashboard'!F30 = TRUE, 'TCO Dashboard'!E30,_xlfn.XLOOKUP('TCO Dashboard'!F19,Fuelcosts_DB[Province],Fuelcosts_DB[Cost of electricity ($/kWh)])) -> 0.1784 | C10: $/kWh | D10: General Service Business Rates | E10: " - Revisit this cost | H10: 7 | I10: 0 | J10: =J9*(1+B$11) -> 6980.0624 | K10: =B20*B21*B40 -> 0 | L10: =L9*(1+B$16) -> 11824.705 | O10: =B55*B6 -> 1620 | P10: =SUM(I10:O10) -> 20424.768 | Q10: =Q9+P10 -> 185808.69 | R10: =($I$4-SUM($R$3:R9))*B$25 -> 3054.9111 | S10: 0 | T10: 0 | U10: 0 | V10: =V9*(1+B$12) -> 1968.2949 | W10: =W9*(1+B$16) -> 6081.2771 | X10: 0 | Y10: =Y9+(1.02) -> 614.68286 | AB10: =B7*B54 -> 3833.32 | AC10: =SUM(S10:AB10) -> 12497.575 | AD10: =AD9+AC10 -> 177180.39 | AE10: =($S$4-SUM($AE$4:AE9))*B$26 -> 5421.5054 | AF10: =($B$37-SUM($AF$4:AF9))*IF('TCO Dashboard'!C$20 = 'Charger database'!A$6,B$28,B$27) -> 652.0424 | AG10: =1/(1+$B$2)^H10 -> 0.75991781 | AH10: =MAX(Q10-AD10,0) -> 8628.297 | AI10: =AG10*P10 -> 15521.145 | AJ10: =AG10*AC10 -> 9497.1297
A11: Diesel/ Petrol annual price escalation | B11: =0.03+0.02 -> 0.05 | C11: % | D11: Up to 350 per cent higher at the pump by 2030: The impact of higher carbon taxes on gasoline prices - Canadian Energy Centre | E11: - Calculated the CAGR of 300% increase in 10 years | H11: Salvage year | M11: =-(I4-SUM(R3:R10)) -> -17311.163 | P11: =SUM(I11:O11) -> -17311.163 | Q11: =Q10+P11 -> 168497.52 | Z11: =-(S4-SUM(AE4:AE10)) -> -30721.864 | AA11: =-(B37-SUM(AF4:AF10)) -> -1521.4323 | AC11: =SUM(S11:AB11) -> -32243.296 | AD11: =AD10+AC11 -> 144937.09 | AG11: =1/(1+$B$2)^8 -> 0.73069021 | AH11: =MAX(Q11-AD11,0) -> 23560.431 | AI11: =AG11*P11 -> -12649.097 | AJ11: =AG11*AC11 -> -23559.861
A12: Energy annual price escalation | B12: 0.03 | C12: % | D12: BC Gov News | H12: Total Cost | I12: =SUM(I4:I11) -> 54000 | J12: =SUM(J3:J11) -> 42408.709 | K12: =SUM(K3:K11) -> 0 | L12: =SUM(L3:L11) -> 78059.976 | M12: =SUM(M3:M11) -> -17311.163 | O12: =SUM(O3:O11) -> 11340 | P12: =SUM(P3:P11) -> 168497.52 | R12: =SUM(R3:R11) -> 36688.837 | S12: =SUM(S4:S11) -> 95833 | T12: =SUM(T4:T11) -> -10000 | U12: =SUM(U3:U11) -> -7757.3392 | V12: =SUM(V3:V11) -> 12630.925 | W12: =SUM(W3:W11) -> 40145.13 | X12: =SUM(X4:X11) -> 15214.072 | Y12: =SUM(Y3:Y11) -> 4281.36 | Z12: =SUM(Z3:Z11) -> -30721.864 | AA12: =SUM(AA3:AA11) -> -1521.4323 | AB12: =SUM(AB3:AB11) -> 26833.24 | AC12: =SUM(AC3:AC11) -> 144937.09 | AE12: =SUM(AE3:AE11) -> 65111.136 | AF12: =SUM(AF3:AF11) -> 13692.639
A13: Maintenance costs | B13: Value | C13: Unit | D13: Source | E13: Notes | H13: Total PV cost | I13: =SUMPRODUCT(I4:I11,$AG3:$AG11) -> #VALUE! | J13: =SUMPRODUCT(J3:J11,$AG3:$AG11) -> 36085.741 | K13: =SUMPRODUCT(K3:K11,$AG3:$AG11) -> 0 | L13: =SUMPRODUCT(L3:L11,$AG3:$AG11) -> 66723.982 | M13: =SUMPRODUCT(M3:M11,$AG3:$AG11) -> -12649.097 | O13: =SUMPRODUCT(O3:O11,$AG3:$AG11) -> 9723.3286 | P13: =SUMPRODUCT(P3:P11,$AG3:$AG11) -> 151807.03 | R13: =SUMPRODUCT(R3:R11,$AG3:$AG11) -> 32246.005 | S13: =SUMPRODUCT(S4:S11,$AG3:$AG11) -> #VALUE! | T13: =SUMPRODUCT(T4:T11,$AG3:$AG11) -> #VALUE! | U13: =SUMPRODUCT(U3:U11,$AG3:$AG11) -> -6951.9199 | V13: =SUMPRODUCT(V3:V11,$AG3:$AG11) -> 10780.137 | W13: =SUMPRODUCT(W3:W11,$AG3:$AG11) -> 34315.191 | X13: =SUMPRODUCT(X4:X11,$AG4:$AG11) -> 14628.915 | Y13: =SUMPRODUCT(Y3:Y11,$AG3:$AG11) -> 3670.0346 | Z13: =SUMPRODUCT(Z3:Z11,$AG3:$AG11) -> -22448.165 | AB13: =SUMPRODUCT(AB3:AB11,$AG3:$AG11) -> 23007.796 | AC13: =SUMPRODUCT(AC3:AC11,$AG3:$AG11) -> 138422.02 | AE13: =SUMPRODUCT(AE3:AE11,$AG3:$AG11) -> 57226.506 | AF13: =SUMPRODUCT(AF3:AF11,$AG3:$AG11) -> 12145.879 | AI13: =SUM(AI3:AI11) -> 151807.03 | AJ13: =SUM(AJ3:AJ11) -> 138422.02
A14: ICE maintenance costs | B14: =IF('TCO Dashboard'!D28 = TRUE,('TCO Dashboard'!C28/'TCO Dashboard'!F20),_xlfn.XLOOKUP('TCO Dashboard'!C21,ICE_DB[Make + Model],ICE_DB[Maintenance cost ($/km)])) -> 0.35 | C14: $/km | D14: internal estimate | E14: -
A15: EV maintenance cost | B15: =IF('TCO Dashboard'!F28 = TRUE, ('TCO Dashboard'!E28/'TCO Dashboard'!F20),_xlfn.XLOOKUP('TCO Dashboard'!C19,EV_DB[Make & Model],EV_DB[Maintenance cost ($/km)])) -> 0.18 | C15: $/km | D15: EV database | E15: -
A16: Maintenance costs escalation | B16: 0.02 | C16: % | D16: Internal estimate | E16: -
A17: Charging infastructure maintenance costs | B17: 0.04 | C17: % | D17: internal estimate
A18: Vehicle efficiency & Duty cycle | B18: Value | C18: Unit | D18: Source | E18: Notes
A19: EV efficiency | B19: =_xlfn.XLOOKUP('TCO Dashboard'!C19,EV_DB[Make & Model],EV_DB[Efficiency (kwh/km)]) -> 0.308 | C19: kWh/km | D19: EV database | E19: - | H19: Scenario 2: Finance vehicles + Purchase chargers upfront
A20: ICE efficiency (L/km) | B20: =_xlfn.XLOOKUP('TCO Dashboard'!C21,ICE_DB[Make + Model],ICE_DB[Efficiency (L/KM)]) -> 0.119 | C20: L/km | D20: ICE database | E20: - | H20: Year | I20: ICE - Down payment | J20: ICE - Annualized monthly payments | K20: ICE - Fuel cost | L20: ICE - Carbon tax | M20: ICE - Tires & Maintenance cost | N20: ICE - salvage value | P20: ICE - vehicle insurance | Q20: ICE - Total cost | R20: ICE - Cumulative Total Cost | S20: ICE- depreciation | T20: EV - Down Payment | U20: EV - Annualized monthly payments | V20: EV - Vehicle Rebate | W20: EV - CFR/LCFS | X20: EV - Charging cost | Y20: EV - Tires & Maintenance Cost | Z20: EV - Charging infrastructure cost | AA20: EV - Charging infrastructure Rebate | AB20: EV - Charger infrastructure maintenance | AC20: EV - Salvage value | AD20: EV - Charger Salvage value | AE20: EV- vehicle insurance | AF20: EV -Total cost | AG20: EV - Cumulative Total Cost | AH20: EV - depreciation | AI20: Chargers - depreciation | AJ20: Discount Factor | AK20: ICE -Total discounted cost | AL20: EV - Total discounted cost | AM20: Cumulative Savings
A21: Annual vehicle KM travelled | B21: =IF(ISBLANK('TCO Dashboard'!F20), 10000,'TCO Dashboard'!F20) -> 30000 | C21: km | D21: Input | E21: - | H21: 0 | K21: 0 | M21: 0 | Q21: =SUM(I21:P21) -> 0 | R21: =Q21 -> 0 | S21: 0 | X21: 0 | Y21: 0 | AA21: =-B52 -> 0 | AF21: =SUM(T21:AE21) -> 0 | AG21: =AF21 -> 0 | AH21: 0 | AI21: 0 | AJ21: =1 -> 1 | AK21: =AJ21*Q21 -> 0 | AL21: =AJ21*AF21 -> 0 | AM21: =MAX(R21-AG21,0) -> 0
A22: Average lifespan | B22: 10 | C22: years | D22: Don't forget the little guys - Truck News | E22: - | H22: 1 | I22: =B30*B6 -> 2700 | J22: =PMT((B31/12),(B32*12),-(B6-(B6*B30)))*12 -> 9291.0538 | K22: =(B$20*B$21)*B$9 -> 5208.63 | L22: =B20*B21*B40 -> 0 | M22: =B14*B21 -> 10500 | P22: =B55*B6 -> 1620 | Q22: =SUM(I22:P22) -> 29319.684 | R22: =R21+Q22 -> 29319.684 | S22: =($B$6-SUM($S$21:S21))*B$25*0.5 -> 4050 | T22: =B33*B7 -> 4791.65 | U22: =PMT((B34/12),(B35*12),-(B7-(B7*B33)-B$50))*12 -> 14677.574 | V22: =-B50 -> -10000 | W22: =-B41-B43 -> -1820.3388 | X22: =(B$19*B$10)*B$21 -> 1648.416 | Y22: =B$15*B$21 -> 5400 | Z22: =B37*B38 -> 15214.072 | AA22: 0 | AB22: =Z22*B17 -> 608.56286 | AE22: =B7*B54 -> 3833.32 | AF22: =SUM(T22:AE22)-V22 -> 44353.256 | AG22: =AG21+AF22 -> 44353.256 | AH22: =($B$7-SUM($AH$21:AH21))*B$26*0.5 -> 7187.475 | AI22: =0.5*($B$37)*IF('TCO Dashboard'!C20 = 'Charger database'!A6,B$28,B$27) -> 2282.1107 | AJ22: =1/(1+$B$2)^H22 -> 0.96153846 | AK22: =AJ22*Q22 -> 28192.004 | AL22: =AJ22*AF22 -> 42647.361 | AM22: =MAX(R22-AG22,0) -> 0
A23: operational days/ year | B23: 260 | C23: days | D23: Input | E23: - | H23: 2 | J23: =PMT((B31/12),(B32*12),-(B6-(B6*B30)))*12 -> 9291.0538 | K23: =K22*(1+B$11) -> 5469.0615 | L23: =B20*B21*B40 -> 0 | M23: =M22*(1+B$16) -> 10710 | P23: =B55*B6 -> 1620 | Q23: =SUM(I23:P23) -> 27090.115 | R23: =R22+Q23 -> 56409.799 | S23: =($B$6-SUM($S$21:S22))*B$25 -> 7492.5 | T23: 0 | U23: =PMT((B34/12),(B35*12),-(B7-(B7*B33)-B$50))*12 -> 14677.574 | V23: 0 | W23: =W22-(W22*B$48) -> -1674.7117 | X23: =X22*(1+B$12) -> 1697.8685 | Y23: =Y22*(1+B$16) -> 5508 | Z23: 0 | AA23: 0 | AB23: =AB22+(1.02) -> 609.58286 | AE23: =B7*B54 -> 3833.32 | AF23: =SUM(T23:AE23) -> 24651.634 | AG23: =AG22+AF23 -> 69004.889 | AH23: =($B$7-SUM($AH$21:AH22))*B$26 -> 13296.829 | AI23: =($B$37-SUM($AI22:AI$22))*IF('TCO Dashboard'!C$20 = 'Charger database'!A$6,B$28,B$27) -> 3879.5883 | AJ23: =1/(1+$B$2)^H23 -> 0.92455621 | AK23: =AJ23*Q23 -> 25046.334 | AL23: =AJ23*AF23 -> 22791.821 | AM23: =MAX(R23-AG23,0) -> 0
A24: Depreciation rates | B24: Value | C24: Unit | D24: Source | E24: Notes | H24: 3 | J24: =PMT((B31/12),(B32*12),-(B6-(B6*B30)))*12 -> 9291.0538 | K24: =K23*(1+B$11) -> 5742.5146 | L24: =B20*B21*B40 -> 0 | M24: =M23*(1+B$16) -> 10924.2 | P24: =B55*B6 -> 1620 | Q24: =SUM(I24:P24) -> 27577.768 | R24: =R23+Q24 -> 83987.567 | S24: =($B$6-SUM($S$21:S23))*B$25 -> 6368.625 | T24: 0 | U24: =PMT((B34/12),(B35*12),-(B7-(B7*B33)-B$50))*12 -> 14677.574 | V24: 0 | W24: =W23-(W23*B$48) -> -1540.7348 | X24: =X23*(1+B$12) -> 1748.8045 | Y24: =Y23*(1+B$16) -> 5618.16 | Z24: 0 | AA24: 0 | AB24: =AB23+(1.02) -> 610.60286 | AE24: =B7*B54 -> 3833.32 | AF24: =SUM(T24:AE24) -> 24947.727 | AG24: =AG23+AF24 -> 93952.616 | AH24: =($B$7-SUM($AH$21:AH23))*B$26 -> 11302.304 | AI24: =($B$37-SUM($AI$22:AI23))*IF('TCO Dashboard'!C$20 = 'Charger database'!A$6,B$28,B$27) -> 2715.7118 | AJ24: =1/(1+$B$2)^H24 -> 0.88899636 | AK24: =AJ24*Q24 -> 24516.536 | AL24: =AJ24*AF24 -> 22178.438 | AM24: =MAX(R24-AG24,0) -> 0
A25: ICE annual declining depreciation rate | B25: =0.15 -> 0.15 | C25: % | D25: Estimation | E25: Low mileage used compared to other trucks, 260 operational days out of a year | H25: 4 | J25: =PMT((B31/12),(B32*12),-(B6-(B6*B30)))*12 -> 9291.0538 | K25: =K24*(1+B$11) -> 6029.6403 | L25: =B20*B21*B40 -> 0 | M25: =M24*(1+B$16) -> 11142.684 | P25: =B55*B6 -> 1620 | Q25: =SUM(I25:P25) -> 28083.378 | R25: =R24+Q25 -> 112070.95 | S25: =($B$6-SUM($S$21:S24))*B$25 -> 5413.3313 | T25: 0 | U25: =PMT((B34/12),(B35*12),-(B7-(B7*B33)-B$50))*12 -> 14677.574 | V25: 0 | W25: =W24-(W24*B$48) -> -1417.476 | X25: =X24*(1+B$12) -> 1801.2687 | Y25: =Y24*(1+B$16) -> 5730.5232 | Z25: 0 | AA25: 0 | AB25: =AB24+(1.02) -> 611.62286 | AE25: =B7*B54 -> 3833.32 | AF25: =SUM(T25:AE25) -> 25236.833 | AG25: =AG24+AF25 -> 119189.45 | AH25: =($B$7-SUM($AH$21:AH24))*B$26 -> 9606.9588 | AI25: =($B$37-SUM($AI$22:AI24))*IF('TCO Dashboard'!C$20 = 'Charger database'!A$6,B$28,B$27) -> 1900.9982 | AJ25: =1/(1+$B$2)^H25 -> 0.85480419 | AK25: =AJ25*Q25 -> 24005.789 | AL25: =AJ25*AF25 -> 21572.55 | AM25: =MAX(R25-AG25,0) -> 0
A26: EV annual declining depreciation rate | B26: 0.15 | C26: % | D26: Estimation | E26: Low mileage, less strain on the battery than expected | H26: 5 | J26: =PMT((B31/12),(B32*12),-(B6-(B6*B30)))*12 -> 9291.0538 | K26: =K25*(1+B$11) -> 6331.1223 | L26: =B20*B21*B40 -> 0 | M26: =M25*(1+B$16) -> 11365.538 | P26: =B55*B6 -> 1620 | Q26: =SUM(I26:P26) -> 28607.714 | R26: =R25+Q26 -> 140678.66 | S26: =($B$6-SUM($S$21:S25))*B$25 -> 4601.3316 | T26: 0 | U26: =PMT((B34/12),(B35*12),-(B7-(B7*B33)-B$50))*12 -> 14677.574 | V26: 0 | W26: =W25-(W25*B$48) -> -1304.0779 | X26: =X25*(1+B$12) -> 1855.3067 | Y26: =Y25*(1+B$16) -> 5845.1337 | Z26: 0 | AA26: 0 | AB26: =AB25+(1.02) -> 612.64286 | AE26: =B7*B54 -> 3833.32 | AF26: =SUM(T26:AE26) -> 25519.899 | AG26: =AG25+AF26 -> 144709.35 | AH26: =($B$7-SUM($AH$21:AH25))*B$26 -> 8165.915 | AI26: =($B$37-SUM($AI$22:AI25))*IF('TCO Dashboard'!C$20 = 'Charger database'!A$6,B$28,B$27) -> 1330.6988 | AJ26: =1/(1+$B$2)^H26 -> 0.82192711 | AK26: =AJ26*Q26 -> 23513.455 | AL26: =AJ26*AF26 -> 20975.497 | AM26: =MAX(R26-AG26,0) -> 0
A27: Class 43.1 CCA Chargers annual declining depreciation rate | B27: 0.3 | C27: % | D27: Estimation | E27: Capital Cost Allowance (CCA) and CCA Classes | H27: 6 | J27: =PMT((B31/12),(B32*12),-(B6-(B6*B30)))*12 -> 9291.0538 | K27: =K26*(1+B$11) -> 6647.6784 | L27: =B20*B21*B40 -> 0 | M27: =M26*(1+B$16) -> 11592.848 | P27: =B55*B6 -> 1620 | Q27: =SUM(I27:P27) -> 29151.581 | R27: =R26+Q27 -> 169830.24 | S27: =($B$6-SUM($S$21:S26))*B$25 -> 3911.1318 | T27: 0 | U27: =PMT((B34/12),(B35*12),-(B7-(B7*B33)-B$50))*12 -> 14677.574 | V27: 0 | W27: 0 | X27: =X26*(1+B$12) -> 1910.9659 | Y27: =Y26*(1+B$16) -> 5962.0363 | Z27: 0 | AA27: 0 | AB27: =AB26+(1.02) -> 613.66286 | AE27: =B7*B54 -> 3833.32 | AF27: =SUM(T27:AE27) -> 26997.559 | AG27: =AG26+AF27 -> 171706.91 | AH27: =($B$7-SUM($AH$21:AH26))*B$26 -> 6941.0277 | AI27: =($B$37-SUM($AI$22:AI26))*IF('TCO Dashboard'!C$20 = 'Charger database'!A$6,B$28,B$27) -> 931.48914 | AJ27: =1/(1+$B$2)^H27 -> 0.79031453 | AK27: =AJ27*Q27 -> 23038.918 | AL27: =AJ27*AF27 -> 21336.563 | AM27: =MAX(R27-AG27,0) -> 0
A28: Class 43.2 CCA Chargers annual declining depreciation rate | B28: 0.5 | C28: % | D28: Estimation | E28: https://www.csagroup.org/standards/areas-of-focus/fuels-transportation/standards-for-battery-electric-vehicles-and-energy-management/ | H28: 7 | J28: =PMT((B31/12),(B32*12),-(B6-(B6*B30)))*12 -> 9291.0538 | K28: =K27*(1+B$11) -> 6980.0624 | L28: =B20*B21*B40 -> 0 | M28: =M27*(1+B$16) -> 11824.705 | P28: =B55*B6 -> 1620 | Q28: =SUM(I28:P28) -> 29715.822 | R28: =R27+Q28 -> 199546.06 | S28: =($B$6-SUM($S$21:S27))*B$25 -> 3324.4621 | T28: 0 | U28: =PMT((B34/12),(B35*12),-(B7-(B7*B33)-B$50))*12 -> 14677.574 | V28: 0 | W28: 0 | X28: =X27*(1+B$12) -> 1968.2949 | Y28: =Y27*(1+B$16) -> 6081.2771 | Z28: 0 | AA28: 0 | AB28: =AB27+(1.02) -> 614.68286 | AE28: =B7*B54 -> 3833.32 | AF28: =SUM(T28:AE28) -> 27175.149 | AG28: =AG27+AF28 -> 198882.06 | AH28: =($B$7-SUM($AH$21:AH27))*B$26 -> 5899.8736 | AI28: =($B$37-SUM($AI$22:AI27))*IF('TCO Dashboard'!C$20 = 'Charger database'!A$6,B$28,B$27) -> 652.0424 | AJ28: =1/(1+$B$2)^H28 -> 0.75991781 | AK28: =AJ28*Q28 -> 22581.582 | AL28: =AJ28*AF28 -> 20650.88 | AM28: =MAX(R28-AG28,0) -> 664.00605
A29: Financing terms | B29: Value | C29: Unit | D29: Source | E29: Notes | H29: Salvage year | N29: =-(B6-SUM(S21:S28)) -> -18838.618 | Q29: =SUM(I29:P29) -> -18838.618 | R29: =R28+Q29 -> 180707.44 | AC29: =-(B7-SUM(AH22:AH28)) -> -33432.617 | AD29: =-(B37-SUM(AI22:AI28)) -> -1521.4323 | AF29: =SUM(T29:AE29) -> -34954.049 | AG29: =AG28+AF29 -> 163928.01 | AJ29: =1/(1+$B$2)^11 -> 0.64958093 | AK29: =AJ29*Q29 -> -12237.207 | AL29: =AJ29*AF29 -> -22705.484 | AM29: =MAX(R29-AG29,0) -> 16779.437
A30: ICE vehicle down payment as % of MSRP | B30: ='TCO Dashboard'!K19 -> 0.05 | C30: % | E30: - | H30: Total Cost | I30: =SUM(I22:I29) -> 2700 | J30: =SUM(J21:J29) -> 65037.377 | K30: =SUM(K21:K29) -> 42408.709 | L30: =SUM(L21:L29) -> 0 | M30: =SUM(M21:M29) -> 78059.976 | N30: =SUM(N21:N29) -> -18838.618 | P30: =SUM(P21:P29) -> 11340 | Q30: =SUM(Q21:Q29) -> 180707.44 | S30: =SUM(S21:S29) -> 35161.382 | T30: =SUM(T22:T29) -> 4791.65 | U30: =SUM(U21:U29) -> 102743.02 | V30: =SUM(V22:V29) -> -10000 | W30: =SUM(W21:W29) -> -7757.3392 | X30: =SUM(X21:X29) -> 12630.925 | Y30: =SUM(Y21:Y29) -> 40145.13 | Z30: =SUM(Z22:Z29) -> 15214.072 | AA30: =SUM(AA21:AA29) -> 0 | AB30: =SUM(AB21:AB29) -> 4281.36 | AC30: =SUM(AC21:AC29) -> -33432.617 | AD30: =SUM(AD21:AD29) -> -1521.4323 | AE30: =SUM(AE21:AE29) -> 26833.24 | AF30: =SUM(AF21:AF29) -> 163928.01 | AH30: =SUM(AH21:AH29) -> 62400.383 | AI30: =SUM(AI21:AI29) -> 13692.639
A31: ICE vehicle loan interest rate | B31: ='TCO Dashboard'!K20 -> 0.07 | C31: % | E31: - | H31: Total PV cost | I31: =SUMPRODUCT(I22:I29,$AJ21:$AJ29) -> #VALUE! | J31: =SUMPRODUCT(J21:J29,$AJ21:$AJ29) -> 55765.413 | K31: =SUMPRODUCT(K21:K29,$AJ21:$AJ29) -> 36085.741 | L31: =SUMPRODUCT(L21:L29,$AJ21:$AJ29) -> 0 | M31: =SUMPRODUCT(M21:M29,$AJ21:$AJ29) -> 66723.982 | N31: =SUMPRODUCT(N21:N29,$AJ21:$AJ29) -> -12237.207 | P31: =SUMPRODUCT(P21:P29,$AJ21:$AJ29) -> 9723.3286 | Q31: =SUMPRODUCT(Q21:Q29,$AJ21:$AJ29) -> 158657.41 | S31: =SUMPRODUCT(S21:S29,$AJ21:$AJ29) -> 30509.792 | T31: =SUMPRODUCT(T22:T29,$AJ21:$AJ29) -> #VALUE! | U31: =SUMPRODUCT(U21:U29,$AJ21:$AJ29) -> 88095.601 | V31: =SUMPRODUCT(V22:V29,$AJ21:$AJ29) -> #VALUE! | W31: =SUMPRODUCT(W21:W29,$AJ21:$AJ29) -> -6951.9199 | X31: =SUMPRODUCT(X21:X29,$AJ21:$AJ29) -> 10780.137 | Y31: =SUMPRODUCT(Y21:Y29,$AJ21:$AJ29) -> 34315.191 | Z31: =SUMPRODUCT(Z22:Z29,$AJ21:$AJ29) -> #VALUE! | AA31: =SUMPRODUCT(AA21:AA29,$AJ21:$AJ29) -> 0 | AB31: =SUMPRODUCT(AB21:AB29,$AJ21:$AJ29) -> 3670.0346 | AC31: =SUMPRODUCT(AC21:AC29,$AJ21:$AJ29) -> -21717.19 | AE31: =SUMPRODUCT(AE21:AE29,$AJ21:$AJ29) -> 23007.796 | AF31: =SUMPRODUCT(AF21:AF29,$AJ21:$AJ29) -> 149447.63 | AH31: =SUMPRODUCT(AH21:AH29,$AJ21:$AJ29) -> 54145.276 | AI31: =SUMPRODUCT(AI21:AI29,$AJ21:$AJ29) -> 12145.879 | AK31: =SUM(AK21:AK29) -> 158657.41 | AL31: =SUM(AL21:AL29) -> 149447.63
A32: ICE vehicle loan term (years) | B32: ='TCO Dashboard'!K21 -> 7 | C32: years
A33: EV down payment as % of MSRP | B33: ='TCO Dashboard'!K22 -> 0.05 | C33: % | E33: -
A34: EV loan interest rate | B34: ='TCO Dashboard'!K23 -> 0.07 | C34: % | E34: -
A35: EV loan term (years) | B35: ='TCO Dashboard'!K24 -> 7 | C35: years
A36: Charging Infrastructure | B36: Value | C36: Unit | D36: Source | E36: Notes | H36: Scenario 3: Finance Vehicles + Charging as a service
A37: Charging station hardware+ installation cost | B37: =IF('TCO Dashboard'!F31=TRUE, 'TCO Dashboard'!E31,_xlfn.XLOOKUP('TCO Dashboard'!C20,Charger_DB[Charger type],Charger_DB[Purchase + installation cost$ CAD])) -> 15214.072 | C37: $(CAD)/ charger | D37: Internal costing | E37: - | H37: Year | I37: ICE - Down payment | J37: ICE - Annualized monthly payments | K37: ICE - Fuel cost | L37: ICE - Carbon tax | M37: ICE - Tires & Maintenance cost | N37: ICE - salvage value | P37: ICE - vehicle insurance | Q37: ICE - Total cost | R37: ICE - Cumulative Total Cost | S37: ICE- depreciation | T37: EV - Down Payment | U37: EV - Annualized monthly payments | V37: EV - Vehicle Rebate | W37: EV - CFR/LCFS | X37: EV - Charging cost | Y37: EV - Tires & Maintenance Cost | Z37: EV - Charging as a service | AA37: EV - Charging Infrastructure Rebate | AC37: EV - Vehicle Salvage value | AD37: EV - Charger Salvage value | AE37: EV- vehicle insurance | AF37: EV -Total cost | AG37: EV - Cumulative Total Cost | AH37: EV - depreciation | AI37: Chargers - depreciation | AJ37: Discount Factor | AK37: ICE -Total discounted cost | AL37: EV - Total discounted cost | AM37: Cumulative Savings
A38: Charger cost assignment | B38: =1/'TCO Dashboard'!F21 -> 1 | C38: % | D38: Decided value | E38: " one charger will serve X trucks" | H38: 0 | K38: 0 | M38: 0 | Q38: =SUM(I38:P38) -> 0 | R38: =Q38 -> 0 | S38: 0 | X38: 0 | Y38: 0 | AF38: =SUM(T38:AE38) -> 0 | AG38: =AF38 -> 0 | AH38: 0 | AI38: 0 | AJ38: =1 -> 1 | AK38: =AJ38*Q38 -> 0 | AL38: =AJ38*AF38 -> 0 | AM38: =MAX(R38-AG38,0) -> 0
A39: Taxes & Credits | B39: Value | C39: Unit | D39: Source | E39: Notes | H39: 1 | I39: =B30*B6 -> 2700 | J39: =PMT((B31/12),(B32*12),-(B6-(B6*B30)))*12 -> 9291.0538 | K39: =(B$20*B$21)*B$9 -> 5208.63 | L39: =B20*B21*B40 -> 0 | M39: =B14*B21 -> 10500 | P39: =B55*B6 -> 1620 | Q39: =SUM(I39:P39) -> 29319.684 | R39: =R38+Q39 -> 29319.684 | S39: =($B$6-SUM($S$38:S38))*B$25 -> 8100 | T39: =B33*B7 -> 4791.65 | U39: =PMT((B34/12),(B35*12),-(B7-(B7*B33)-B$50))*12 -> 14677.574 | V39: =-B50 -> -10000 | W39: =-B41-B43 -> -1820.3388 | X39: =(B$19*B$10)*B$21 -> 1648.416 | Y39: =B$15*B$21 -> 5400 | Z39: =(((B37*B38)-B52)*1.8)/7 -> 3912.1898 | AA39: =-B52 -> 0 | AE39: =B7*B54 -> 3833.32 | AF39: =SUM(T39:AE39)-V39-AA39 -> 32442.811 | AG39: =AG38+AF39 -> 32442.811 | AH39: =($B$7-SUM($AH$38:AH38))*B$26*0.5 -> 7187.475 | AI39: =0.5*($B$37)*IF('TCO Dashboard'!C20 = 'Charger database'!A$6,B$28,B$27) -> 2282.1107 | AJ39: =1/(1+$B$2)^H39 -> 0.96153846 | AK39: =AJ39*Q39 -> 28192.004 | AL39: =AJ39*AF39 -> 31195.011 | AM39: =MAX(R39-AG39,0) -> 0
A40: Carbon tax | B40: 0 | C40: $/L | D40: Carbon tax rates by fuel type - Province of British Columbia | E40: - | H40: 2 | J40: =PMT((B31/12),(B32*12),-(B6-(B6*B30)))*12 -> 9291.0538 | K40: =K39*(1+B$11) -> 5469.0615 | L40: =B20*B21*B40 -> 0 | M40: =M39*(1+B$16) -> 10710 | P40: =B55*B6 -> 1620 | Q40: =SUM(I40:P40) -> 27090.115 | R40: =R39+Q40 -> 56409.799 | S40: =($B$6-SUM($S$38:S39))*B$25 -> 6885 | T40: 0 | U40: =PMT((B34/12),(B35*12),-(B7-(B7*B33)-B$50))*12 -> 14677.574 | W40: =W39-(W39*B$48) -> -1674.7117 | X40: =X39*(1+B$12) -> 1697.8685 | Y40: =Y39*(1+B$16) -> 5508 | Z40: =(((B37*B38)-B52)*1.8)/7 -> 3912.1898 | AE40: =B7*B54 -> 3833.32 | AF40: =SUM(T40:AE40) -> 27954.241 | AG40: =AG39+AF40 -> 60397.052 | AH40: =($B$7-SUM($AH$38:AH39))*B$26 -> 13296.829 | AI40: =($B$37-SUM($AI$39:AI39))*IF('TCO Dashboard'!C$20 = 'Charger database'!A$6,B$28,B$27) -> 3879.5883 | AJ40: =1/(1+$B$2)^H40 -> 0.92455621 | AK40: =AJ40*Q40 -> 25046.334 | AL40: =AJ40*AF40 -> 25845.267 | AM40: =MAX(R40-AG40,0) -> 0
A41: CFR credits annual value | B41: {=IF(OR( _xlfn.XLOOKUP('TCO Dashboard'!C19,EV_DB[Make & Model],EV_DB[Category],"not found")="light duty", _xlfn.XLOOKUP('TCO Dashboard'!C19,EV_DB[Make & Model],EV_DB[Category],"not found")="medium duty"), ('Cost analysis - purchase'!B21*B19)*(_xlfn.XLOOKUP(1,(CFR_DB[Vehicle type] = "Light + medium duty")*(CFR_DB[Province]='TCO Dashboard'!F19),CFR_DB[Marginal CFR $ value per kWh dispensed])), ('Cost analysis - purchase'!B21*B19)*(_xlfn.XLOOKUP(1,(CFR_DB[Vehicle type] = "Heavy duty")*(CFR_DB[Province]='TCO Dashboard'!F19),CFR_DB[Marginal CFR $ value per kWh dispensed])))} -> 1820.3388 | C41: $ | D41: Projection by trading partner | E41: CFR is expected to continue until 2030 | H41: 3 | J41: =PMT((B31/12),(B32*12),-(B6-(B6*B30)))*12 -> 9291.0538 | K41: =K40*(1+B$11) -> 5742.5146 | L41: =B20*B21*B40 -> 0 | M41: =M40*(1+B$16) -> 10924.2 | P41: =B55*B6 -> 1620 | Q41: =SUM(I41:P41) -> 27577.768 | R41: =R40+Q41 -> 83987.567 | S41: =($B$6-SUM($S$38:S40))*B$25 -> 5852.25 | T41: 0 | U41: =PMT((B34/12),(B35*12),-(B7-(B7*B33)-B$50))*12 -> 14677.574 | W41: =W40-(W40*B$48) -> -1540.7348 | X41: =X40*(1+B$12) -> 1748.8045 | Y41: =Y40*(1+B$16) -> 5618.16 | Z41: =(((B37*B38)-B52)*1.8)/7 -> 3912.1898 | AE41: =B7*B54 -> 3833.32 | AF41: =SUM(T41:AE41) -> 28249.314 | AG41: =AG40+AF41 -> 88646.365 | AH41: =($B$7-SUM($AH$38:AH40))*B$26 -> 11302.304 | AI41: =($B$37-SUM($AI$39:AI40))*IF('TCO Dashboard'!C$20 = 'Charger database'!A$6,B$28,B$27) -> 2715.7118 | AJ41: =1/(1+$B$2)^H41 -> 0.88899636 | AK41: =AJ41*Q41 -> 24516.536 | AL41: =AJ41*AF41 -> 25113.537 | AM41: =MAX(R41-AG41,0) -> 0
A42: Last year for credit programs | B42: 2030 | C42: year | H42: 4 | J42: =PMT((B31/12),(B32*12),-(B6-(B6*B30)))*12 -> 9291.0538 | K42: =K41*(1+B$11) -> 6029.6403 | L42: =B20*B21*B40 -> 0 | M42: =M41*(1+B$16) -> 11142.684 | P42: =B55*B6 -> 1620 | Q42: =SUM(I42:P42) -> 28083.378 | R42: =R41+Q42 -> 112070.95 | S42: =($B$6-SUM($S$38:S41))*B$25 -> 4974.4125 | T42: 0 | U42: =PMT((B34/12),(B35*12),-(B7-(B7*B33)-B$50))*12 -> 14677.574 | W42: =W41-(W41*B$48) -> -1417.476 | X42: =X41*(1+B$12) -> 1801.2687 | Y42: =Y41*(1+B$16) -> 5730.5232 | Z42: =(((B37*B38)-B52)*1.8)/7 -> 3912.1898 | AE42: =B7*B54 -> 3833.32 | AF42: =SUM(T42:AE42) -> 28537.4 | AG42: =AG41+AF42 -> 117183.76 | AH42: =($B$7-SUM($AH$38:AH41))*B$26 -> 9606.9588 | AI42: =($B$37-SUM($AI$39:AI41))*IF('TCO Dashboard'!C$20 = 'Charger database'!A$6,B$28,B$27) -> 1900.9982 | AJ42: =1/(1+$B$2)^H42 -> 0.85480419 | AK42: =AJ42*Q42 -> 24005.789 | AL42: =AJ42*AF42 -> 24393.889 | AM42: =MAX(R42-AG42,0) -> 0
A43: LCFS credit annual value | B43: =IF(AND('TCO Dashboard'!F19="BC",OR( _xlfn.XLOOKUP('TCO Dashboard'!C19,EV_DB[Make & Model],EV_DB[Category],"not found")="light duty", _xlfn.XLOOKUP('TCO Dashboard'!C19,EV_DB[Make & Model],EV_DB[Category],"not found")="medium duty")), ('Cost analysis - purchase'!B21*B19)*B45*B44, IF(AND('TCO Dashboard'!F19="BC", _xlfn.XLOOKUP('TCO Dashboard'!C19,EV_DB[Make & Model],EV_DB[Category],"not found")="heavy duty"),('Cost analysis - purchase'!B21*B19)*B46*B44,0)) -> 0 | C43: $ | H43: 5 | J43: =PMT((B31/12),(B32*12),-(B6-(B6*B30)))*12 -> 9291.0538 | K43: =K42*(1+B$11) -> 6331.1223 | L43: =B20*B21*B40 -> 0 | M43: =M42*(1+B$16) -> 11365.538 | P43: =B55*B6 -> 1620 | Q43: =SUM(I43:P43) -> 28607.714 | R43: =R42+Q43 -> 140678.66 | S43: =($B$6-SUM($S$38:S42))*B$25 -> 4228.2506 | T43: 0 | U43: =PMT((B34/12),(B35*12),-(B7-(B7*B33)-B$50))*12 -> 14677.574 | W43: =W42-(W42*B$48) -> -1304.0779 | X43: =X42*(1+B$12) -> 1855.3067 | Y43: =Y42*(1+B$16) -> 5845.1337 | Z43: =(((B37*B38)-B52)*1.8)/7 -> 3912.1898 | AE43: =B7*B54 -> 3833.32 | AF43: =SUM(T43:AE43) -> 28819.446 | AG43: =AG42+AF43 -> 146003.21 | AH43: =($B$7-SUM($AH$38:AH42))*B$26 -> 8165.915 | AI43: =($B$37-SUM($AI$39:AI42))*IF('TCO Dashboard'!C$20 = 'Charger database'!A$6,B$28,B$27) -> 1330.6988 | AJ43: =1/(1+$B$2)^H43 -> 0.82192711 | AK43: =AJ43*Q43 -> 23513.455 | AL43: =AJ43*AF43 -> 23687.484 | AM43: =MAX(R43-AG43,0) -> 0
A44: LCFS credit price | B44: 190 | C44: $ | H44: 6 | J44: =PMT((B31/12),(B32*12),-(B6-(B6*B30)))*12 -> 9291.0538 | K44: =K43*(1+B$11) -> 6647.6784 | L44: =B20*B21*B40 -> 0 | M44: =M43*(1+B$16) -> 11592.848 | P44: =B55*B6 -> 1620 | Q44: =SUM(I44:P44) -> 29151.581 | R44: =R43+Q44 -> 169830.24 | S44: =($B$6-SUM($S$38:S43))*B$25 -> 3594.013 | T44: 0 | U44: =PMT((B34/12),(B35*12),-(B7-(B7*B33)-B$50))*12 -> 14677.574 | W44: 0 | X44: =X43*(1+B$12) -> 1910.9659 | Y44: =Y43*(1+B$16) -> 5962.0363 | Z44: =(((B37*B38)-B52)*1.8)/7 -> 3912.1898 | AE44: =B7*B54 -> 3833.32 | AF44: =SUM(T44:AE44) -> 30296.086 | AG44: =AG43+AF44 -> 176299.3 | AH44: =($B$7-SUM($AH$38:AH43))*B$26 -> 6941.0277 | AI44: =($B$37-SUM($AI$39:AI43))*IF('TCO Dashboard'!C$20 = 'Charger database'!A$6,B$28,B$27) -> 931.48914 | AJ44: =1/(1+$B$2)^H44 -> 0.79031453 | AK44: =AJ44*Q44 -> 23038.918 | AL44: =AJ44*AF44 -> 23943.437 | AM44: =MAX(R44-AG44,0) -> 0
A45: light duty marginal kWh | B45: 0.00092 | C45: credit | H45: 7 | J45: =PMT((B31/12),(B32*12),-(B6-(B6*B30)))*12 -> 9291.0538 | K45: =K44*(1+B$11) -> 6980.0624 | L45: =B20*B21*B40 -> 0 | M45: =M44*(1+B$16) -> 11824.705 | P45: =B55*B6 -> 1620 | Q45: =SUM(I45:P45) -> 29715.822 | R45: =R44+Q45 -> 199546.06 | S45: =($B$6-SUM($S$38:S44))*B$25 -> 3054.9111 | T45: 0 | U45: =PMT((B34/12),(B35*12),-(B7-(B7*B33)-B$50))*12 -> 14677.574 | W45: 0 | X45: =X44*(1+B$12) -> 1968.2949 | Y45: =Y44*(1+B$16) -> 6081.2771 | Z45: =(((B37*B38)-B52)*1.8)/7 -> 3912.1898 | AE45: =B7*B54 -> 3833.32 | AF45: =SUM(T45:AE45) -> 30472.656 | AG45: =AG44+AF45 -> 206771.95 | AH45: =($B$7-SUM($AH$38:AH44))*B$26 -> 5899.8736 | AI45: =($B$37-SUM($AI$39:AI44))*IF('TCO Dashboard'!C$20 = 'Charger database'!A$6,B$28,B$27) -> 652.0424 | AJ45: =1/(1+$B$2)^H45 -> 0.75991781 | AK45: =AJ45*Q45 -> 22581.582 | AL45: =AJ45*AF45 -> 23156.714 | AM45: =MAX(R45-AG45,0) -> 0
A46: heavy duty marginal kWh | B46: 0.00101 | C46: credit | H46: Salvage year | N46: =-(B6-SUM(S38:S45)) -> -17311.163 | Q46: =SUM(I46:P46) -> -17311.163 | R46: =R45+Q46 -> 182234.9 | T46: 0 | W46: 0 | X46: 0 | Y46: 0 | Z46: 0 | AC46: =-(B7-SUM(AH39:AH45)) -> -33432.617 | AD46: =-(B37-SUM(AI39:AI45)) -> -1521.4323 | AF46: =SUM(T46:AE46) -> -34954.049 | AG46: =AG45+AF46 -> 171817.9 | AJ46: =1/(1+$B$2)^11 -> 0.64958093 | AK46: =AJ46*Q46 -> -11245.001 | AL46: =AJ46*AF46 -> -22705.484 | AM46: =MAX(R46-AG46,0) -> 10416.995
A47: Annual decline in LCFS price | B47: 0.08 | C47: % | H47: Total cost | I47: =SUM(I39:I46) -> 2700 | J47: =SUM(J38:J46) -> 65037.377 | K47: =SUM(K38:K46) -> 42408.709 | L47: =SUM(L38:L46) -> 0 | M47: =SUM(M38:M46) -> 78059.976 | N47: =SUM(N38:N46) -> -17311.163 | P47: =SUM(P38:P46) -> 11340 | Q47: =SUM(Q38:Q46) -> 182234.9 | S47: =SUM(S38:S46) -> 36688.837 | T47: =SUM(T39:T46) -> 4791.65 | U47: =SUM(U38:U46) -> 102743.02 | V47: =SUM(V39:V46) -> -10000 | W47: =SUM(W38:W46) -> -7757.3392 | X47: =SUM(X38:X46) -> 12630.925 | Y47: =SUM(Y38:Y46) -> 40145.13 | Z47: =SUM(Z38:Z46) -> 27385.329 | AA47: =SUM(AA39:AA46) -> 0 | AC47: =SUM(AC38:AC46) -> -33432.617 | AD47: =SUM(AD38:AD46) -> -1521.4323 | AE47: =SUM(AE38:AE46) -> 26833.24 | AF47: =SUM(AF38:AF46) -> 171817.9 | AH47: =SUM(AH38:AH46) -> 62400.383 | AI47: =SUM(AI38:AI46) -> 13692.639
A48: Annual decline in CFR price | B48: 0.08 | C48: % | H48: Total PV cost | I48: =SUMPRODUCT(I39:I46,$AJ38:$AJ46) -> #VALUE! | J48: =SUMPRODUCT(J38:J46,$AJ38:$AJ46) -> 55765.413 | K48: =SUMPRODUCT(K38:K46,$AJ38:$AJ46) -> 36085.741 | L48: =SUMPRODUCT(L38:L46,$AJ38:$AJ46) -> 0 | M48: =SUMPRODUCT(M38:M46,$AJ38:$AJ46) -> 66723.982 | N48: =SUMPRODUCT(N38:N46,$AJ38:$AJ46) -> -11245.001 | P48: =SUMPRODUCT(P38:P46,$AJ38:$AJ46) -> 9723.3286 | Q48: =SUMPRODUCT(Q38:Q46,$AJ38:$AJ46) -> 159649.62 | S48: =SUMPRODUCT(S38:S46,$AJ38:$AJ46) -> 32246.005 | T48: =SUMPRODUCT(T38:T46,$AJ38:$AJ46) -> 4607.3558 | U48: =SUMPRODUCT(U38:U46,$AJ38:$AJ46) -> 88095.601 | V48: =SUMPRODUCT(V39:V46,$AJ39:$AJ46) -> -9615.3846 | W48: =SUMPRODUCT(W38:W46,$AJ38:$AJ46) -> -6951.9199 | X48: =SUMPRODUCT(X38:X46,$AJ38:$AJ46) -> 10780.137 | Y48: =SUMPRODUCT(Y38:Y46,$AJ38:$AJ46) -> 34315.191 | Z48: =SUMPRODUCT(Z38:Z46,$AJ38:$AJ46) -> 23481.177 | AA48: =SUMPRODUCT(AA39:AA46,$AJ38:$AJ46) -> #VALUE! | AC48: =SUMPRODUCT(AC38:AC46,$AJ38:$AJ46) -> -21717.19 | AE48: =SUMPRODUCT(AE38:AE46,$AJ38:$AJ46) -> 23007.796 | AF48: =SUMPRODUCT(AF38:AF46,$AJ38:$AJ46) -> 154629.85 | AH48: =SUMPRODUCT(AH38:AH46,$AJ38:$AJ46) -> 54145.276 | AI48: =SUMPRODUCT(AI38:AI46,$AJ38:$AJ46) -> 12145.879 | AK48: =SUM(AK38:AK46) -> 159649.62 | AL48: =SUM(AL38:AL46) -> 154629.85
A49: Rebates/ incentives | B49: Value | C49: Unit | D49: Source | E49: Notes
A50: EV rebate/incentive total value | B50: {=IF('TCO Dashboard'!F32=TRUE,_xlfn.XLOOKUP('TCO Dashboard'!C19, EV_DB[Make & Model], _xlfn.XLOOKUP('TCO Dashboard'!F19 & " - Total rebate(s) value", EV_DB[#Headers], EV_DB[])+'TCO Dashboard'!E32), _xlfn.XLOOKUP('TCO Dashboard'!C19, EV_DB[Make & Model], _xlfn.XLOOKUP('TCO Dashboard'!F19 & " - Total rebate(s) value", EV_DB[#Headers], EV_DB[])))} -> 10000 | C50: $(CAD) | D50: EV database | E50: -
A51: ICE rebate/incentive total value | B51: =IF('TCO Dashboard'!D32=TRUE,'TCO Dashboard'!D32,0) -> 0 | C51: $(CAD) | D51: N/A | E51: -
A52: Charger infrastructure total incentives | B52: {=IF('TCO Dashboard'!F33=TRUE,'TCO Dashboard'!E33,IF('TCO Dashboard'!F19="BC",_xlfn.XLOOKUP(1,('TCO Dashboard'!C20=chrgrincentive_DB[Charger type])*('TCO Dashboard'!F19=chrgrincentive_DB[Province]),chrgrincentive_DB[Plugin BC]),0))} -> 0 | C52: $(CAD) | D52: Charger incentives database | E52: - | H52: Scenario 4: Lease Vehicles + Charging as a service
A53: Annual insurance | B53: Value | C53: Unit | D53: Source | E53: Notes | H53: Year | I53: ICE - Down payment | J53: ICE - Annualized monthly payments | K53: ICE - Fuel cost | L53: ICE - Carbon tax | M53: ICE - Tires & Maintenance cost | N53: ICE - salvage value | P53: ICE - vehicle insurance | Q53: ICE - Total cost | R53: ICE - Cumulative Total Cost | S53: ICE- depreciation | T53: EV - Down Payment | U53: EV - Annualized monthly payments | V53: EV - Vehicle Rebate | W53: EV - CFR/LCFS | X53: EV - Charging cost | Y53: EV - Tires & Maintenance Cost | Z53: EV - Charging as a service | AA53: EV - Charging Infrastructure Rebate | AB53: EV - Charger infrastructure maintenance | AC53: EV - Salvage value | AE53: EV- vehicle insurance | AF53: EV -Total cost | AG53: EV - Cumulative Total Cost | AH53: EV - depreciation | AI53: Discount Factor | AJ53: ICE -Total discounted cost | AK53: EV - Total discounted cost | AL53: Cumulative Savings
A54: EV insurance as % of value | B54: 0.04 | H54: 0 | K54: 0 | M54: 0 | Q54: =SUM(I54:P54) -> 0 | R54: =Q54 -> 0 | S54: 0 | X54: 0 | Y54: 0 | AF54: =SUM(T54:AE54) -> 0 | AG54: =AF54 -> 0 | AH54: 0 | AI54: =1 -> 1 | AJ54: =AI54*Q54 -> 0 | AK54: =AI54*AF54 -> 0 | AL54: =MAX(R54-AG54,0) -> 0
A55: ICE annual insurance as % of value | B55: 0.03 | H55: 1 | I55: =B30*B6 -> 2700 | J55: =PMT((B46/12),(B47*12),-(B22-(B22*B45)))*12 -> 124.8953 | K55: =(B$20*B$21)*B$9 -> 5208.63 | L55: =B38*#REF!*B56 -> #REF! | M55: =B32*#REF! -> #REF! | P55: =#REF!*B22 -> #REF! | Q55: =SUM(I55:P55) -> #REF! | R55: =R54+Q55 -> #REF! | S55: =($B$6-SUM($S$38:S54))*B$25 -> -7743.5518 | T55: =B48*B23 -> 20.8 | U55: =PMT((B49/12),(B50*12),-(B23-(B23*B48)-B$50))*12 -> #VALUE! | V55: =-B66 -> #VALUE! | W55: =-B57-B59 -> #VALUE! | X55: =(B$19*B$10)*B$21 -> 1648.416 | Y55: =B$15*B$21 -> 5400 | Z55: =(((B52*B53)-B68)*1.8)/7 -> #VALUE! | AA55: =-B68 -> #VALUE! | AB55: =(B52*B53)*B35 -> #VALUE! | AE55: =B23*#REF! -> #REF! | AF55: =SUM(T55:AE55)-V55-AA55 -> #VALUE! | AG55: =AG54+AF55 -> #VALUE! | AH55: =($B$7-SUM($AH$38:AH54))*B$26*0.5 -> -6233.4782 | AI55: =1/(1+$B$2)^H55 -> 0.96153846 | AJ55: =AI55*Q55 -> #REF! | AK55: =AI55*AF55 -> #VALUE! | AL55: =MAX(R55-AG55,0) -> #REF!
H56: 2 | J56: =PMT((B46/12),(B47*12),-(B22-(B22*B45)))*12 -> 124.8953 | K56: =K55*(1+B$11) -> 5469.0615 | L56: =B38*#REF!*B56 -> #REF! | M56: =M55*(1+B$16) -> #REF! | P56: =#REF!*B22 -> #REF! | Q56: =SUM(I56:P56) -> #REF! | R56: =R55+Q56 -> #REF! | S56: =($B$6-SUM($S$38:S55))*B$25 -> -6582.0191 | T56: 0 | U56: =PMT((B49/12),(B50*12),-(B23-(B23*B48)-B$50))*12 -> #VALUE! | W56: =W55-(W55*B$48) -> #VALUE! | X56: =X55*(1+B$12) -> 1697.8685 | Y56: =Y55*(1+B$16) -> 5508 | Z56: =(((B52*B53)-B68)*1.8)/7 -> #VALUE! | AB56: =AB55+(1.02) -> #VALUE! | AE56: =B23*#REF! -> #REF! | AF56: =SUM(T56:AE56) -> #VALUE! | AG56: =AG55+AF56 -> #VALUE! | AH56: =($B$7-SUM($AH$38:AH55))*B$26 -> -11531.935 | AI56: =1/(1+$B$2)^H56 -> 0.92455621 | AJ56: =AI56*Q56 -> #REF! | AK56: =AI56*AF56 -> #VALUE! | AL56: =MAX(R56-AG56,0) -> #REF!
A57: Assumptions | H57: 3 | J57: =PMT((B46/12),(B47*12),-(B22-(B22*B45)))*12 -> 124.8953 | K57: =K56*(1+B$11) -> 5742.5146 | L57: =B38*#REF!*B56 -> #REF! | M57: =M56*(1+B$16) -> #REF! | P57: =#REF!*B22 -> #REF! | Q57: =SUM(I57:P57) -> #REF! | R57: =R56+Q57 -> #REF! | S57: =($B$6-SUM($S$38:S56))*B$25 -> -5594.7162 | T57: 0 | U57: =PMT((B49/12),(B50*12),-(B23-(B23*B48)-B$50))*12 -> #VALUE! | W57: =W56-(W56*B$48) -> #VALUE! | X57: =X56*(1+B$12) -> 1748.8045 | Y57: =Y56*(1+B$16) -> 5618.16 | Z57: =(((B52*B53)-B68)*1.8)/7 -> #VALUE! | AB57: =AB56+(1.02) -> #VALUE! | AE57: =B23*#REF! -> #REF! | AF57: =SUM(T57:AE57) -> #VALUE! | AG57: =AG56+AF57 -> #VALUE! | AH57: =($B$7-SUM($AH$38:AH56))*B$26 -> -9802.1445 | AI57: =1/(1+$B$2)^H57 -> 0.88899636 | AJ57: =AI57*Q57 -> #REF! | AK57: =AI57*AF57 -> #VALUE! | AL57: =MAX(R57-AG57,0) -> #REF!
A58: Energy Costs | B58: Commercial medium duty power consumers | H58: 4 | J58: =PMT((B46/12),(B47*12),-(B22-(B22*B45)))*12 -> 124.8953 | K58: =K57*(1+B$11) -> 6029.6403 | L58: =B38*#REF!*B56 -> #REF! | M58: =M57*(1+B$16) -> #REF! | P58: =#REF!*B22 -> #REF! | Q58: =SUM(I58:P58) -> #REF! | R58: =R57+Q58 -> #REF! | S58: =($B$6-SUM($S$38:S57))*B$25 -> -4755.5088 | T58: 0 | U58: =PMT((B49/12),(B50*12),-(B23-(B23*B48)-B$50))*12 -> #VALUE! | W58: =W57-(W57*B$48) -> #VALUE! | X58: =X57*(1+B$12) -> 1801.2687 | Y58: =Y57*(1+B$16) -> 5730.5232 | Z58: =(((B52*B53)-B68)*1.8)/7 -> #VALUE! | AB58: =AB57+(1.02) -> #VALUE! | AE58: =B23*#REF! -> #REF! | AF58: =SUM(T58:AE58) -> #VALUE! | AG58: =AG57+AF58 -> #VALUE! | AH58: =($B$7-SUM($AH$38:AH57))*B$26 -> -8331.8228 | AI58: =1/(1+$B$2)^H58 -> 0.85480419 | AJ58: =AI58*Q58 -> #REF! | AK58: =AI58*AF58 -> #VALUE! | AL58: =MAX(R58-AG58,0) -> #REF!
B59: Prices per province | H59: 5 | J59: =PMT((B46/12),(B47*12),-(B22-(B22*B45)))*12 -> 124.8953 | K59: =K58*(1+B$11) -> 6331.1223 | L59: =B38*#REF!*B56 -> #REF! | M59: =M58*(1+B$16) -> #REF! | P59: =#REF!*B22 -> #REF! | Q59: =SUM(I59:P59) -> #REF! | R59: =R58+Q59 -> #REF! | S59: =($B$6-SUM($S$38:S58))*B$25 -> -4042.1825 | T59: 0 | U59: =PMT((B49/12),(B50*12),-(B23-(B23*B48)-B$50))*12 -> #VALUE! | W59: =W58-(W58*B$48) -> #VALUE! | X59: =X58*(1+B$12) -> 1855.3067 | Y59: =Y58*(1+B$16) -> 5845.1337 | Z59: =(((B52*B53)-B68)*1.8)/7 -> #VALUE! | AB59: =AB58+(1.02) -> #VALUE! | AE59: =B23*#REF! -> #REF! | AF59: =SUM(T59:AE59) -> #VALUE! | AG59: =AG58+AF59 -> #VALUE! | AH59: =($B$7-SUM($AH$38:AH58))*B$26 -> -7082.0494 | AI59: =1/(1+$B$2)^H59 -> 0.82192711 | AJ59: =AI59*Q59 -> #REF! | AK59: =AI59*AF59 -> #VALUE! | AL59: =MAX(R59-AG59,0) -> #REF!
A60: CFR Credits | B60: Assumes 6 hour charger utilization | H60: 6 | J60: =PMT((B46/12),(B47*12),-(B22-(B22*B45)))*12 -> 124.8953 | K60: =K59*(1+B$11) -> 6647.6784 | L60: =B38*#REF!*B56 -> #REF! | M60: =M59*(1+B$16) -> #REF! | P60: =#REF!*B22 -> #REF! | Q60: =SUM(I60:P60) -> #REF! | R60: =R59+Q60 -> #REF! | S60: =($B$6-SUM($S$38:S59))*B$25 -> -3435.8551 | T60: 0 | U60: =PMT((B49/12),(B50*12),-(B23-(B23*B48)-B$50))*12 -> #VALUE! | W60: 0 | X60: =X59*(1+B$12) -> 1910.9659 | Y60: =Y59*(1+B$16) -> 5962.0363 | Z60: =(((B52*B53)-B68)*1.8)/7 -> #VALUE! | AB60: =AB59+(1.02) -> #VALUE! | AE60: =B23*#REF! -> #REF! | AF60: =SUM(T60:AE60) -> #VALUE! | AG60: =AG59+AF60 -> #VALUE! | AH60: =($B$7-SUM($AH$38:AH59))*B$26 -> -6019.742 | AI60: =1/(1+$B$2)^H60 -> 0.79031453 | AJ60: =AI60*Q60 -> #REF! | AK60: =AI60*AF60 -> #VALUE! | AL60: =MAX(R60-AG60,0) -> #REF!
B61: L2 - charger Power 7.2kW | H61: 7 | J61: =PMT((B46/12),(B47*12),-(B22-(B22*B45)))*12 -> 124.8953 | K61: =K60*(1+B$11) -> 6980.0624 | L61: =B38*#REF!*B56 -> #REF! | M61: =M60*(1+B$16) -> #REF! | P61: =#REF!*B22 -> #REF! | Q61: =SUM(I61:P61) -> #REF! | R61: =R60+Q61 -> #REF! | S61: =($B$6-SUM($S$38:S60))*B$25 -> -2920.4768 | T61: 0 | U61: =PMT((B49/12),(B50*12),-(B23-(B23*B48)-B$50))*12 -> #VALUE! | W61: 0 | X61: =X60*(1+B$12) -> 1968.2949 | Y61: =Y60*(1+B$16) -> 6081.2771 | Z61: =(((B52*B53)-B68)*1.8)/7 -> #VALUE! | AB61: =AB60+(1.02) -> #VALUE! | AE61: =B23*#REF! -> #REF! | AF61: =SUM(T61:AE61) -> #VALUE! | AG61: =AG60+AF61 -> #VALUE! | AH61: =($B$7-SUM($AH$38:AH60))*B$26 -> -5116.7807 | AI61: =1/(1+$B$2)^H61 -> 0.75991781 | AJ61: =AI61*Q61 -> #REF! | AK61: =AI61*AF61 -> #VALUE! | AL61: =MAX(R61-AG61,0) -> #REF!
B62: L3 - low power DCFC 24kW | H62: Salvage year | N62: =-(B22-SUM(S54:S61)) -> -35084.31 | Q62: =SUM(I62:P62) -> -35084.31 | R62: =R61+Q62 -> #REF! | T62: 0 | W62: 0 | X62: 0 | Y62: 0 | Z62: 0 | AB62: 0 | AC62: =-(B23-SUM(AH55:AH61)) -> -54377.952 | AF62: =SUM(T62:AE62) -> -54377.952 | AG62: =AG61+AF62 -> #VALUE! | AI62: =1/(1+$B$2)^11 -> 0.64958093 | AJ62: =AI62*Q62 -> -22790.099 | AK62: =AI62*AF62 -> -35322.881 | AL62: =MAX(R62-AG62,0) -> #REF!
B63: L3 - high power DCFC - 150kw | H63: Total cost | I63: =SUM(I55:I62) -> 2700 | J63: =SUM(J54:J62) -> 874.26711 | K63: =SUM(K54:K62) -> 42408.709 | L63: =SUM(L54:L62) -> #REF! | M63: =SUM(M54:M62) -> #REF! | N63: =SUM(N54:N62) -> -35084.31 | P63: =SUM(P54:P62) -> #REF! | Q63: =SUM(Q54:Q62) -> #REF! | S63: =SUM(S54:S62) -> -35074.31 | T63: =SUM(T55:T62) -> 20.8 | U63: =SUM(U54:U62) -> #VALUE! | V63: =SUM(V55:V62) -> #VALUE! | W63: =SUM(W54:W62) -> #VALUE! | X63: =SUM(X54:X62) -> 12630.925 | Y63: =SUM(Y54:Y62) -> 40145.13 | Z63: =SUM(Z54:Z62) -> #VALUE! | AA63: =SUM(AA55:AA62) -> #VALUE! | AB63: =SUM(AB54:AB62) -> #VALUE! | AC63: =SUM(AC54:AC62) -> -54377.952 | AE63: =SUM(AE54:AE62) -> #REF! | AF63: =SUM(AF54:AF62) -> #VALUE! | AH63: =SUM(AH54:AH62) -> -54117.952
B64: Assumes $100/credit | H64: Total PV cost | I64: =SUMPRODUCT(I55:I62,$AI54:$AI62) -> #VALUE! | J64: =SUMPRODUCT(J54:J62,$AI54:$AI62) -> 749.62842 | K64: =SUMPRODUCT(K54:K62,$AI54:$AI62) -> 36085.741 | L64: =SUMPRODUCT(L54:L62,$AI54:$AI62) -> #REF! | M64: =SUMPRODUCT(M54:M62,$AI54:$AI62) -> #REF! | N64: =SUMPRODUCT(N54:N62,$AI54:$AI62) -> -22790.099 | P64: =SUMPRODUCT(P54:P62,$AI54:$AI62) -> #REF! | Q64: =SUMPRODUCT(Q54:Q62,$AI54:$AI62) -> #REF! | S64: =SUMPRODUCT(S54:S62,$AI54:$AI62) -> -30826.989 | T64: =SUMPRODUCT(T54:T62,$AI54:$AI62) -> 20 | U64: =SUMPRODUCT(U54:U62,$AI54:$AI62) -> #VALUE! | V64: =SUMPRODUCT(V55:V62,$AI55:$AI62) -> #VALUE! | W64: =SUMPRODUCT(W54:W62,$AI54:$AI62) -> #VALUE! | X64: =SUMPRODUCT(X54:X62,$AI54:$AI62) -> 10780.137 | Y64: =SUMPRODUCT(Y54:Y62,$AI54:$AI62) -> 34315.191 | Z64: =SUMPRODUCT(Z54:Z62,$AI54:$AI62) -> #VALUE! | AA64: =SUMPRODUCT(AA55:AA62,$AI54:$AI62) -> #VALUE! | AB64: =SUMPRODUCT(AB54:AB62,$AI54:$AI62) -> #VALUE! | AC64: =SUMPRODUCT(AC54:AC62,$AI54:$AI62) -> -35322.881 | AE64: =SUMPRODUCT(AE54:AE62,$AI54:$AI62) -> #REF! | AF64: =SUMPRODUCT(AF54:AF62,$AI54:$AI62) -> #VALUE! | AH64: =SUMPRODUCT(AH54:AH62,$AI54:$AI62) -> -46958.549 | AJ64: =SUM(AJ54:AJ62) -> #REF! | AK64: =SUM(AK54:AK62) -> #VALUE!
B65: Assumed 365 days of operation
A66: LCFS | B66: Assumes 1:1 charger ratio
B67: Calculated based on average driven distances in regional transportation
B68: Assumes $190/credit
A69: Fuel Efficiency | B69: Based on average efficiency between highway and city driving

Sheet EV database
A1: Manufacturer | B1: Model | C1: Make & Model | D1: Type/Use Case | E1: Model Year | F1: FHWA Class (2B - 8) | G1: Category | H1: GVWR, lbs. (Gross Vehicle Weight Rating) | I1: Max Payload, lbs. | J1: Cost, $MSRP CAD | K1: Maintenance cost ($/km) | L1: Refrigerated Unit | M1: Battery Size, kWh | N1: Efficiency (kwh/km) | O1: Max Charge Rate, kw | P1: Battery Voltage (V) | Q1: Range (km) | R1: Federal Rebates (iMHZEV) | S1: ON Vehicle Rebates | T1: BC Vehicle Rebates | U1: QC Vehicle Rebates | V1: AB Vehicle Rebates | W1: SC Vehicle Rebates | X1: NS Vehicle Rebates | Y1: NB Vehicle Rebates | Z1: MB Vehicle Rebates | AA1: PEI Vehicle Rebates | AB1: NL Vehicle Rebates | AC1: YT Vehicle Rebates | AD1: NU Vehicle Rebates | AE1: NT Vehicle Rebates | AF1: ON - Total rebate(s) value | AG1: BC - Total rebate(s) value | AH1: QC - Total rebate(s) value | AI1: AB - Total rebate(s) value | AJ1: SC - Total rebate(s) value | AK1: NS - Total rebate(s) value | AL1: NB - Total rebate(s) value | AM1: MB - Total rebate(s) value | AN1: PEI - Total rebate(s) value | AO1: NL - Total rebate(s) value | AP1: YT - Total rebate(s) value | AQ1: NU - Total rebate(s) value | AR1: NT - Total rebate(s) value
A2: Ram | B2: Electric 1500 Large Battery | C2: =EV_DB[[#This Row],[Manufacturer ]]& " " &EV_DB[[#This Row],[Model]] -> Ram Electric 1500 Large Battery | D2: Pick-up truck | E2: 2025 | F2: 2B | G2: {=_xlfn.IFS(OR(EV_DB[[#This Row],[FHWA Class (2B - 8)]]= "2B", EV_DB[[#This Row],[FHWA Class (2B - 8)]]=3), "Light Duty",OR(EV_DB[[#This Row],[FHWA Class (2B - 8)]]=4,EV_DB[[#This Row],[FHWA Class (2B - 8)]]=5,EV_DB[[#This Row],[FHWA Class (2B - 8)]]=6),"Medium Duty",OR(EV_DB[[#This Row],[FHWA Class (2B - 8)]]=7,EV_DB[[#This Row],[FHWA Class (2B - 8)]]=8), "Heavy Duty")} -> Light Duty | H2: 7,800 | I2: 1700 | J2: 81085 | K2: {=_xlfn.IFS(EV_DB[[#This Row],[Category]]="Light Duty",'Maintenance costs table'!$D$4,EV_DB[[#This Row],[Category]]="Medium Duty",'Maintenance costs table'!$D$8,EV_DB[[#This Row],[Category]]="Heavy Duty",'Maintenance costs table'!$D$6)} -> 0.18 | L2: No | M2: 229kwh | N2: 0.29 | Q2: 800 | R2: {=_xlfn.IFS(EV_DB[[#This Row],[Battery Size, kWh]]>350 & EV_DB[[#This Row],[FHWA Class (2B - 8)]]=8,'iMHZEV table'!$D$4,EV_DB[[#This Row],[Battery Size, kWh]]<=350 & EV_DB[[#This Row],[FHWA Class (2B - 8)]]=8,'iMHZEV table'!$D$5, TRUE, _xlfn.XLOOKUP(EV_DB[[#This Row],[FHWA Class (2B - 8)]],'iMHZEV table'!$A$3:$A$11,'iMHZEV table'!$D$3:$D$11))} -> 10000 | T2: {=_xlfn.IFS(EV_DB[[#This Row],[FHWA Class (2B - 8)]]= "2B",10000,EV_DB[[#This Row],[FHWA Class (2B - 8)]]=3,55000,OR(EV_DB[[#This Row],[FHWA Class (2B - 8)]]=4,EV_DB[[#This Row],[FHWA Class (2B - 8)]]=5), 75000,OR(EV_DB[[#This Row],[FHWA Class (2B - 8)]]=6,EV_DB[[#This Row],[FHWA Class (2B - 8)]]=7),100000,EV_DB[[#This Row],[FHWA Class (2B - 8)]]=8, 150000)} -> 10000 | AF2: =MIN(MAX(EV_DB[[#This Row],[Federal Rebates (iMHZEV) ]],EV_DB[[#This Row],[ON Vehicle Rebates]]),PRODUCT(EV_DB[[#This Row],[Cost, $MSRP CAD]],0.75)) -> 10000 | AG2: =MIN(EV_DB[[#This Row],[Federal Rebates (iMHZEV) ]]+EV_DB[[#This Row],[BC Vehicle Rebates]],PRODUCT(EV_DB[[#This Row],[Cost, $MSRP CAD]],0.75)) -> 20000 | AH2: =MIN(EV_DB[[#This Row],[Federal Rebates (iMHZEV) ]]+EV_DB[[#This Row],[QC Vehicle Rebates]],PRODUCT(EV_DB[[#This Row],[Cost, $MSRP CAD]],0.75)) -> 10000 | AI2: =MIN(MAX(EV_DB[[#This Row],[Federal Rebates (iMHZEV) ]],EV_DB[[#This Row],[AB Vehicle Rebates]]),PRODUCT(EV_DB[[#This Row],[Cost, $MSRP CAD]],0.75)) -> 10000 | AJ2: =MIN(MAX(EV_DB[[#This Row],[Federal Rebates (iMHZEV) ]],EV_DB[[#This Row],[SC Vehicle Rebates]]),PRODUCT(EV_DB[[#This Row],[Cost, $MSRP CAD]],0.75)) -> 10000 | AK2: =MIN(MAX(EV_DB[[#This Row],[Federal Rebates (iMHZEV) ]],EV_DB[[#This Row],[NS Vehicle Rebates]]),PRODUCT(EV_DB[[#This Row],[Cost, $MSRP CAD]],0.75)) -> 10000 | AL2: =MIN(MAX(EV_DB[[#This Row],[Federal Rebates (iMHZEV) ]],EV_DB[[#This Row],[NB Vehicle Rebates]]),PRODUCT(EV_DB[[#This Row],[Cost, $MSRP CAD]],0.75)) -> 10000 | AM2: =MIN(MAX(EV_DB[[#This Row],[Federal Rebates (iMHZEV) ]],EV_DB[[#This Row],[MB Vehicle Rebates]]),PRODUCT(EV_DB[[#This Row],[Cost, $MSRP CAD]],0.75)) -> 10000 | AN2: =MIN(MAX(EV_DB[[#This Row],[Federal Rebates (iMHZEV) ]],EV_DB[[#This Row],[PEI Vehicle Rebates]]),PRODUCT(EV_DB[[#This Row],[Cost, $MSRP CAD]],0.75)) -> 10000 | AO2: =MIN(MAX(EV_DB[[#This Row],[Federal Rebates (iMHZEV) ]],EV_DB[[#This Row],[NL Vehicle Rebates]]),PRODUCT(EV_DB[[#This Row],[Cost, $MSRP CAD]],0.75)) -> 10000 | AP2: =MIN(MAX(EV_DB[[#This Row],[Federal Rebates (iMHZEV) ]]+EV_DB[[#This Row],[YT Vehicle Rebates]]),PRODUCT(EV_DB[[#This Row],[Cost, $MSRP CAD]],0.75)) -> 10000 | AQ2: =MIN(MAX(EV_DB[[#This Row],[Federal Rebates (iMHZEV) ]],EV_DB[[#This Row],[NU Vehicle Rebates]]),PRODUCT(EV_DB[[#This Row],[Cost, $MSRP CAD]],0.75)) -> 10000 | AR2: =MIN(MAX(EV_DB[[#This Row],[Federal Rebates (iMHZEV) ]],EV_DB[[#This Row],[NT Vehicle Rebates]]),PRODUCT(EV_DB[[#This Row],[Cost, $MSRP CAD]],0.75)) -> 10000
A3: GMC | B3: GMC Sierra EV Denali Edition 1 | C3: =EV_DB[[#This Row],[Manufacturer ]]& " " &EV_DB[[#This Row],[Model]] -> GMC GMC Sierra EV Denali Edition 1 | D3: Pick-up truck | E3: 2025 | F3: 2B | G3: {=_xlfn.IFS(OR(EV_DB[[#This Row],[FHWA Class (2B - 8)]]= "2B", EV_DB[[#This Row],[FHWA Class (2B - 8)]]=3), "Light Duty",OR(EV_DB[[#This Row],[FHWA Class (2B - 8)]]=4,EV_DB[[#This Row],[FHWA Class (2B - 8)]]=5,EV_DB[[#This Row],[FHWA Class (2B - 8)]]=6),"Medium Duty",OR(EV_DB[[#This Row],[FHWA Class (2B - 8)]]=7,EV_DB[[#This Row],[FHWA Class (2B - 8)]]=8), "Heavy Duty")} -> Light Duty | H3: 9990 | I3: 1450 | J3: 92290 | K3: {=_xlfn.IFS(EV_DB[[#This Row],[Category]]="Light Duty",'Maintenance costs table'!$D$4,EV_DB[[#This Row],[Category]]="Medium Duty",'Maintenance costs table'!$D$8,EV_DB[[#This Row],[Category]]="Heavy Duty",'Maintenance costs table'!$D$6)} -> 0.18 | L3: No | M3: 205kwh | N3: 0.349 | O3: DC public fast-charging of 100 miles in approximately 10 minutes | Q3: 708.111 | R3: {=_xlfn.IFS(EV_DB[[#This Row],[Battery Size, kWh]]>350 & EV_DB[[#This Row],[FHWA Class (2B - 8)]]=8,'iMHZEV table'!$D$4,EV_DB[[#This Row],[Battery Size, kWh]]<=350 & EV_DB[[#This Row],[FHWA Class (2B - 8)]]=8,'iMHZEV table'!$D$5, TRUE, _xlfn.XLOOKUP(EV_DB[[#This Row],[FHWA Class (2B - 8)]],'iMHZEV table'!$A$3:$A$11,'iMHZEV table'!$D$3:$D$11))} -> 10000 | T3: {=_xlfn.IFS(EV_DB[[#This Row],[FHWA Class (2B - 8)]]= "2B",10000,EV_DB[[#This Row],[FHWA Class (2B - 8)]]=3,55000,OR(EV_DB[[#This Row],[FHWA Class (2B - 8)]]=4,EV_DB[[#This Row],[FHWA Class (2B - 8)]]=5), 75000,OR(EV_DB[[#This Row],[FHWA Class (2B - 8)]]=6,EV_DB[[#This Row],[FHWA Class (2B - 8)]]=7),100000,EV_DB[[#This Row],[FHWA Class (2B - 8)]]=8, 150000)} -> 10000 | AF3: =MIN(MAX(EV_DB[[#This Row],[Federal Rebates (iMHZEV) ]],EV_DB[[#This Row],[ON Vehicle Rebates]]),PRODUCT(EV_DB[[#This Row],[Cost, $MSRP CAD]],0.75)) -> 10000 | AG3: =MIN(EV_DB[[#This Row],[Federal Rebates (iMHZEV) ]]+EV_DB[[#This Row],[BC Vehicle Rebates]],PRODUCT(EV_DB[[#This Row],[Cost, $MSRP CAD]],0.75)) -> 20000 | AH3: =MIN(EV_DB[[#This Row],[Federal Rebates (iMHZEV) ]]+EV_DB[[#This Row],[QC Vehicle Rebates]],PRODUCT(EV_DB[[#This Row],[Cost, $MSRP CAD]],0.75)) -> 10000 | AI3: =MIN(MAX(EV_DB[[#This Row],[Federal Rebates (iMHZEV) ]],EV_DB[[#This Row],[AB Vehicle Rebates]]),PRODUCT(EV_DB[[#This Row],[Cost, $MSRP CAD]],0.75)) -> 10000 | AJ3: =MIN(MAX(EV_DB[[#This Row],[Federal Rebates (iMHZEV) ]],EV_DB[[#This Row],[SC Vehicle Rebates]]),PRODUCT(EV_DB[[#This Row],[Cost, $MSRP CAD]],0.75)) -> 10000 | AK3: =MIN(MAX(EV_DB[[#This Row],[Federal Rebates (iMHZEV) ]],EV_DB[[#This Row],[NS Vehicle Rebates]]),PRODUCT(EV_DB[[#This Row],[Cost, $MSRP CAD]],0.75)) -> 10000 | AL3: =MIN(MAX(EV_DB[[#This Row],[Federal Rebates (iMHZEV) ]],EV_DB[[#This Row],[NB Vehicle Rebates]]),PRODUCT(EV_DB[[#This Row],[Cost, $MSRP CAD]],0.75)) -> 10000 | AM3: =MIN(MAX(EV_DB[[#This Row],[Federal Rebates (iMHZEV) ]],EV_DB[[#This Row],[MB Vehicle Rebates]]),PRODUCT(EV_DB[[#This Row],[Cost, $MSRP CAD]],0.75)) -> 10000 | AN3: =MIN(MAX(EV_DB[[#This Row],[Federal Rebates (iMHZEV) ]],EV_DB[[#This Row],[PEI Vehicle Rebates]]),PRODUCT(EV_DB[[#This Row],[Cost, $MSRP CAD]],0.75)) -> 10000 | AO3: =MIN(MAX(EV_DB[[#This Row],[Federal Rebates (iMHZEV) ]],EV_DB[[#This Row],[NL Vehicle Rebates]]),PRODUCT(EV_DB[[#This Row],[Cost, $MSRP CAD]],0.75)) -> 10000 | AP3: =MIN(MAX(EV_DB[[#This Row],[Federal Rebates (iMHZEV) ]]+EV_DB[[#This Row],[YT Vehicle Rebates]]),PRODUCT(EV_DB[[#This Row],[Cost, $MSRP CAD]],0.75)) -> 10000 | AQ3: =MIN(MAX(EV_DB[[#This Row],[Federal Rebates (iMHZEV) ]],EV_DB[[#This Row],[NU Vehicle Rebates]]),PRODUCT(EV_DB[[#This Row],[Cost, $MSRP CAD]],0.75)) -> 10000 | AR3: =MIN(MAX(EV_DB[[#This Row],[Federal Rebates (iMHZEV) ]],EV_DB[[#This Row],[NT Vehicle Rebates]]),PRODUCT(EV_DB[[#This Row],[Cost, $MSRP CAD]],0.75)) -> 10000
A4: Chevrolet | B4: Silverado EV 3WT Max Range | C4: =EV_DB[[#This Row],[Manufacturer ]]& " " &EV_DB[[#This Row],[Model]] -> Chevrolet Silverado EV 3WT Max Range | D4: Pick-up truck | E4: 2025 | F4: 2B | G4: {=_xlfn.IFS(OR(EV_DB[[#This Row],[FHWA Class (2B - 8)]]= "2B", EV_DB[[#This Row],[FHWA Class (2B - 8)]]=3), "Light Duty",OR(EV_DB[[#This Row],[FHWA Class (2B - 8)]]=4,EV_DB[[#This Row],[FHWA Class (2B - 8)]]=5,EV_DB[[#This Row],[FHWA Class (2B - 8)]]=6),"Medium Duty",OR(EV_DB[[#This Row],[FHWA Class (2B - 8)]]=7,EV_DB[[#This Row],[FHWA Class (2B - 8)]]=8), "Heavy Duty")} -> Light Duty | H4: 9900 | I4: 1800 | J4: 85833 | K4: {=_xlfn.IFS(EV_DB[[#This Row],[Category]]="Light Duty",'Maintenance costs table'!$D$4,EV_DB[[#This Row],[Category]]="Medium Duty",'Maintenance costs table'!$D$8,EV_DB[[#This Row],[Category]]="Heavy Duty",'Maintenance costs table'!$D$6)} -> 0.18 | L4: No | M4: 205kwh | N4: 0.314 | O4: 11.5 kW capable onboard charging module 120V: N/A 240V: 11.0 h 400V: 0.5 h 10 minutes at a public DC charging station can add 100 miles of range. | Q4: 792 | R4: {=_xlfn.IFS(EV_DB[[#This Row],[Battery Size, kWh]]>350 & EV_DB[[#This Row],[FHWA Class (2B - 8)]]=8,'iMHZEV table'!$D$4,EV_DB[[#This Row],[Battery Size, kWh]]<=350 & EV_DB[[#This Row],[FHWA Class (2B - 8)]]=8,'iMHZEV table'!$D$5, TRUE, _xlfn.XLOOKUP(EV_DB[[#This Row],[FHWA Class (2B - 8)]],'iMHZEV table'!$A$3:$A$11,'iMHZEV table'!$D$3:$D$11))} -> 10000 | T4: {=_xlfn.IFS(EV_DB[[#This Row],[FHWA Class (2B - 8)]]= "2B",10000,EV_DB[[#This Row],[FHWA Class (2B - 8)]]=3,55000,OR(EV_DB[[#This Row],[FHWA Class (2B - 8)]]=4,EV_DB[[#This Row],[FHWA Class (2B - 8)]]=5), 75000,OR(EV_DB[[#This Row],[FHWA Class (2B - 8)]]=6,EV_DB[[#This Row],[FHWA Class (2B - 8)]]=7),100000,EV_DB[[#This Row],[FHWA Class (2B - 8)]]=8, 150000)} -> 10000 | AF4: =MIN(MAX(EV_DB[[#This Row],[Federal Rebates (iMHZEV) ]],EV_DB[[#This Row],[ON Vehicle Rebates]]),PRODUCT(EV_DB[[#This Row],[Cost, $MSRP CAD]],0.75)) -> 10000 | AG4: =MIN(EV_DB[[#This Row],[Federal Rebates (iMHZEV) ]]+EV_DB[[#This Row],[BC Vehicle Rebates]],PRODUCT(EV_DB[[#This Row],[Cost, $MSRP CAD]],0.75)) -> 20000 | AH4: =MIN(EV_DB[[#This Row],[Federal Rebates (iMHZEV) ]]+EV_DB[[#This Row],[QC Vehicle Rebates]],PRODUCT(EV_DB[[#This Row],[Cost, $MSRP CAD]],0.75)) -> 10000 | AI4: =MIN(MAX(EV_DB[[#This Row],[Federal Rebates (iMHZEV) ]],EV_DB[[#This Row],[AB Vehicle Rebates]]),PRODUCT(EV_DB[[#This Row],[Cost, $MSRP CAD]],0.75)) -> 10000 | AJ4: =MIN(MAX(EV_DB[[#This Row],[Federal Rebates (iMHZEV) ]],EV_DB[[#This Row],[SC Vehicle Rebates]]),PRODUCT(EV_DB[[#This Row],[Cost, $MSRP CAD]],0.75)) -> 10000 | AK4: =MIN(MAX(EV_DB[[#This Row],[Federal Rebates (iMHZEV) ]],EV_DB[[#This Row],[NS Vehicle Rebates]]),PRODUCT(EV_DB[[#This Row],[Cost, $MSRP CAD]],0.75)) -> 10000 | AL4: =MIN(MAX(EV_DB[[#This Row],[Federal Rebates (iMHZEV) ]],EV_DB[[#This Row],[NB Vehicle Rebates]]),PRODUCT(EV_DB[[#This Row],[Cost, $MSRP CAD]],0.75)) -> 10000 | AM4: =MIN(MAX(EV_DB[[#This Row],[Federal Rebates (iMHZEV) ]],EV_DB[[#This Row],[MB Vehicle Rebates]]),PRODUCT(EV_DB[[#This Row],[Cost, $MSRP CAD]],0.75)) -> 10000 | AN4: =MIN(MAX(EV_DB[[#This Row],[Federal Rebates (iMHZEV) ]],EV_DB[[#This Row],[PEI Vehicle Rebates]]),PRODUCT(EV_DB[[#This Row],[Cost, $MSRP CAD]],0.75)) -> 10000 | AO4: =MIN(MAX(EV_DB[[#This Row],[Federal Rebates (iMHZEV) ]],EV_DB[[#This Row],[NL Vehicle Rebates]]),PRODUCT(EV_DB[[#This Row],[Cost, $MSRP CAD]],0.75)) -> 10000 | AP4: =MIN(MAX(EV_DB[[#This Row],[Federal Rebates (iMHZEV) ]]+EV_DB[[#This Row],[YT Vehicle Rebates]]),PRODUCT(EV_DB[[#This Row],[Cost, $MSRP CAD]],0.75)) -> 10000 | AQ4: =MIN(MAX(EV_DB[[#This Row],[Federal Rebates (iMHZEV) ]],EV_DB[[#This Row],[NU Vehicle Rebates]]),PRODUCT(EV_DB[[#This Row],[Cost, $MSRP CAD]],0.75)) -> 10000 | AR4: =MIN(MAX(EV_DB[[#This Row],[Federal Rebates (iMHZEV) ]],EV_DB[[#This Row],[NT Vehicle Rebates]]),PRODUCT(EV_DB[[#This Row],[Cost, $MSRP CAD]],0.75)) -> 10000
A5: Chevrolet | B5: Silverado EV LT E4WD | C5: =EV_DB[[#This Row],[Manufacturer ]]& " " &EV_DB[[#This Row],[Model]] -> Chevrolet Silverado EV LT E4WD | D5: Pick-up truck | E5: 2025 | F5: 2B | G5: {=_xlfn.IFS(OR(EV_DB[[#This Row],[FHWA Class (2B - 8)]]= "2B", EV_DB[[#This Row],[FHWA Class (2B - 8)]]=3), "Light Duty",OR(EV_DB[[#This Row],[FHWA Class (2B - 8)]]=4,EV_DB[[#This Row],[FHWA Class (2B - 8)]]=5,EV_DB[[#This Row],[FHWA Class (2B - 8)]]=6),"Medium Duty",OR(EV_DB[[#This Row],[FHWA Class (2B - 8)]]=7,EV_DB[[#This Row],[FHWA Class (2B - 8)]]=8), "Heavy Duty")} -> Light Duty | H5: 9990 | I5: 1800 | J5: 95833 | K5: {=_xlfn.IFS(EV_DB[[#This Row],[Category]]="Light Duty",'Maintenance costs table'!$D$4,EV_DB[[#This Row],[Category]]="Medium Duty",'Maintenance costs table'!$D$8,EV_DB[[#This Row],[Category]]="Heavy Duty",'Maintenance costs table'!$D$6)} -> 0.18 | L5: No | M5: 170kwh | N5: 0.308 | O5: 11.5 kW capable onboard charging module 120V: N/A 240V: 11.0 h 400V: 0.5 h 10 minutes at a public DC charging station can add 100 miles of range. | Q5: 740 | R5: {=_xlfn.IFS(EV_DB[[#This Row],[Battery Size, kWh]]>350 & EV_DB[[#This Row],[FHWA Class (2B - 8)]]=8,'iMHZEV table'!$D$4,EV_DB[[#This Row],[Battery Size, kWh]]<=350 & EV_DB[[#This Row],[FHWA Class (2B - 8)]]=8,'iMHZEV table'!$D$5, TRUE, _xlfn.XLOOKUP(EV_DB[[#This Row],[FHWA Class (2B - 8)]],'iMHZEV table'!$A$3:$A$11,'iMHZEV table'!$D$3:$D$11))} -> 10000 | T5: {=_xlfn.IFS(EV_DB[[#This Row],[FHWA Class (2B - 8)]]= "2B",10000,EV_DB[[#This Row],[FHWA Class (2B - 8)]]=3,55000,OR(EV_DB[[#This Row],[FHWA Class (2B - 8)]]=4,EV_DB[[#This Row],[FHWA Class (2B - 8)]]=5), 75000,OR(EV_DB[[#This Row],[FHWA Class (2B - 8)]]=6,EV_DB[[#This Row],[FHWA Class (2B - 8)]]=7),100000,EV_DB[[#This Row],[FHWA Class (2B - 8)]]=8, 150000)} -> 10000 | AF5: =MIN(MAX(EV_DB[[#This Row],[Federal Rebates (iMHZEV) ]],EV_DB[[#This Row],[ON Vehicle Rebates]]),PRODUCT(EV_DB[[#This Row],[Cost, $MSRP CAD]],0.75)) -> 10000 | AG5: =MIN(EV_DB[[#This Row],[Federal Rebates (iMHZEV) ]]+EV_DB[[#This Row],[BC Vehicle Rebates]],PRODUCT(EV_DB[[#This Row],[Cost, $MSRP CAD]],0.75)) -> 20000 | AH5: =MIN(EV_DB[[#This Row],[Federal Rebates (iMHZEV) ]]+EV_DB[[#This Row],[QC Vehicle Rebates]],PRODUCT(EV_DB[[#This Row],[Cost, $MSRP CAD]],0.75)) -> 10000 | AI5: =MIN(MAX(EV_DB[[#This Row],[Federal Rebates (iMHZEV) ]],EV_DB[[#This Row],[AB Vehicle Rebates]]),PRODUCT(EV_DB[[#This Row],[Cost, $MSRP CAD]],0.75)) -> 10000 | AJ5: =MIN(MAX(EV_DB[[#This Row],[Federal Rebates (iMHZEV) ]],EV_DB[[#This Row],[SC Vehicle Rebates]]),PRODUCT(EV_DB[[#This Row],[Cost, $MSRP CAD]],0.75)) -> 10000 | AK5: =MIN(MAX(EV_DB[[#This Row],[Federal Rebates (iMHZEV) ]],EV_DB[[#This Row],[NS Vehicle Rebates]]),PRODUCT(EV_DB[[#This Row],[Cost, $MSRP CAD]],0.75)) -> 10000 | AL5: =MIN(MAX(EV_DB[[#This Row],[Federal Rebates (iMHZEV) ]],EV_DB[[#This Row],[NB Vehicle Rebates]]),PRODUCT(EV_DB[[#This Row],[Cost, $MSRP CAD]],0.75)) -> 10000 | AM5: =MIN(MAX(EV_DB[[#This Row],[Federal Rebates (iMHZEV) ]],EV_DB[[#This Row],[MB Vehicle Rebates]]),PRODUCT(EV_DB[[#This Row],[Cost, $MSRP CAD]],0.75)) -> 10000 | AN5: =MIN(MAX(EV_DB[[#This Row],[Federal Rebates (iMHZEV) ]],EV_DB[[#This Row],[PEI Vehicle Rebates]]),PRODUCT(EV_DB[[#This Row],[Cost, $MSRP CAD]],0.75)) -> 10000 | AO5: =MIN(MAX(EV_DB[[#This Row],[Federal Rebates (iMHZEV) ]],EV_DB[[#This Row],[NL Vehicle Rebates]]),PRODUCT(EV_DB[[#This Row],[Cost, $MSRP CAD]],0.75)) -> 10000 | AP5: =MIN(MAX(EV_DB[[#This Row],[Federal Rebates (iMHZEV) ]]+EV_DB[[#This Row],[YT Vehicle Rebates]]),PRODUCT(EV_DB[[#This Row],[Cost, $MSRP CAD]],0.75)) -> 10000 | AQ5: =MIN(MAX(EV_DB[[#This Row],[Federal Rebates (iMHZEV) ]],EV_DB[[#This Row],[NU Vehicle Rebates]]),PRODUCT(EV_DB[[#This Row],[Cost, $MSRP CAD]],0.75)) -> 10000 | AR5: =MIN(MAX(EV_DB[[#This Row],[Federal Rebates (iMHZEV) ]],EV_DB[[#This Row],[NT Vehicle Rebates]]),PRODUCT(EV_DB[[#This Row],[Cost, $MSRP CAD]],0.75)) -> 10000
A6: Ford | B6: F 150 Lightning | C6: =EV_DB[[#This Row],[Manufacturer ]]& " " &EV_DB[[#This Row],[Model]] -> Ford F 150 Lightning | D6: Pick-up truck | E6: 2025 | F6: 2B | G6: {=_xlfn.IFS(OR(EV_DB[[#This Row],[FHWA Class (2B - 8)]]= "2B", EV_DB[[#This Row],[FHWA Class (2B - 8)]]=3), "Light Duty",OR(EV_DB[[#This Row],[FHWA Class (2B - 8)]]=4,EV_DB[[#This Row],[FHWA Class (2B - 8)]]=5,EV_DB[[#This Row],[FHWA Class (2B - 8)]]=6),"Medium Duty",OR(EV_DB[[#This Row],[FHWA Class (2B - 8)]]=7,EV_DB[[#This Row],[FHWA Class (2B - 8)]]=8), "Heavy Duty")} -> Light Duty | H6: 8550 | I6: 2235 | J6: 62890 | K6: {=_xlfn.IFS(EV_DB[[#This Row],[Category]]="Light Duty",'Maintenance costs table'!$D$4,EV_DB[[#This Row],[Category]]="Medium Duty",'Maintenance costs table'!$D$8,EV_DB[[#This Row],[Category]]="Heavy Duty",'Maintenance costs table'!$D$6)} -> 0.18 | L6: No | M6: 98 kWh | N6: 0.254 | O6: 15% to 80% with a 150+ kW DC fast charger takes about 36 minutes for the Standard Range and | Q6: 386 | R6: {=_xlfn.IFS(EV_DB[[#This Row],[Battery Size, kWh]]>350 & EV_DB[[#This Row],[FHWA Class (2B - 8)]]=8,'iMHZEV table'!$D$4,EV_DB[[#This Row],[Battery Size, kWh]]<=350 & EV_DB[[#This Row],[FHWA Class (2B - 8)]]=8,'iMHZEV table'!$D$5, TRUE, _xlfn.XLOOKUP(EV_DB[[#This Row],[FHWA Class (2B - 8)]],'iMHZEV table'!$A$3:$A$11,'iMHZEV table'!$D$3:$D$11))} -> 10000 | T6: {=_xlfn.IFS(EV_DB[[#This Row],[FHWA Class (2B - 8)]]= "2B",10000,EV_DB[[#This Row],[FHWA Class (2B - 8)]]=3,55000,OR(EV_DB[[#This Row],[FHWA Class (2B - 8)]]=4,EV_DB[[#This Row],[FHWA Class (2B - 8)]]=5), 75000,OR(EV_DB[[#This Row],[FHWA Class (2B - 8)]]=6,EV_DB[[#This Row],[FHWA Class (2B - 8)]]=7),100000,EV_DB[[#This Row],[FHWA Class (2B - 8)]]=8, 150000)} -> 10000 | AF6: =MIN(MAX(EV_DB[[#This Row],[Federal Rebates (iMHZEV) ]],EV_DB[[#This Row],[ON Vehicle Rebates]]),PRODUCT(EV_DB[[#This Row],[Cost, $MSRP CAD]],0.75)) -> 10000 | AG6: =MIN(EV_DB[[#This Row],[Federal Rebates (iMHZEV) ]]+EV_DB[[#This Row],[BC Vehicle Rebates]],PRODUCT(EV_DB[[#This Row],[Cost, $MSRP CAD]],0.75)) -> 20000 | AH6: =MIN(EV_DB[[#This Row],[Federal Rebates (iMHZEV) ]]+EV_DB[[#This Row],[QC Vehicle Rebates]],PRODUCT(EV_DB[[#This Row],[Cost, $MSRP CAD]],0.75)) -> 10000 | AI6: =MIN(MAX(EV_DB[[#This Row],[Federal Rebates (iMHZEV) ]],EV_DB[[#This Row],[AB Vehicle Rebates]]),PRODUCT(EV_DB[[#This Row],[Cost, $MSRP CAD]],0.75)) -> 10000 | AJ6: =MIN(MAX(EV_DB[[#This Row],[Federal Rebates (iMHZEV) ]],EV_DB[[#This Row],[SC Vehicle Rebates]]),PRODUCT(EV_DB[[#This Row],[Cost, $MSRP CAD]],0.75)) -> 10000 | AK6: =MIN(MAX(EV_DB[[#This Row],[Federal Rebates (iMHZEV) ]],EV_DB[[#This Row],[NS Vehicle Rebates]]),PRODUCT(EV_DB[[#This Row],[Cost, $MSRP CAD]],0.75)) -> 10000 | AL6: =MIN(MAX(EV_DB[[#This Row],[Federal Rebates (iMHZEV) ]],EV_DB[[#This Row],[NB Vehicle Rebates]]),PRODUCT(EV_DB[[#This Row],[Cost, $MSRP CAD]],0.75)) -> 10000 | AM6: =MIN(MAX(EV_DB[[#This Row],[Federal Rebates (iMHZEV) ]],EV_DB[[#This Row],[MB Vehicle Rebates]]),PRODUCT(EV_DB[[#This Row],[Cost, $MSRP CAD]],0.75)) -> 10000 | AN6: =MIN(MAX(EV_DB[[#This Row],[Federal Rebates (iMHZEV) ]],EV_DB[[#This Row],[PEI Vehicle Rebates]]),PRODUCT(EV_DB[[#This Row],[Cost, $MSRP CAD]],0.75)) -> 10000 | AO6: =MIN(MAX(EV_DB[[#This Row],[Federal Rebates (iMHZEV) ]],EV_DB[[#This Row],[NL Vehicle Rebates]]),PRODUCT(EV_DB[[#This Row],[Cost, $MSRP CAD]],0.75)) -> 10000 | AP6: =MIN(MAX(EV_DB[[#This Row],[Federal Rebates (iMHZEV) ]]+EV_DB[[#This Row],[YT Vehicle Rebates]]),PRODUCT(EV_DB[[#This Row],[Cost, $MSRP CAD]],0.75)) -> 10000 | AQ6: =MIN(MAX(EV_DB[[#This Row],[Federal Rebates (iMHZEV) ]],EV_DB[[#This Row],[NU Vehicle Rebates]]),PRODUCT(EV_DB[[#This Row],[Cost, $MSRP CAD]],0.75)) -> 10000 | AR6: =MIN(MAX(EV_DB[[#This Row],[Federal Rebates (iMHZEV) ]],EV_DB[[#This Row],[NT Vehicle Rebates]]),PRODUCT(EV_DB[[#This Row],[Cost, $MSRP CAD]],0.75)) -> 10000
A7: Ford | B7: F 150 Lightning Flash and Lariat | C7: =EV_DB[[#This Row],[Manufacturer ]]& " " &EV_DB[[#This Row],[Model]] -> Ford F 150 Lightning Flash and Lariat | D7: Pick-up truck | E7: 2025 | F7: 2B | G7: {=_xlfn.IFS(OR(EV_DB[[#This Row],[FHWA Class (2B - 8)]]= "2B", EV_DB[[#This Row],[FHWA Class (2B - 8)]]=3), "Light Duty",OR(EV_DB[[#This Row],[FHWA Class (2B - 8)]]=4,EV_DB[[#This Row],[FHWA Class (2B - 8)]]=5,EV_DB[[#This Row],[FHWA Class (2B - 8)]]=6),"Medium Duty",OR(EV_DB[[#This Row],[FHWA Class (2B - 8)]]=7,EV_DB[[#This Row],[FHWA Class (2B - 8)]]=8), "Heavy Duty")} -> Light Duty | H7: 8550 | I7: 2235 | J7: 79090 | K7: {=_xlfn.IFS(EV_DB[[#This Row],[Category]]="Light Duty",'Maintenance costs table'!$D$4,EV_DB[[#This Row],[Category]]="Medium Duty",'Maintenance costs table'!$D$8,EV_DB[[#This Row],[Category]]="Heavy Duty",'Maintenance costs table'!$D$6)} -> 0.18 | L7: No | M7: 131 kWh | N7: 0.265 | O7: 150+ kW DC fast charger - 41 minutes for the Extended Range | Q7: 515 | R7: {=_xlfn.IFS(EV_DB[[#This Row],[Battery Size, kWh]]>350 & EV_DB[[#This Row],[FHWA Class (2B - 8)]]=8,'iMHZEV table'!$D$4,EV_DB[[#This Row],[Battery Size, kWh]]<=350 & EV_DB[[#This Row],[FHWA Class (2B - 8)]]=8,'iMHZEV table'!$D$5, TRUE, _xlfn.XLOOKUP(EV_DB[[#This Row],[FHWA Class (2B - 8)]],'iMHZEV table'!$A$3:$A$11,'iMHZEV table'!$D$3:$D$11))} -> 10000 | T7: {=_xlfn.IFS(EV_DB[[#This Row],[FHWA Class (2B - 8)]]= "2B",10000,EV_DB[[#This Row],[FHWA Class (2B - 8)]]=3,55000,OR(EV_DB[[#This Row],[FHWA Class (2B - 8)]]=4,EV_DB[[#This Row],[FHWA Class (2B - 8)]]=5), 75000,OR(EV_DB[[#This Row],[FHWA Class (2B - 8)]]=6,EV_DB[[#This Row],[FHWA Class (2B - 8)]]=7),100000,EV_DB[[#This Row],[FHWA Class (2B - 8)]]=8, 150000)} -> 10000 | AF7: =MIN(MAX(EV_DB[[#This Row],[Federal Rebates (iMHZEV) ]],EV_DB[[#This Row],[ON Vehicle Rebates]]),PRODUCT(EV_DB[[#This Row],[Cost, $MSRP CAD]],0.75)) -> 10000 | AG7: =MIN(EV_DB[[#This Row],[Federal Rebates (iMHZEV) ]]+EV_DB[[#This Row],[BC Vehicle Rebates]],PRODUCT(EV_DB[[#This Row],[Cost, $MSRP CAD]],0.75)) -> 20000 | AH7: =MIN(EV_DB[[#This Row],[Federal Rebates (iMHZEV) ]]+EV_DB[[#This Row],[QC Vehicle Rebates]],PRODUCT(EV_DB[[#This Row],[Cost, $MSRP CAD]],0.75)) -> 10000 | AI7: =MIN(MAX(EV_DB[[#This Row],[Federal Rebates (iMHZEV) ]],EV_DB[[#This Row],[AB Vehicle Rebates]]),PRODUCT(EV_DB[[#This Row],[Cost, $MSRP CAD]],0.75)) -> 10000 | AJ7: =MIN(MAX(EV_DB[[#This Row],[Federal Rebates (iMHZEV) ]],EV_DB[[#This Row],[SC Vehicle Rebates]]),PRODUCT(EV_DB[[#This Row],[Cost, $MSRP CAD]],0.75)) -> 10000 | AK7: =MIN(MAX(EV_DB[[#This Row],[Federal Rebates (iMHZEV) ]],EV_DB[[#This Row],[NS Vehicle Rebates]]),PRODUCT(EV_DB[[#This Row],[Cost, $MSRP CAD]],0.75)) -> 10000 | AL7: =MIN(MAX(EV_DB[[#This Row],[Federal Rebates (iMHZEV) ]],EV_DB[[#This Row],[NB Vehicle Rebates]]),PRODUCT(EV_DB[[#This Row],[Cost, $MSRP CAD]],0.75)) -> 10000 | AM7: =MIN(MAX(EV_DB[[#This Row],[Federal Rebates (iMHZEV) ]],EV_DB[[#This Row],[MB Vehicle Rebates]]),PRODUCT(EV_DB[[#This Row],[Cost, $MSRP CAD]],0.75)) -> 10000 | AN7: =MIN(MAX(EV_DB[[#This Row],[Federal Rebates (iMHZEV) ]],EV_DB[[#This Row],[PEI Vehicle Rebates]]),PRODUCT(EV_DB[[#This Row],[Cost, $MSRP CAD]],0.75)) -> 10000 | AO7: =MIN(MAX(EV_DB[[#This Row],[Federal Rebates (iMHZEV) ]],EV_DB[[#This Row],[NL Vehicle Rebates]]),PRODUCT(EV_DB[[#This Row],[Cost, $MSRP CAD]],0.75)) -> 10000 | AP7: =MIN(MAX(EV_DB[[#This Row],[Federal Rebates (iMHZEV) ]]+EV_DB[[#This Row],[YT Vehicle Rebates]]),PRODUCT(EV_DB[[#This Row],[Cost, $MSRP CAD]],0.75)) -> 10000 | AQ7: =MIN(MAX(EV_DB[[#This Row],[Federal Rebates (iMHZEV) ]],EV_DB[[#This Row],[NU Vehicle Rebates]]),PRODUCT(EV_DB[[#This Row],[Cost, $MSRP CAD]],0.75)) -> 10000 | AR7: =MIN(MAX(EV_DB[[#This Row],[Federal Rebates (iMHZEV) ]],EV_DB[[#This Row],[NT Vehicle Rebates]]),PRODUCT(EV_DB[[#This Row],[Cost, $MSRP CAD]],0.75)) -> 10000
A8: Mercedes-Benz | B8: eSprinter (2500) | C8: =EV_DB[[#This Row],[Manufacturer ]]& " " &EV_DB[[#This Row],[Model]] -> Mercedes-Benz eSprinter (2500) | D8: Delivery van | E8: 2024 | F8: 2B | G8: {=_xlfn.IFS(OR(EV_DB[[#This Row],[FHWA Class (2B - 8)]]= "2B", EV_DB[[#This Row],[FHWA Class (2B - 8)]]=3), "Light Duty",OR(EV_DB[[#This Row],[FHWA Class (2B - 8)]]=4,EV_DB[[#This Row],[FHWA Class (2B - 8)]]=5,EV_DB[[#This Row],[FHWA Class (2B - 8)]]=6),"Medium Duty",OR(EV_DB[[#This Row],[FHWA Class (2B - 8)]]=7,EV_DB[[#This Row],[FHWA Class (2B - 8)]]=8), "Heavy Duty")} -> Light Duty | H8: 9370 | I8: 2623 | J8: 99500 | K8: {=_xlfn.IFS(EV_DB[[#This Row],[Category]]="Light Duty",'Maintenance costs table'!$D$4,EV_DB[[#This Row],[Category]]="Medium Duty",'Maintenance costs table'!$D$8,EV_DB[[#This Row],[Category]]="Heavy Duty",'Maintenance costs table'!$D$6)} -> 0.18 | L8: No | M8: 113 kWh | N8: 0.23 | O8: DC Charge time is 10-80% battery 115 kW/ - 42 minutes (optimal) 50 kW/ - 93 minutes | P8: 365 | Q8: 370 | R8: {=_xlfn.IFS(EV_DB[[#This Row],[Battery Size, kWh]]>350 & EV_DB[[#This Row],[FHWA Class (2B - 8)]]=8,'iMHZEV table'!$D$4,EV_DB[[#This Row],[Battery Size, kWh]]<=350 & EV_DB[[#This Row],[FHWA Class (2B - 8)]]=8,'iMHZEV table'!$D$5, TRUE, _xlfn.XLOOKUP(EV_DB[[#This Row],[FHWA Class (2B - 8)]],'iMHZEV table'!$A$3:$A$11,'iMHZEV table'!$D$3:$D$11))} -> 10000 | T8: {=_xlfn.IFS(EV_DB[[#This Row],[FHWA Class (2B - 8)]]= "2B",10000,EV_DB[[#This Row],[FHWA Class (2B - 8)]]=3,55000,OR(EV_DB[[#This Row],[FHWA Class (2B - 8)]]=4,EV_DB[[#This Row],[FHWA Class (2B - 8)]]=5), 75000,OR(EV_DB[[#This Row],[FHWA Class (2B - 8)]]=6,EV_DB[[#This Row],[FHWA Class (2B - 8)]]=7),100000,EV_DB[[#This Row],[FHWA Class (2B - 8)]]=8, 150000)} -> 10000 | AF8: =MIN(MAX(EV_DB[[#This Row],[Federal Rebates (iMHZEV) ]],EV_DB[[#This Row],[ON Vehicle Rebates]]),PRODUCT(EV_DB[[#This Row],[Cost, $MSRP CAD]],0.75)) -> 10000 | AG8: =MIN(EV_DB[[#This Row],[Federal Rebates (iMHZEV) ]]+EV_DB[[#This Row],[BC Vehicle Rebates]],PRODUCT(EV_DB[[#This Row],[Cost, $MSRP CAD]],0.75)) -> 20000 | AH8: =MIN(EV_DB[[#This Row],[Federal Rebates (iMHZEV) ]]+EV_DB[[#This Row],[QC Vehicle Rebates]],PRODUCT(EV_DB[[#This Row],[Cost, $MSRP CAD]],0.75)) -> 10000 | AI8: =MIN(MAX(EV_DB[[#This Row],[Federal Rebates (iMHZEV) ]],EV_DB[[#This Row],[AB Vehicle Rebates]]),PRODUCT(EV_DB[[#This Row],[Cost, $MSRP CAD]],0.75)) -> 10000 | AJ8: =MIN(MAX(EV_DB[[#This Row],[Federal Rebates (iMHZEV) ]],EV_DB[[#This Row],[SC Vehicle Rebates]]),PRODUCT(EV_DB[[#This Row],[Cost, $MSRP CAD]],0.75)) -> 10000 | AK8: =MIN(MAX(EV_DB[[#This Row],[Federal Rebates (iMHZEV) ]],EV_DB[[#This Row],[NS Vehicle Rebates]]),PRODUCT(EV_DB[[#This Row],[Cost, $MSRP CAD]],0.75)) -> 10000 | AL8: =MIN(MAX(EV_DB[[#This Row],[Federal Rebates (iMHZEV) ]],EV_DB[[#This Row],[NB Vehicle Rebates]]),PRODUCT(EV_DB[[#This Row],[Cost, $MSRP CAD]],0.75)) -> 10000 | AM8: =MIN(MAX(EV_DB[[#This Row],[Federal Rebates (iMHZEV) ]],EV_DB[[#This Row],[MB Vehicle Rebates]]),PRODUCT(EV_DB[[#This Row],[Cost, $MSRP CAD]],0.75)) -> 10000 | AN8: =MIN(MAX(EV_DB[[#This Row],[Federal Rebates (iMHZEV) ]],EV_DB[[#This Row],[PEI Vehicle Rebates]]),PRODUCT(EV_DB[[#This Row],[Cost, $MSRP CAD]],0.75)) -> 10000 | AO8: =MIN(MAX(EV_DB[[#This Row],[Federal Rebates (iMHZEV) ]],EV_DB[[#This Row],[NL Vehicle Rebates]]),PRODUCT(EV_DB[[#This Row],[Cost, $MSRP CAD]],0.75)) -> 10000 | AP8: =MIN(MAX(EV_DB[[#This Row],[Federal Rebates (iMHZEV) ]]+EV_DB[[#This Row],[YT Vehicle Rebates]]),PRODUCT(EV_DB[[#This Row],[Cost, $MSRP CAD]],0.75)) -> 10000 | AQ8: =MIN(MAX(EV_DB[[#This Row],[Federal Rebates (iMHZEV) ]],EV_DB[[#This Row],[NU Vehicle Rebates]]),PRODUCT(EV_DB[[#This Row],[Cost, $MSRP CAD]],0.75)) -> 10000 | AR8: =MIN(MAX(EV_DB[[#This Row],[Federal Rebates (iMHZEV) ]],EV_DB[[#This Row],[NT Vehicle Rebates]]),PRODUCT(EV_DB[[#This Row],[Cost, $MSRP CAD]],0.75)) -> 10000
A9: RAM | B9: ProMaster Van | C9: =EV_DB[[#This Row],[Manufacturer ]]& " " &EV_DB[[#This Row],[Model]] -> RAM ProMaster Van | D9: Cargo van | E9: 2025 | F9: 2B | G9: {=_xlfn.IFS(OR(EV_DB[[#This Row],[FHWA Class (2B - 8)]]= "2B", EV_DB[[#This Row],[FHWA Class (2B - 8)]]=3), "Light Duty",OR(EV_DB[[#This Row],[FHWA Class (2B - 8)]]=4,EV_DB[[#This Row],[FHWA Class (2B - 8)]]=5,EV_DB[[#This Row],[FHWA Class (2B - 8)]]=6),"Medium Duty",OR(EV_DB[[#This Row],[FHWA Class (2B - 8)]]=7,EV_DB[[#This Row],[FHWA Class (2B - 8)]]=8), "Heavy Duty")} -> Light Duty | H9: 9350 | I9: 3020 | J9: 119000 | K9: {=_xlfn.IFS(EV_DB[[#This Row],[Category]]="Light Duty",'Maintenance costs table'!$D$4,EV_DB[[#This Row],[Category]]="Medium Duty",'Maintenance costs table'!$D$8,EV_DB[[#This Row],[Category]]="Heavy Duty",'Maintenance costs table'!$D$6)} -> 0.18 | L9: No | M9: 110kWh | N9: 0.24 | O9: The ProMaster EV supports Level 3 DC fast-charging capacities of 50 kW, 85 kW, 125 kW, and 150 kW. Additionally, a Level 2 wall box providing 11 kW is also available3 | P9: 400 | Q9: 264 | R9: {=_xlfn.IFS(EV_DB[[#This Row],[Battery Size, kWh]]>350 & EV_DB[[#This Row],[FHWA Class (2B - 8)]]=8,'iMHZEV table'!$D$4,EV_DB[[#This Row],[Battery Size, kWh]]<=350 & EV_DB[[#This Row],[FHWA Class (2B - 8)]]=8,'iMHZEV table'!$D$5, TRUE, _xlfn.XLOOKUP(EV_DB[[#This Row],[FHWA Class (2B - 8)]],'iMHZEV table'!$A$3:$A$11,'iMHZEV table'!$D$3:$D$11))} -> 10000 | T9: {=_xlfn.IFS(EV_DB[[#This Row],[FHWA Class (2B - 8)]]= "2B",10000,EV_DB[[#This Row],[FHWA Class (2B - 8)]]=3,55000,OR(EV_DB[[#This Row],[FHWA Class (2B - 8)]]=4,EV_DB[[#This Row],[FHWA Class (2B - 8)]]=5), 75000,OR(EV_DB[[#This Row],[FHWA Class (2B - 8)]]=6,EV_DB[[#This Row],[FHWA Class (2B - 8)]]=7),100000,EV_DB[[#This Row],[FHWA Class (2B - 8)]]=8, 150000)} -> 10000 | AF9: =MIN(MAX(EV_DB[[#This Row],[Federal Rebates (iMHZEV) ]],EV_DB[[#This Row],[ON Vehicle Rebates]]),PRODUCT(EV_DB[[#This Row],[Cost, $MSRP CAD]],0.75)) -> 10000 | AG9: =MIN(EV_DB[[#This Row],[Federal Rebates (iMHZEV) ]]+EV_DB[[#This Row],[BC Vehicle Rebates]],PRODUCT(EV_DB[[#This Row],[Cost, $MSRP CAD]],0.75)) -> 20000 | AH9: =MIN(EV_DB[[#This Row],[Federal Rebates (iMHZEV) ]]+EV_DB[[#This Row],[QC Vehicle Rebates]],PRODUCT(EV_DB[[#This Row],[Cost, $MSRP CAD]],0.75)) -> 10000 | AI9: =MIN(MAX(EV_DB[[#This Row],[Federal Rebates (iMHZEV) ]],EV_DB[[#This Row],[AB Vehicle Rebates]]),PRODUCT(EV_DB[[#This Row],[Cost, $MSRP CAD]],0.75)) -> 10000 | AJ9: =MIN(MAX(EV_DB[[#This Row],[Federal Rebates (iMHZEV) ]],EV_DB[[#This Row],[SC Vehicle Rebates]]),PRODUCT(EV_DB[[#This Row],[Cost, $MSRP CAD]],0.75)) -> 10000 | AK9: =MIN(MAX(EV_DB[[#This Row],[Federal Rebates (iMHZEV) ]],EV_DB[[#This Row],[NS Vehicle Rebates]]),PRODUCT(EV_DB[[#This Row],[Cost, $MSRP CAD]],0.75)) -> 10000 | AL9: =MIN(MAX(EV_DB[[#This Row],[Federal Rebates (iMHZEV) ]],EV_DB[[#This Row],[NB Vehicle Rebates]]),PRODUCT(EV_DB[[#This Row],[Cost, $MSRP CAD]],0.75)) -> 10000 | AM9: =MIN(MAX(EV_DB[[#This Row],[Federal Rebates (iMHZEV) ]],EV_DB[[#This Row],[MB Vehicle Rebates]]),PRODUCT(EV_DB[[#This Row],[Cost, $MSRP CAD]],0.75)) -> 10000 | AN9: =MIN(MAX(EV_DB[[#This Row],[Federal Rebates (iMHZEV) ]],EV_DB[[#This Row],[PEI Vehicle Rebates]]),PRODUCT(EV_DB[[#This Row],[Cost, $MSRP CAD]],0.75)) -> 10000 | AO9: =MIN(MAX(EV_DB[[#This Row],[Federal Rebates (iMHZEV) ]],EV_DB[[#This Row],[NL Vehicle Rebates]]),PRODUCT(EV_DB[[#This Row],[Cost, $MSRP CAD]],0.75)) -> 10000 | AP9: =MIN(MAX(EV_DB[[#This Row],[Federal Rebates (iMHZEV) ]]+EV_DB[[#This Row],[YT Vehicle Rebates]]),PRODUCT(EV_DB[[#This Row],[Cost, $MSRP CAD]],0.75)) -> 10000 | AQ9: =MIN(MAX(EV_DB[[#This Row],[Federal Rebates (iMHZEV) ]],EV_DB[[#This Row],[NU Vehicle Rebates]]),PRODUCT(EV_DB[[#This Row],[Cost, $MSRP CAD]],0.75)) -> 10000 | AR9: =MIN(MAX(EV_DB[[#This Row],[Federal Rebates (iMHZEV) ]],EV_DB[[#This Row],[NT Vehicle Rebates]]),PRODUCT(EV_DB[[#This Row],[Cost, $MSRP CAD]],0.75)) -> 10000
A10: Rivian | B10: R1T Dual | C10: =EV_DB[[#This Row],[Manufacturer ]]& " " &EV_DB[[#This Row],[Model]] -> Rivian R1T Dual | D10: Pick-up truck | E10: 2025 | F10: 3 | G10: {=_xlfn.IFS(OR(EV_DB[[#This Row],[FHWA Class (2B - 8)]]= "2B", EV_DB[[#This Row],[FHWA Class (2B - 8)]]=3), "Light Duty",OR(EV_DB[[#This Row],[FHWA Class (2B - 8)]]=4,EV_DB[[#This Row],[FHWA Class (2B - 8)]]=5,EV_DB[[#This Row],[FHWA Class (2B - 8)]]=6),"Medium Duty",OR(EV_DB[[#This Row],[FHWA Class (2B - 8)]]=7,EV_DB[[#This Row],[FHWA Class (2B - 8)]]=8), "Heavy Duty")} -> Light Duty | H10: 8532 | I10: 1764 | J10: 77900 | K10: {=_xlfn.IFS(EV_DB[[#This Row],[Category]]="Light Duty",'Maintenance costs table'!$D$4,EV_DB[[#This Row],[Category]]="Medium Duty",'Maintenance costs table'!$D$8,EV_DB[[#This Row],[Category]]="Heavy Duty",'Maintenance costs table'!$D$6)} -> 0.18 | L10: No | M10: 135 kWh | N10: 0.254 | Q10: 530 | R10: {=_xlfn.IFS(EV_DB[[#This Row],[Battery Size, kWh]]>350 & EV_DB[[#This Row],[FHWA Class (2B - 8)]]=8,'iMHZEV table'!$D$4,EV_DB[[#This Row],[Battery Size, kWh]]<=350 & EV_DB[[#This Row],[FHWA Class (2B - 8)]]=8,'iMHZEV table'!$D$5, TRUE, _xlfn.XLOOKUP(EV_DB[[#This Row],[FHWA Class (2B - 8)]],'iMHZEV table'!$A$3:$A$11,'iMHZEV table'!$D$3:$D$11))} -> 40000 | T10: {=_xlfn.IFS(EV_DB[[#This Row],[FHWA Class (2B - 8)]]= "2B",10000,EV_DB[[#This Row],[FHWA Class (2B - 8)]]=3,55000,OR(EV_DB[[#This Row],[FHWA Class (2B - 8)]]=4,EV_DB[[#This Row],[FHWA Class (2B - 8)]]=5), 75000,OR(EV_DB[[#This Row],[FHWA Class (2B - 8)]]=6,EV_DB[[#This Row],[FHWA Class (2B - 8)]]=7),100000,EV_DB[[#This Row],[FHWA Class (2B - 8)]]=8, 150000)} -> 55000 | AF10: =MIN(MAX(EV_DB[[#This Row],[Federal Rebates (iMHZEV) ]],EV_DB[[#This Row],[ON Vehicle Rebates]]),PRODUCT(EV_DB[[#This Row],[Cost, $MSRP CAD]],0.75)) -> 40000 | AG10: =MIN(EV_DB[[#This Row],[Federal Rebates (iMHZEV) ]]+EV_DB[[#This Row],[BC Vehicle Rebates]],PRODUCT(EV_DB[[#This Row],[Cost, $MSRP CAD]],0.75)) -> 58425 | AH10: =MIN(EV_DB[[#This Row],[Federal Rebates (iMHZEV) ]]+EV_DB[[#This Row],[QC Vehicle Rebates]],PRODUCT(EV_DB[[#This Row],[Cost, $MSRP CAD]],0.75)) -> 40000 | AI10: =MIN(MAX(EV_DB[[#This Row],[Federal Rebates (iMHZEV) ]],EV_DB[[#This Row],[AB Vehicle Rebates]]),PRODUCT(EV_DB[[#This Row],[Cost, $MSRP CAD]],0.75)) -> 40000 | AJ10: =MIN(MAX(EV_DB[[#This Row],[Federal Rebates (iMHZEV) ]],EV_DB[[#This Row],[SC Vehicle Rebates]]),PRODUCT(EV_DB[[#This Row],[Cost, $MSRP CAD]],0.75)) -> 40000 | AK10: =MIN(MAX(EV_DB[[#This Row],[Federal Rebates (iMHZEV) ]],EV_DB[[#This Row],[NS Vehicle Rebates]]),PRODUCT(EV_DB[[#This Row],[Cost, $MSRP CAD]],0.75)) -> 40000 | AL10: =MIN(MAX(EV_DB[[#This Row],[Federal Rebates (iMHZEV) ]],EV_DB[[#This Row],[NB Vehicle Rebates]]),PRODUCT(EV_DB[[#This Row],[Cost, $MSRP CAD]],0.75)) -> 40000 | AM10: =MIN(MAX(EV_DB[[#This Row],[Federal Rebates (iMHZEV) ]],EV_DB[[#This Row],[MB Vehicle Rebates]]),PRODUCT(EV_DB[[#This Row],[Cost, $MSRP CAD]],0.75)) -> 40000 | AN10: =MIN(MAX(EV_DB[[#This Row],[Federal Rebates (iMHZEV) ]],EV_DB[[#This Row],[PEI Vehicle Rebates]]),PRODUCT(EV_DB[[#This Row],[Cost, $MSRP CAD]],0.75)) -> 40000 | AO10: =MIN(MAX(EV_DB[[#This Row],[Federal Rebates (iMHZEV) ]],EV_DB[[#This Row],[NL Vehicle Rebates]]),PRODUCT(EV_DB[[#This Row],[Cost, $MSRP CAD]],0.75)) -> 40000 | AP10: =MIN(MAX(EV_DB[[#This Row],[Federal Rebates (iMHZEV) ]]+EV_DB[[#This Row],[YT Vehicle Rebates]]),PRODUCT(EV_DB[[#This Row],[Cost, $MSRP CAD]],0.75)) -> 40000 | AQ10: =MIN(MAX(EV_DB[[#This Row],[Federal Rebates (iMHZEV) ]],EV_DB[[#This Row],[NU Vehicle Rebates]]),PRODUCT(EV_DB[[#This Row],[Cost, $MSRP CAD]],0.75)) -> 40000 | AR10: =MIN(MAX(EV_DB[[#This Row],[Federal Rebates (iMHZEV) ]],EV_DB[[#This Row],[NT Vehicle Rebates]]),PRODUCT(EV_DB[[#This Row],[Cost, $MSRP CAD]],0.75)) -> 40000
A11: Ford | B11: E-Transit | C11: =EV_DB[[#This Row],[Manufacturer ]]& " " &EV_DB[[#This Row],[Model]] -> Ford E-Transit | D11: Cargo, delivery, work van | E11: 2024 | F11: 2B | G11: {=_xlfn.IFS(OR(EV_DB[[#This Row],[FHWA Class (2B - 8)]]= "2B", EV_DB[[#This Row],[FHWA Class (2B - 8)]]=3), "Light Duty",OR(EV_DB[[#This Row],[FHWA Class (2B - 8)]]=4,EV_DB[[#This Row],[FHWA Class (2B - 8)]]=5,EV_DB[[#This Row],[FHWA Class (2B - 8)]]=6),"Medium Duty",OR(EV_DB[[#This Row],[FHWA Class (2B - 8)]]=7,EV_DB[[#This Row],[FHWA Class (2B - 8)]]=8), "Heavy Duty")} -> Light Duty | H11: 8670 - 11,000 | I11: 3776 | J11: 68705 | K11: {=_xlfn.IFS(EV_DB[[#This Row],[Category]]="Light Duty",'Maintenance costs table'!$D$4,EV_DB[[#This Row],[Category]]="Medium Duty",'Maintenance costs table'!$D$8,EV_DB[[#This Row],[Category]]="Heavy Duty",'Maintenance costs table'!$D$6)} -> 0.18 | L11: No | M11: 68 kWh | N11: 0.22 | O11: 15-80% DCFC (115 kW) 34 min 15-80% (50 kW) 65 min 0-100% 240V L2 (48A) 8 hours 0-100% 240V L2 (30A) ~12 hours | Q11: 254 | R11: {=_xlfn.IFS(EV_DB[[#This Row],[Battery Size, kWh]]>350 & EV_DB[[#This Row],[FHWA Class (2B - 8)]]=8,'iMHZEV table'!$D$4,EV_DB[[#This Row],[Battery Size, kWh]]<=350 & EV_DB[[#This Row],[FHWA Class (2B - 8)]]=8,'iMHZEV table'!$D$5, TRUE, _xlfn.XLOOKUP(EV_DB[[#This Row],[FHWA Class (2B - 8)]],'iMHZEV table'!$A$3:$A$11,'iMHZEV table'!$D$3:$D$11))} -> 10000 | T11: {=_xlfn.IFS(EV_DB[[#This Row],[FHWA Class (2B - 8)]]= "2B",10000,EV_DB[[#This Row],[FHWA Class (2B - 8)]]=3,55000,OR(EV_DB[[#This Row],[FHWA Class (2B - 8)]]=4,EV_DB[[#This Row],[FHWA Class (2B - 8)]]=5), 75000,OR(EV_DB[[#This Row],[FHWA Class (2B - 8)]]=6,EV_DB[[#This Row],[FHWA Class (2B - 8)]]=7),100000,EV_DB[[#This Row],[FHWA Class (2B - 8)]]=8, 150000)} -> 10000 | AF11: =MIN(MAX(EV_DB[[#This Row],[Federal Rebates (iMHZEV) ]],EV_DB[[#This Row],[ON Vehicle Rebates]]),PRODUCT(EV_DB[[#This Row],[Cost, $MSRP CAD]],0.75)) -> 10000 | AG11: =MIN(EV_DB[[#This Row],[Federal Rebates (iMHZEV) ]]+EV_DB[[#This Row],[BC Vehicle Rebates]],PRODUCT(EV_DB[[#This Row],[Cost, $MSRP CAD]],0.75)) -> 20000 | AH11: =MIN(EV_DB[[#This Row],[Federal Rebates (iMHZEV) ]]+EV_DB[[#This Row],[QC Vehicle Rebates]],PRODUCT(EV_DB[[#This Row],[Cost, $MSRP CAD]],0.75)) -> 10000 | AI11: =MIN(MAX(EV_DB[[#This Row],[Federal Rebates (iMHZEV) ]],EV_DB[[#This Row],[AB Vehicle Rebates]]),PRODUCT(EV_DB[[#This Row],[Cost, $MSRP CAD]],0.75)) -> 10000 | AJ11: =MIN(MAX(EV_DB[[#This Row],[Federal Rebates (iMHZEV) ]],EV_DB[[#This Row],[SC Vehicle Rebates]]),PRODUCT(EV_DB[[#This Row],[Cost, $MSRP CAD]],0.75)) -> 10000 | AK11: =MIN(MAX(EV_DB[[#This Row],[Federal Rebates (iMHZEV) ]],EV_DB[[#This Row],[NS Vehicle Rebates]]),PRODUCT(EV_DB[[#This Row],[Cost, $MSRP CAD]],0.75)) -> 10000 | AL11: =MIN(MAX(EV_DB[[#This Row],[Federal Rebates (iMHZEV) ]],EV_DB[[#This Row],[NB Vehicle Rebates]]),PRODUCT(EV_DB[[#This Row],[Cost, $MSRP CAD]],0.75)) -> 10000 | AM11: =MIN(MAX(EV_DB[[#This Row],[Federal Rebates (iMHZEV) ]],EV_DB[[#This Row],[MB Vehicle Rebates]]),PRODUCT(EV_DB[[#This Row],[Cost, $MSRP CAD]],0.75)) -> 10000 | AN11: =MIN(MAX(EV_DB[[#This Row],[Federal Rebates (iMHZEV) ]],EV_DB[[#This Row],[PEI Vehicle Rebates]]),PRODUCT(EV_DB[[#This Row],[Cost, $MSRP CAD]],0.75)) -> 10000 | AO11: =MIN(MAX(EV_DB[[#This Row],[Federal Rebates (iMHZEV) ]],EV_DB[[#This Row],[NL Vehicle Rebates]]),PRODUCT(EV_DB[[#This Row],[Cost, $MSRP CAD]],0.75)) -> 10000 | AP11: =MIN(MAX(EV_DB[[#This Row],[Federal Rebates (iMHZEV) ]]+EV_DB[[#This Row],[YT Vehicle Rebates]]),PRODUCT(EV_DB[[#This Row],[Cost, $MSRP CAD]],0.75)) -> 10000 | AQ11: =MIN(MAX(EV_DB[[#This Row],[Federal Rebates (iMHZEV) ]],EV_DB[[#This Row],[NU Vehicle Rebates]]),PRODUCT(EV_DB[[#This Row],[Cost, $MSRP CAD]],0.75)) -> 10000 | AR11: =MIN(MAX(EV_DB[[#This Row],[Federal Rebates (iMHZEV) ]],EV_DB[[#This Row],[NT Vehicle Rebates]]),PRODUCT(EV_DB[[#This Row],[Cost, $MSRP CAD]],0.75)) -> 10000
A12: GM (Brightdrop) | B12: EV410 | C12: =EV_DB[[#This Row],[Manufacturer ]]& " " &EV_DB[[#This Row],[Model]] -> GM (Brightdrop) EV410 | D12: Delivery Van | E12: 2024 | F12: 2B | G12: {=_xlfn.IFS(OR(EV_DB[[#This Row],[FHWA Class (2B - 8)]]= "2B", EV_DB[[#This Row],[FHWA Class (2B - 8)]]=3), "Light Duty",OR(EV_DB[[#This Row],[FHWA Class (2B - 8)]]=4,EV_DB[[#This Row],[FHWA Class (2B - 8)]]=5,EV_DB[[#This Row],[FHWA Class (2B - 8)]]=6),"Medium Duty",OR(EV_DB[[#This Row],[FHWA Class (2B - 8)]]=7,EV_DB[[#This Row],[FHWA Class (2B - 8)]]=8), "Heavy Duty")} -> Light Duty | H12: 9900 | I12: 2200 | J12: 118650 | K12: {=_xlfn.IFS(EV_DB[[#This Row],[Category]]="Light Duty",'Maintenance costs table'!$D$4,EV_DB[[#This Row],[Category]]="Medium Duty",'Maintenance costs table'!$D$8,EV_DB[[#This Row],[Category]]="Heavy Duty",'Maintenance costs table'!$D$6)} -> 0.18 | L12: No | M12: 173 kWh | N12: 0.25 | Q12: 400 | R12: 40000 | T12: 39546 | AF12: =MIN(MAX(EV_DB[[#This Row],[Federal Rebates (iMHZEV) ]],EV_DB[[#This Row],[ON Vehicle Rebates]]),PRODUCT(EV_DB[[#This Row],[Cost, $MSRP CAD]],0.75)) -> 40000 | AG12: =MIN(EV_DB[[#This Row],[Federal Rebates (iMHZEV) ]]+EV_DB[[#This Row],[BC Vehicle Rebates]],PRODUCT(EV_DB[[#This Row],[Cost, $MSRP CAD]],0.75)) -> 79546 | AH12: =MIN(EV_DB[[#This Row],[Federal Rebates (iMHZEV) ]]+EV_DB[[#This Row],[QC Vehicle Rebates]],PRODUCT(EV_DB[[#This Row],[Cost, $MSRP CAD]],0.75)) -> 40000 | AI12: =MIN(MAX(EV_DB[[#This Row],[Federal Rebates (iMHZEV) ]],EV_DB[[#This Row],[AB Vehicle Rebates]]),PRODUCT(EV_DB[[#This Row],[Cost, $MSRP CAD]],0.75)) -> 40000 | AJ12: =MIN(MAX(EV_DB[[#This Row],[Federal Rebates (iMHZEV) ]],EV_DB[[#This Row],[SC Vehicle Rebates]]),PRODUCT(EV_DB[[#This Row],[Cost, $MSRP CAD]],0.75)) -> 40000 | AK12: =MIN(MAX(EV_DB[[#This Row],[Federal Rebates (iMHZEV) ]],EV_DB[[#This Row],[NS Vehicle Rebates]]),PRODUCT(EV_DB[[#This Row],[Cost, $MSRP CAD]],0.75)) -> 40000 | AL12: =MIN(MAX(EV_DB[[#This Row],[Federal Rebates (iMHZEV) ]],EV_DB[[#This Row],[NB Vehicle Rebates]]),PRODUCT(EV_DB[[#This Row],[Cost, $MSRP CAD]],0.75)) -> 40000 | AM12: =MIN(MAX(EV_DB[[#This Row],[Federal Rebates (iMHZEV) ]],EV_DB[[#This Row],[MB Vehicle Rebates]]),PRODUCT(EV_DB[[#This Row],[Cost, $MSRP CAD]],0.75)) -> 40000 | AN12: =MIN(MAX(EV_DB[[#This Row],[Federal Rebates (iMHZEV) ]],EV_DB[[#This Row],[PEI Vehicle Rebates]]),PRODUCT(EV_DB[[#This Row],[Cost, $MSRP CAD]],0.75)) -> 40000 | AO12: =MIN(MAX(EV_DB[[#This Row],[Federal Rebates (iMHZEV) ]],EV_DB[[#This Row],[NL Vehicle Rebates]]),PRODUCT(EV_DB[[#This Row],[Cost, $MSRP CAD]],0.75)) -> 40000 | AP12: =MIN(MAX(EV_DB[[#This Row],[Federal Rebates (iMHZEV) ]]+EV_DB[[#This Row],[YT Vehicle Rebates]]),PRODUCT(EV_DB[[#This Row],[Cost, $MSRP CAD]],0.75)) -> 40000 | AQ12: =MIN(MAX(EV_DB[[#This Row],[Federal Rebates (iMHZEV) ]],EV_DB[[#This Row],[NU Vehicle Rebates]]),PRODUCT(EV_DB[[#This Row],[Cost, $MSRP CAD]],0.75)) -> 40000 | AR12: =MIN(MAX(EV_DB[[#This Row],[Federal Rebates (iMHZEV) ]],EV_DB[[#This Row],[NT Vehicle Rebates]]),PRODUCT(EV_DB[[#This Row],[Cost, $MSRP CAD]],0.75)) -> 40000
A13: GM (Brightdrop) | B13: EV600 | C13: =EV_DB[[#This Row],[Manufacturer ]]& " " &EV_DB[[#This Row],[Model]] -> GM (Brightdrop) EV600 | D13: Delivery Van | E13: 2024 | F13: 3 | G13: {=_xlfn.IFS(OR(EV_DB[[#This Row],[FHWA Class (2B - 8)]]= "2B", EV_DB[[#This Row],[FHWA Class (2B - 8)]]=3), "Light Duty",OR(EV_DB[[#This Row],[FHWA Class (2B - 8)]]=4,EV_DB[[#This Row],[FHWA Class (2B - 8)]]=5,EV_DB[[#This Row],[FHWA Class (2B - 8)]]=6),"Medium Duty",OR(EV_DB[[#This Row],[FHWA Class (2B - 8)]]=7,EV_DB[[#This Row],[FHWA Class (2B - 8)]]=8), "Heavy Duty")} -> Light Duty | H13: 11000 | I13: 2200 | J13: 136615 | K13: {=_xlfn.IFS(EV_DB[[#This Row],[Category]]="Light Duty",'Maintenance costs table'!$D$4,EV_DB[[#This Row],[Category]]="Medium Duty",'Maintenance costs table'!$D$8,EV_DB[[#This Row],[Category]]="Heavy Duty",'Maintenance costs table'!$D$6)} -> 0.18 | L13: No | M13: 173 kWh | N13: 0.28 | Q13: 400 | R13: {=_xlfn.IFS(EV_DB[[#This Row],[Battery Size, kWh]]>350 & EV_DB[[#This Row],[FHWA Class (2B - 8)]]=8,'iMHZEV table'!$D$4,EV_DB[[#This Row],[Battery Size, kWh]]<=350 & EV_DB[[#This Row],[FHWA Class (2B - 8)]]=8,'iMHZEV table'!$D$5, TRUE, _xlfn.XLOOKUP(EV_DB[[#This Row],[FHWA Class (2B - 8)]],'iMHZEV table'!$A$3:$A$11,'iMHZEV table'!$D$3:$D$11))} -> 40000 | T13: {=_xlfn.IFS(EV_DB[[#This Row],[FHWA Class (2B - 8)]]= "2B",10000,EV_DB[[#This Row],[FHWA Class (2B - 8)]]=3,55000,OR(EV_DB[[#This Row],[FHWA Class (2B - 8)]]=4,EV_DB[[#This Row],[FHWA Class (2B - 8)]]=5), 75000,OR(EV_DB[[#This Row],[FHWA Class (2B - 8)]]=6,EV_DB[[#This Row],[FHWA Class (2B - 8)]]=7),100000,EV_DB[[#This Row],[FHWA Class (2B - 8)]]=8, 150000)} -> 55000 | AF13: =MIN(MAX(EV_DB[[#This Row],[Federal Rebates (iMHZEV) ]],EV_DB[[#This Row],[ON Vehicle Rebates]]),PRODUCT(EV_DB[[#This Row],[Cost, $MSRP CAD]],0.75)) -> 40000 | AG13: =MIN(EV_DB[[#This Row],[Federal Rebates (iMHZEV) ]]+EV_DB[[#This Row],[BC Vehicle Rebates]],PRODUCT(EV_DB[[#This Row],[Cost, $MSRP CAD]],0.75)) -> 95000 | AH13: =MIN(EV_DB[[#This Row],[Federal Rebates (iMHZEV) ]]+EV_DB[[#This Row],[QC Vehicle Rebates]],PRODUCT(EV_DB[[#This Row],[Cost, $MSRP CAD]],0.75)) -> 40000 | AI13: =MIN(MAX(EV_DB[[#This Row],[Federal Rebates (iMHZEV) ]],EV_DB[[#This Row],[AB Vehicle Rebates]]),PRODUCT(EV_DB[[#This Row],[Cost, $MSRP CAD]],0.75)) -> 40000 | AJ13: =MIN(MAX(EV_DB[[#This Row],[Federal Rebates (iMHZEV) ]],EV_DB[[#This Row],[SC Vehicle Rebates]]),PRODUCT(EV_DB[[#This Row],[Cost, $MSRP CAD]],0.75)) -> 40000 | AK13: =MIN(MAX(EV_DB[[#This Row],[Federal Rebates (iMHZEV) ]],EV_DB[[#This Row],[NS Vehicle Rebates]]),PRODUCT(EV_DB[[#This Row],[Cost, $MSRP CAD]],0.75)) -> 40000 | AL13: =MIN(MAX(EV_DB[[#This Row],[Federal Rebates (iMHZEV) ]],EV_DB[[#This Row],[NB Vehicle Rebates]]),PRODUCT(EV_DB[[#This Row],[Cost, $MSRP CAD]],0.75)) -> 40000 | AM13: =MIN(MAX(EV_DB[[#This Row],[Federal Rebates (iMHZEV) ]],EV_DB[[#This Row],[MB Vehicle Rebates]]),PRODUCT(EV_DB[[#This Row],[Cost, $MSRP CAD]],0.75)) -> 40000 | AN13: =MIN(MAX(EV_DB[[#This Row],[Federal Rebates (iMHZEV) ]],EV_DB[[#This Row],[PEI Vehicle Rebates]]),PRODUCT(EV_DB[[#This Row],[Cost, $MSRP CAD]],0.75)) -> 40000 | AO13: =MIN(MAX(EV_DB[[#This Row],[Federal Rebates (iMHZEV) ]],EV_DB[[#This Row],[NL Vehicle Rebates]]),PRODUCT(EV_DB[[#This Row],[Cost, $MSRP CAD]],0.75)) -> 40000 | AP13: =MIN(MAX(EV_DB[[#This Row],[Federal Rebates (iMHZEV) ]]+EV_DB[[#This Row],[YT Vehicle Rebates]]),PRODUCT(EV_DB[[#This Row],[Cost, $MSRP CAD]],0.75)) -> 40000 | AQ13: =MIN(MAX(EV_DB[[#This Row],[Federal Rebates (iMHZEV) ]],EV_DB[[#This Row],[NU Vehicle Rebates]]),PRODUCT(EV_DB[[#This Row],[Cost, $MSRP CAD]],0.75)) -> 40000 | AR13: =MIN(MAX(EV_DB[[#This Row],[Federal Rebates (iMHZEV) ]],EV_DB[[#This Row],[NT Vehicle Rebates]]),PRODUCT(EV_DB[[#This Row],[Cost, $MSRP CAD]],0.75)) -> 40000
A14: Canoo | B14: LDV 190 | C14: =EV_DB[[#This Row],[Manufacturer ]]& " " &EV_DB[[#This Row],[Model]] -> Canoo LDV 190 | D14: Delivery Van | E14: 2024 | F14: 2B | G14: {=_xlfn.IFS(OR(EV_DB[[#This Row],[FHWA Class (2B - 8)]]= "2B", EV_DB[[#This Row],[FHWA Class (2B - 8)]]=3), "Light Duty",OR(EV_DB[[#This Row],[FHWA Class (2B - 8)]]=4,EV_DB[[#This Row],[FHWA Class (2B - 8)]]=5,EV_DB[[#This Row],[FHWA Class (2B - 8)]]=6),"Medium Duty",OR(EV_DB[[#This Row],[FHWA Class (2B - 8)]]=7,EV_DB[[#This Row],[FHWA Class (2B - 8)]]=8), "Heavy Duty")} -> Light Duty | H14: 6525 | I14: 1763 | J14: 43000 | K14: {=_xlfn.IFS(EV_DB[[#This Row],[Category]]="Light Duty",'Maintenance costs table'!$D$4,EV_DB[[#This Row],[Category]]="Medium Duty",'Maintenance costs table'!$D$8,EV_DB[[#This Row],[Category]]="Heavy Duty",'Maintenance costs table'!$D$6)} -> 0.18 | L14: No | M14: ~80 kWh | N14: 0.24 | Q14: 321 | R14: {=_xlfn.IFS(EV_DB[[#This Row],[Battery Size, kWh]]>350 & EV_DB[[#This Row],[FHWA Class (2B - 8)]]=8,'iMHZEV table'!$D$4,EV_DB[[#This Row],[Battery Size, kWh]]<=350 & EV_DB[[#This Row],[FHWA Class (2B - 8)]]=8,'iMHZEV table'!$D$5, TRUE, _xlfn.XLOOKUP(EV_DB[[#This Row],[FHWA Class (2B - 8)]],'iMHZEV table'!$A$3:$A$11,'iMHZEV table'!$D$3:$D$11))} -> 10000 | T14: {=_xlfn.IFS(EV_DB[[#This Row],[FHWA Class (2B - 8)]]= "2B",10000,EV_DB[[#This Row],[FHWA Class (2B - 8)]]=3,55000,OR(EV_DB[[#This Row],[FHWA Class (2B - 8)]]=4,EV_DB[[#This Row],[FHWA Class (2B - 8)]]=5), 75000,OR(EV_DB[[#This Row],[FHWA Class (2B - 8)]]=6,EV_DB[[#This Row],[FHWA Class (2B - 8)]]=7),100000,EV_DB[[#This Row],[FHWA Class (2B - 8)]]=8, 150000)} -> 10000 | AF14: =MIN(MAX(EV_DB[[#This Row],[Federal Rebates (iMHZEV) ]],EV_DB[[#This Row],[ON Vehicle Rebates]]),PRODUCT(EV_DB[[#This Row],[Cost, $MSRP CAD]],0.75)) -> 10000 | AG14: =MIN(EV_DB[[#This Row],[Federal Rebates (iMHZEV) ]]+EV_DB[[#This Row],[BC Vehicle Rebates]],PRODUCT(EV_DB[[#This Row],[Cost, $MSRP CAD]],0.75)) -> 20000 | AH14: =MIN(EV_DB[[#This Row],[Federal Rebates (iMHZEV) ]]+EV_DB[[#This Row],[QC Vehicle Rebates]],PRODUCT(EV_DB[[#This Row],[Cost, $MSRP CAD]],0.75)) -> 10000 | AI14: =MIN(MAX(EV_DB[[#This Row],[Federal Rebates (iMHZEV) ]],EV_DB[[#This Row],[AB Vehicle Rebates]]),PRODUCT(EV_DB[[#This Row],[Cost, $MSRP CAD]],0.75)) -> 10000 | AJ14: =MIN(MAX(EV_DB[[#This Row],[Federal Rebates (iMHZEV) ]],EV_DB[[#This Row],[SC Vehicle Rebates]]),PRODUCT(EV_DB[[#This Row],[Cost, $MSRP CAD]],0.75)) -> 10000 | AK14: =MIN(MAX(EV_DB[[#This Row],[Federal Rebates (iMHZEV) ]],EV_DB[[#This Row],[NS Vehicle Rebates]]),PRODUCT(EV_DB[[#This Row],[Cost, $MSRP CAD]],0.75)) -> 10000 | AL14: =MIN(MAX(EV_DB[[#This Row],[Federal Rebates (iMHZEV) ]],EV_DB[[#This Row],[NB Vehicle Rebates]]),PRODUCT(EV_DB[[#This Row],[Cost, $MSRP CAD]],0.75)) -> 10000 | AM14: =MIN(MAX(EV_DB[[#This Row],[Federal Rebates (iMHZEV) ]],EV_DB[[#This Row],[MB Vehicle Rebates]]),PRODUCT(EV_DB[[#This Row],[Cost, $MSRP CAD]],0.75)) -> 10000 | AN14: =MIN(MAX(EV_DB[[#This Row],[Federal Rebates (iMHZEV) ]],EV_DB[[#This Row],[PEI Vehicle Rebates]]),PRODUCT(EV_DB[[#This Row],[Cost, $MSRP CAD]],0.75)) -> 10000 | AO14: =MIN(MAX(EV_DB[[#This Row],[Federal Rebates (iMHZEV) ]],EV_DB[[#This Row],[NL Vehicle Rebates]]),PRODUCT(EV_DB[[#This Row],[Cost, $MSRP CAD]],0.75)) -> 10000 | AP14: =MIN(MAX(EV_DB[[#This Row],[Federal Rebates (iMHZEV) ]]+EV_DB[[#This Row],[YT Vehicle Rebates]]),PRODUCT(EV_DB[[#This Row],[Cost, $MSRP CAD]],0.75)) -> 10000 | AQ14: =MIN(MAX(EV_DB[[#This Row],[Federal Rebates (iMHZEV) ]],EV_DB[[#This Row],[NU Vehicle Rebates]]),PRODUCT(EV_DB[[#This Row],[Cost, $MSRP CAD]],0.75)) -> 10000 | AR14: =MIN(MAX(EV_DB[[#This Row],[Federal Rebates (iMHZEV) ]],EV_DB[[#This Row],[NT Vehicle Rebates]]),PRODUCT(EV_DB[[#This Row],[Cost, $MSRP CAD]],0.75)) -> 10000
A15: Canoo | B15: LDV 130 | C15: =EV_DB[[#This Row],[Manufacturer ]]& " " &EV_DB[[#This Row],[Model]] -> Canoo LDV 130 | D15: Service Van | E15: 2024 | F15: 2B | G15: {=_xlfn.IFS(OR(EV_DB[[#This Row],[FHWA Class (2B - 8)]]= "2B", EV_DB[[#This Row],[FHWA Class (2B - 8)]]=3), "Light Duty",OR(EV_DB[[#This Row],[FHWA Class (2B - 8)]]=4,EV_DB[[#This Row],[FHWA Class (2B - 8)]]=5,EV_DB[[#This Row],[FHWA Class (2B - 8)]]=6),"Medium Duty",OR(EV_DB[[#This Row],[FHWA Class (2B - 8)]]=7,EV_DB[[#This Row],[FHWA Class (2B - 8)]]=8), "Heavy Duty")} -> Light Duty | H15: 6525 | I15: 1763 | J15: 43000 | K15: {=_xlfn.IFS(EV_DB[[#This Row],[Category]]="Light Duty",'Maintenance costs table'!$D$4,EV_DB[[#This Row],[Category]]="Medium Duty",'Maintenance costs table'!$D$8,EV_DB[[#This Row],[Category]]="Heavy Duty",'Maintenance costs table'!$D$6)} -> 0.18 | L15: No | M15: 80kwh | N15: 0.24 | Q15: 321 | R15: {=_xlfn.IFS(EV_DB[[#This Row],[Battery Size, kWh]]>350 & EV_DB[[#This Row],[FHWA Class (2B - 8)]]=8,'iMHZEV table'!$D$4,EV_DB[[#This Row],[Battery Size, kWh]]<=350 & EV_DB[[#This Row],[FHWA Class (2B - 8)]]=8,'iMHZEV table'!$D$5, TRUE, _xlfn.XLOOKUP(EV_DB[[#This Row],[FHWA Class (2B - 8)]],'iMHZEV table'!$A$3:$A$11,'iMHZEV table'!$D$3:$D$11))} -> 10000 | T15: {=_xlfn.IFS(EV_DB[[#This Row],[FHWA Class (2B - 8)]]= "2B",10000,EV_DB[[#This Row],[FHWA Class (2B - 8)]]=3,55000,OR(EV_DB[[#This Row],[FHWA Class (2B - 8)]]=4,EV_DB[[#This Row],[FHWA Class (2B - 8)]]=5), 75000,OR(EV_DB[[#This Row],[FHWA Class (2B - 8)]]=6,EV_DB[[#This Row],[FHWA Class (2B - 8)]]=7),100000,EV_DB[[#This Row],[FHWA Class (2B - 8)]]=8, 150000)} -> 10000 | AF15: =MIN(MAX(EV_DB[[#This Row],[Federal Rebates (iMHZEV) ]],EV_DB[[#This Row],[ON Vehicle Rebates]]),PRODUCT(EV_DB[[#This Row],[Cost, $MSRP CAD]],0.75)) -> 10000 | AG15: =MIN(EV_DB[[#This Row],[Federal Rebates (iMHZEV) ]]+EV_DB[[#This Row],[BC Vehicle Rebates]],PRODUCT(EV_DB[[#This Row],[Cost, $MSRP CAD]],0.75)) -> 20000 | AH15: =MIN(EV_DB[[#This Row],[Federal Rebates (iMHZEV) ]]+EV_DB[[#This Row],[QC Vehicle Rebates]],PRODUCT(EV_DB[[#This Row],[Cost, $MSRP CAD]],0.75)) -> 10000 | AI15: =MIN(MAX(EV_DB[[#This Row],[Federal Rebates (iMHZEV) ]],EV_DB[[#This Row],[AB Vehicle Rebates]]),PRODUCT(EV_DB[[#This Row],[Cost, $MSRP CAD]],0.75)) -> 10000 | AJ15: =MIN(MAX(EV_DB[[#This Row],[Federal Rebates (iMHZEV) ]],EV_DB[[#This Row],[SC Vehicle Rebates]]),PRODUCT(EV_DB[[#This Row],[Cost, $MSRP CAD]],0.75)) -> 10000 | AK15: =MIN(MAX(EV_DB[[#This Row],[Federal Rebates (iMHZEV) ]],EV_DB[[#This Row],[NS Vehicle Rebates]]),PRODUCT(EV_DB[[#This Row],[Cost, $MSRP CAD]],0.75)) -> 10000 | AL15: =MIN(MAX(EV_DB[[#This Row],[Federal Rebates (iMHZEV) ]],EV_DB[[#This Row],[NB Vehicle Rebates]]),PRODUCT(EV_DB[[#This Row],[Cost, $MSRP CAD]],0.75)) -> 10000 | AM15: =MIN(MAX(EV_DB[[#This Row],[Federal Rebates (iMHZEV) ]],EV_DB[[#This Row],[MB Vehicle Rebates]]),PRODUCT(EV_DB[[#This Row],[Cost, $MSRP CAD]],0.75)) -> 10000 | AN15: =MIN(MAX(EV_DB[[#This Row],[Federal Rebates (iMHZEV) ]],EV_DB[[#This Row],[PEI Vehicle Rebates]]),PRODUCT(EV_DB[[#This Row],[Cost, $MSRP CAD]],0.75)) -> 10000 | AO15: =MIN(MAX(EV_DB[[#This Row],[Federal Rebates (iMHZEV) ]],EV_DB[[#This Row],[NL Vehicle Rebates]]),PRODUCT(EV_DB[[#This Row],[Cost, $MSRP CAD]],0.75)) -> 10000 | AP15: =MIN(MAX(EV_DB[[#This Row],[Federal Rebates (iMHZEV) ]]+EV_DB[[#This Row],[YT Vehicle Rebates]]),PRODUCT(EV_DB[[#This Row],[Cost, $MSRP CAD]],0.75)) -> 10000 | AQ15: =MIN(MAX(EV_DB[[#This Row],[Federal Rebates (iMHZEV) ]],EV_DB[[#This Row],[NU Vehicle Rebates]]),PRODUCT(EV_DB[[#This Row],[Cost, $MSRP CAD]],0.75)) -> 10000 | AR15: =MIN(MAX(EV_DB[[#This Row],[Federal Rebates (iMHZEV) ]],EV_DB[[#This Row],[NT Vehicle Rebates]]),PRODUCT(EV_DB[[#This Row],[Cost, $MSRP CAD]],0.75)) -> 10000
A16: Rivian | B16: EDV-500 | C16: =EV_DB[[#This Row],[Manufacturer ]]& " " &EV_DB[[#This Row],[Model]] -> Rivian EDV-500 | D16: Delivery Van | E16: 2025 | F16: 2B | G16: {=_xlfn.IFS(OR(EV_DB[[#This Row],[FHWA Class (2B - 8)]]= "2B", EV_DB[[#This Row],[FHWA Class (2B - 8)]]=3), "Light Duty",OR(EV_DB[[#This Row],[FHWA Class (2B - 8)]]=4,EV_DB[[#This Row],[FHWA Class (2B - 8)]]=5,EV_DB[[#This Row],[FHWA Class (2B - 8)]]=6),"Medium Duty",OR(EV_DB[[#This Row],[FHWA Class (2B - 8)]]=7,EV_DB[[#This Row],[FHWA Class (2B - 8)]]=8), "Heavy Duty")} -> Light Duty | H16: 9,500 | I16: 2734 | J16: 90000 | K16: {=_xlfn.IFS(EV_DB[[#This Row],[Category]]="Light Duty",'Maintenance costs table'!$D$4,EV_DB[[#This Row],[Category]]="Medium Duty",'Maintenance costs table'!$D$8,EV_DB[[#This Row],[Category]]="Heavy Duty",'Maintenance costs table'!$D$6)} -> 0.18 | L16: No | M16: 110kwh | N16: 0.3 | Q16: 259 | R16: {=_xlfn.IFS(EV_DB[[#This Row],[Battery Size, kWh]]>350 & EV_DB[[#This Row],[FHWA Class (2B - 8)]]=8,'iMHZEV table'!$D$4,EV_DB[[#This Row],[Battery Size, kWh]]<=350 & EV_DB[[#This Row],[FHWA Class (2B - 8)]]=8,'iMHZEV table'!$D$5, TRUE, _xlfn.XLOOKUP(EV_DB[[#This Row],[FHWA Class (2B - 8)]],'iMHZEV table'!$A$3:$A$11,'iMHZEV table'!$D$3:$D$11))} -> 10000 | T16: {=_xlfn.IFS(EV_DB[[#This Row],[FHWA Class (2B - 8)]]= "2B",10000,EV_DB[[#This Row],[FHWA Class (2B - 8)]]=3,55000,OR(EV_DB[[#This Row],[FHWA Class (2B - 8)]]=4,EV_DB[[#This Row],[FHWA Class (2B - 8)]]=5), 75000,OR(EV_DB[[#This Row],[FHWA Class (2B - 8)]]=6,EV_DB[[#This Row],[FHWA Class (2B - 8)]]=7),100000,EV_DB[[#This Row],[FHWA Class (2B - 8)]]=8, 150000)} -> 10000 | AF16: =MIN(MAX(EV_DB[[#This Row],[Federal Rebates (iMHZEV) ]],EV_DB[[#This Row],[ON Vehicle Rebates]]),PRODUCT(EV_DB[[#This Row],[Cost, $MSRP CAD]],0.75)) -> 10000 | AG16: =MIN(EV_DB[[#This Row],[Federal Rebates (iMHZEV) ]]+EV_DB[[#This Row],[BC Vehicle Rebates]],PRODUCT(EV_DB[[#This Row],[Cost, $MSRP CAD]],0.75)) -> 20000 | AH16: =MIN(EV_DB[[#This Row],[Federal Rebates (iMHZEV) ]]+EV_DB[[#This Row],[QC Vehicle Rebates]],PRODUCT(EV_DB[[#This Row],[Cost, $MSRP CAD]],0.75)) -> 10000 | AI16: =MIN(MAX(EV_DB[[#This Row],[Federal Rebates (iMHZEV) ]],EV_DB[[#This Row],[AB Vehicle Rebates]]),PRODUCT(EV_DB[[#This Row],[Cost, $MSRP CAD]],0.75)) -> 10000 | AJ16: =MIN(MAX(EV_DB[[#This Row],[Federal Rebates (iMHZEV) ]],EV_DB[[#This Row],[SC Vehicle Rebates]]),PRODUCT(EV_DB[[#This Row],[Cost, $MSRP CAD]],0.75)) -> 10000 | AK16: =MIN(MAX(EV_DB[[#This Row],[Federal Rebates (iMHZEV) ]],EV_DB[[#This Row],[NS Vehicle Rebates]]),PRODUCT(EV_DB[[#This Row],[Cost, $MSRP CAD]],0.75)) -> 10000 | AL16: =MIN(MAX(EV_DB[[#This Row],[Federal Rebates (iMHZEV) ]],EV_DB[[#This Row],[NB Vehicle Rebates]]),PRODUCT(EV_DB[[#This Row],[Cost, $MSRP CAD]],0.75)) -> 10000 | AM16: =MIN(MAX(EV_DB[[#This Row],[Federal Rebates (iMHZEV) ]],EV_DB[[#This Row],[MB Vehicle Rebates]]),PRODUCT(EV_DB[[#This Row],[Cost, $MSRP CAD]],0.75)) -> 10000 | AN16: =MIN(MAX(EV_DB[[#This Row],[Federal Rebates (iMHZEV) ]],EV_DB[[#This Row],[PEI Vehicle Rebates]]),PRODUCT(EV_DB[[#This Row],[Cost, $MSRP CAD]],0.75)) -> 10000 | AO16: =MIN(MAX(EV_DB[[#This Row],[Federal Rebates (iMHZEV) ]],EV_DB[[#This Row],[NL Vehicle Rebates]]),PRODUCT(EV_DB[[#This Row],[Cost, $MSRP CAD]],0.75)) -> 10000 | AP16: =MIN(MAX(EV_DB[[#This Row],[Federal Rebates (iMHZEV) ]]+EV_DB[[#This Row],[YT Vehicle Rebates]]),PRODUCT(EV_DB[[#This Row],[Cost, $MSRP CAD]],0.75)) -> 10000 | AQ16: =MIN(MAX(EV_DB[[#This Row],[Federal Rebates (iMHZEV) ]],EV_DB[[#This Row],[NU Vehicle Rebates]]),PRODUCT(EV_DB[[#This Row],[Cost, $MSRP CAD]],0.75)) -> 10000 | AR16: =MIN(MAX(EV_DB[[#This Row],[Federal Rebates (iMHZEV) ]],EV_DB[[#This Row],[NT Vehicle Rebates]]),PRODUCT(EV_DB[[#This Row],[Cost, $MSRP CAD]],0.75)) -> 10000
A17: GreenPower | B17: EV Star | C17: =EV_DB[[#This Row],[Manufacturer ]]& " " &EV_DB[[#This Row],[Model]] -> GreenPower EV Star | D17: Delivery Van | E17: 2023 | F17: 4 | G17: {=_xlfn.IFS(OR(EV_DB[[#This Row],[FHWA Class (2B - 8)]]= "2B", EV_DB[[#This Row],[FHWA Class (2B - 8)]]=3), "Light Duty",OR(EV_DB[[#This Row],[FHWA Class (2B - 8)]]=4,EV_DB[[#This Row],[FHWA Class (2B - 8)]]=5,EV_DB[[#This Row],[FHWA Class (2B - 8)]]=6),"Medium Duty",OR(EV_DB[[#This Row],[FHWA Class (2B - 8)]]=7,EV_DB[[#This Row],[FHWA Class (2B - 8)]]=8), "Heavy Duty")} -> Medium Duty | H17: 7000 | I17: 7000 | J17: 174900 | K17: {=_xlfn.IFS(EV_DB[[#This Row],[Category]]="Light Duty",'Maintenance costs table'!$D$4,EV_DB[[#This Row],[Category]]="Medium Duty",'Maintenance costs table'!$D$8,EV_DB[[#This Row],[Category]]="Heavy Duty",'Maintenance costs table'!$D$6)} -> 0.25 | L17: No | M17: 118 kwh | N17: 0.26 | O17: Dual (AC/DC) Level-2, J1772, 19.2 kW AC, ~8 hrs DCFC, CCS-1, 60 kW, ~2 hrs Wireless DC (option), 60 kW, ~2 hrs | Q17: 241 | R17: {=_xlfn.IFS(EV_DB[[#This Row],[Battery Size, kWh]]>350 & EV_DB[[#This Row],[FHWA Class (2B - 8)]]=8,'iMHZEV table'!$D$4,EV_DB[[#This Row],[Battery Size, kWh]]<=350 & EV_DB[[#This Row],[FHWA Class (2B - 8)]]=8,'iMHZEV table'!$D$5, TRUE, _xlfn.XLOOKUP(EV_DB[[#This Row],[FHWA Class (2B - 8)]],'iMHZEV table'!$A$3:$A$11,'iMHZEV table'!$D$3:$D$11))} -> 75000 | T17: {=_xlfn.IFS(EV_DB[[#This Row],[FHWA Class (2B - 8)]]= "2B",10000,EV_DB[[#This Row],[FHWA Class (2B - 8)]]=3,55000,OR(EV_DB[[#This Row],[FHWA Class (2B - 8)]]=4,EV_DB[[#This Row],[FHWA Class (2B - 8)]]=5), 75000,OR(EV_DB[[#This Row],[FHWA Class (2B - 8)]]=6,EV_DB[[#This Row],[FHWA Class (2B - 8)]]=7),100000,EV_DB[[#This Row],[FHWA Class (2B - 8)]]=8, 150000)} -> 75000 | AF17: =MIN(MAX(EV_DB[[#This Row],[Federal Rebates (iMHZEV) ]],EV_DB[[#This Row],[ON Vehicle Rebates]]),PRODUCT(EV_DB[[#This Row],[Cost, $MSRP CAD]],0.75)) -> 75000 | AG17: =MIN(EV_DB[[#This Row],[Federal Rebates (iMHZEV) ]]+EV_DB[[#This Row],[BC Vehicle Rebates]],PRODUCT(EV_DB[[#This Row],[Cost, $MSRP CAD]],0.75)) -> 131175 | AH17: =MIN(EV_DB[[#This Row],[Federal Rebates (iMHZEV) ]]+EV_DB[[#This Row],[QC Vehicle Rebates]],PRODUCT(EV_DB[[#This Row],[Cost, $MSRP CAD]],0.75)) -> 75000 | AI17: =MIN(MAX(EV_DB[[#This Row],[Federal Rebates (iMHZEV) ]],EV_DB[[#This Row],[AB Vehicle Rebates]]),PRODUCT(EV_DB[[#This Row],[Cost, $MSRP CAD]],0.75)) -> 75000 | AJ17: =MIN(MAX(EV_DB[[#This Row],[Federal Rebates (iMHZEV) ]],EV_DB[[#This Row],[SC Vehicle Rebates]]),PRODUCT(EV_DB[[#This Row],[Cost, $MSRP CAD]],0.75)) -> 75000 | AK17: =MIN(MAX(EV_DB[[#This Row],[Federal Rebates (iMHZEV) ]],EV_DB[[#This Row],[NS Vehicle Rebates]]),PRODUCT(EV_DB[[#This Row],[Cost, $MSRP CAD]],0.75)) -> 75000 | AL17: =MIN(MAX(EV_DB[[#This Row],[Federal Rebates (iMHZEV) ]],EV_DB[[#This Row],[NB Vehicle Rebates]]),PRODUCT(EV_DB[[#This Row],[Cost, $MSRP CAD]],0.75)) -> 75000 | AM17: =MIN(MAX(EV_DB[[#This Row],[Federal Rebates (iMHZEV) ]],EV_DB[[#This Row],[MB Vehicle Rebates]]),PRODUCT(EV_DB[[#This Row],[Cost, $MSRP CAD]],0.75)) -> 75000 | AN17: =MIN(MAX(EV_DB[[#This Row],[Federal Rebates (iMHZEV) ]],EV_DB[[#This Row],[PEI Vehicle Rebates]]),PRODUCT(EV_DB[[#This Row],[Cost, $MSRP CAD]],0.75)) -> 75000 | AO17: =MIN(MAX(EV_DB[[#This Row],[Federal Rebates (iMHZEV) ]],EV_DB[[#This Row],[NL Vehicle Rebates]]),PRODUCT(EV_DB[[#This Row],[Cost, $MSRP CAD]],0.75)) -> 75000 | AP17: =MIN(MAX(EV_DB[[#This Row],[Federal Rebates (iMHZEV) ]]+EV_DB[[#This Row],[YT Vehicle Rebates]]),PRODUCT(EV_DB[[#This Row],[Cost, $MSRP CAD]],0.75)) -> 75000 | AQ17: =MIN(MAX(EV_DB[[#This Row],[Federal Rebates (iMHZEV) ]],EV_DB[[#This Row],[NU Vehicle Rebates]]),PRODUCT(EV_DB[[#This Row],[Cost, $MSRP CAD]],0.75)) -> 75000 | AR17: =MIN(MAX(EV_DB[[#This Row],[Federal Rebates (iMHZEV) ]],EV_DB[[#This Row],[NT Vehicle Rebates]]),PRODUCT(EV_DB[[#This Row],[Cost, $MSRP CAD]],0.75)) -> 75000
A18: GreenPower | B18: EV STAR REEFERX | C18: =EV_DB[[#This Row],[Manufacturer ]]& " " &EV_DB[[#This Row],[Model]] -> GreenPower EV STAR REEFERX | D18: Delivery Van | E18: 2024 | F18: 4 | G18: {=_xlfn.IFS(OR(EV_DB[[#This Row],[FHWA Class (2B - 8)]]= "2B", EV_DB[[#This Row],[FHWA Class (2B - 8)]]=3), "Light Duty",OR(EV_DB[[#This Row],[FHWA Class (2B - 8)]]=4,EV_DB[[#This Row],[FHWA Class (2B - 8)]]=5,EV_DB[[#This Row],[FHWA Class (2B - 8)]]=6),"Medium Duty",OR(EV_DB[[#This Row],[FHWA Class (2B - 8)]]=7,EV_DB[[#This Row],[FHWA Class (2B - 8)]]=8), "Heavy Duty")} -> Medium Duty | H18: 6500 | I18: 5500 | J18: 190000 | K18: {=_xlfn.IFS(EV_DB[[#This Row],[Category]]="Light Duty",'Maintenance costs table'!$D$4,EV_DB[[#This Row],[Category]]="Medium Duty",'Maintenance costs table'!$D$8,EV_DB[[#This Row],[Category]]="Heavy Duty",'Maintenance costs table'!$D$6)} -> 0.25 | L18: Yes | M18: 118 | N18: 0.26 | O18: 8 hours at level 2 2 hours at level 3 | Q18: 241 | R18: {=_xlfn.IFS(EV_DB[[#This Row],[Battery Size, kWh]]>350 & EV_DB[[#This Row],[FHWA Class (2B - 8)]]=8,'iMHZEV table'!$D$4,EV_DB[[#This Row],[Battery Size, kWh]]<=350 & EV_DB[[#This Row],[FHWA Class (2B - 8)]]=8,'iMHZEV table'!$D$5, TRUE, _xlfn.XLOOKUP(EV_DB[[#This Row],[FHWA Class (2B - 8)]],'iMHZEV table'!$A$3:$A$11,'iMHZEV table'!$D$3:$D$11))} -> 75000 | T18: {=_xlfn.IFS(EV_DB[[#This Row],[FHWA Class (2B - 8)]]= "2B",10000,EV_DB[[#This Row],[FHWA Class (2B - 8)]]=3,55000,OR(EV_DB[[#This Row],[FHWA Class (2B - 8)]]=4,EV_DB[[#This Row],[FHWA Class (2B - 8)]]=5), 75000,OR(EV_DB[[#This Row],[FHWA Class (2B - 8)]]=6,EV_DB[[#This Row],[FHWA Class (2B - 8)]]=7),100000,EV_DB[[#This Row],[FHWA Class (2B - 8)]]=8, 150000)} -> 75000 | AF18: =MIN(MAX(EV_DB[[#This Row],[Federal Rebates (iMHZEV) ]],EV_DB[[#This Row],[ON Vehicle Rebates]]),PRODUCT(EV_DB[[#This Row],[Cost, $MSRP CAD]],0.75)) -> 75000 | AG18: =MIN(EV_DB[[#This Row],[Federal Rebates (iMHZEV) ]]+EV_DB[[#This Row],[BC Vehicle Rebates]],PRODUCT(EV_DB[[#This Row],[Cost, $MSRP CAD]],0.75)) -> 142500 | AH18: =MIN(EV_DB[[#This Row],[Federal Rebates (iMHZEV) ]]+EV_DB[[#This Row],[QC Vehicle Rebates]],PRODUCT(EV_DB[[#This Row],[Cost, $MSRP CAD]],0.75)) -> 75000 | AI18: =MIN(MAX(EV_DB[[#This Row],[Federal Rebates (iMHZEV) ]],EV_DB[[#This Row],[AB Vehicle Rebates]]),PRODUCT(EV_DB[[#This Row],[Cost, $MSRP CAD]],0.75)) -> 75000 | AJ18: =MIN(MAX(EV_DB[[#This Row],[Federal Rebates (iMHZEV) ]],EV_DB[[#This Row],[SC Vehicle Rebates]]),PRODUCT(EV_DB[[#This Row],[Cost, $MSRP CAD]],0.75)) -> 75000 | AK18: =MIN(MAX(EV_DB[[#This Row],[Federal Rebates (iMHZEV) ]],EV_DB[[#This Row],[NS Vehicle Rebates]]),PRODUCT(EV_DB[[#This Row],[Cost, $MSRP CAD]],0.75)) -> 75000 | AL18: =MIN(MAX(EV_DB[[#This Row],[Federal Rebates (iMHZEV) ]],EV_DB[[#This Row],[NB Vehicle Rebates]]),PRODUCT(EV_DB[[#This Row],[Cost, $MSRP CAD]],0.75)) -> 75000 | AM18: =MIN(MAX(EV_DB[[#This Row],[Federal Rebates (iMHZEV) ]],EV_DB[[#This Row],[MB Vehicle Rebates]]),PRODUCT(EV_DB[[#This Row],[Cost, $MSRP CAD]],0.75)) -> 75000 | AN18: =MIN(MAX(EV_DB[[#This Row],[Federal Rebates (iMHZEV) ]],EV_DB[[#This Row],[PEI Vehicle Rebates]]),PRODUCT(EV_DB[[#This Row],[Cost, $MSRP CAD]],0.75)) -> 75000 | AO18: =MIN(MAX(EV_DB[[#This Row],[Federal Rebates (iMHZEV) ]],EV_DB[[#This Row],[NL Vehicle Rebates]]),PRODUCT(EV_DB[[#This Row],[Cost, $MSRP CAD]],0.75)) -> 75000 | AP18: =MIN(MAX(EV_DB[[#This Row],[Federal Rebates (iMHZEV) ]]+EV_DB[[#This Row],[YT Vehicle Rebates]]),PRODUCT(EV_DB[[#This Row],[Cost, $MSRP CAD]],0.75)) -> 75000 | AQ18: =MIN(MAX(EV_DB[[#This Row],[Federal Rebates (iMHZEV) ]],EV_DB[[#This Row],[NU Vehicle Rebates]]),PRODUCT(EV_DB[[#This Row],[Cost, $MSRP CAD]],0.75)) -> 75000 | AR18: =MIN(MAX(EV_DB[[#This Row],[Federal Rebates (iMHZEV) ]],EV_DB[[#This Row],[NT Vehicle Rebates]]),PRODUCT(EV_DB[[#This Row],[Cost, $MSRP CAD]],0.75)) -> 75000
A19: GreenPower | B19: EV Star Utility Truck | C19: =EV_DB[[#This Row],[Manufacturer ]]& " " &EV_DB[[#This Row],[Model]] -> GreenPower EV Star Utility Truck | D19: Utility Truck | E19: 2024 | F19: 4 | G19: {=_xlfn.IFS(OR(EV_DB[[#This Row],[FHWA Class (2B - 8)]]= "2B", EV_DB[[#This Row],[FHWA Class (2B - 8)]]=3), "Light Duty",OR(EV_DB[[#This Row],[FHWA Class (2B - 8)]]=4,EV_DB[[#This Row],[FHWA Class (2B - 8)]]=5,EV_DB[[#This Row],[FHWA Class (2B - 8)]]=6),"Medium Duty",OR(EV_DB[[#This Row],[FHWA Class (2B - 8)]]=7,EV_DB[[#This Row],[FHWA Class (2B - 8)]]=8), "Heavy Duty")} -> Medium Duty | H19: 6000 | I19: 6000 | J19: 190000 | K19: {=_xlfn.IFS(EV_DB[[#This Row],[Category]]="Light Duty",'Maintenance costs table'!$D$4,EV_DB[[#This Row],[Category]]="Medium Duty",'Maintenance costs table'!$D$8,EV_DB[[#This Row],[Category]]="Heavy Duty",'Maintenance costs table'!$D$6)} -> 0.25 | L19: No | M19: 118 | N19: 0.26 | O19: DC fast charge at 60 kW in around two hours At Level 2, up to 19.2 kW AC, it can charge in around 8 hours. | Q19: 241 | R19: {=_xlfn.IFS(EV_DB[[#This Row],[Battery Size, kWh]]>350 & EV_DB[[#This Row],[FHWA Class (2B - 8)]]=8,'iMHZEV table'!$D$4,EV_DB[[#This Row],[Battery Size, kWh]]<=350 & EV_DB[[#This Row],[FHWA Class (2B - 8)]]=8,'iMHZEV table'!$D$5, TRUE, _xlfn.XLOOKUP(EV_DB[[#This Row],[FHWA Class (2B - 8)]],'iMHZEV table'!$A$3:$A$11,'iMHZEV table'!$D$3:$D$11))} -> 75000 | T19: {=_xlfn.IFS(EV_DB[[#This Row],[FHWA Class (2B - 8)]]= "2B",10000,EV_DB[[#This Row],[FHWA Class (2B - 8)]]=3,55000,OR(EV_DB[[#This Row],[FHWA Class (2B - 8)]]=4,EV_DB[[#This Row],[FHWA Class (2B - 8)]]=5), 75000,OR(EV_DB[[#This Row],[FHWA Class (2B - 8)]]=6,EV_DB[[#This Row],[FHWA Class (2B - 8)]]=7),100000,EV_DB[[#This Row],[FHWA Class (2B - 8)]]=8, 150000)} -> 75000 | AF19: =MIN(MAX(EV_DB[[#This Row],[Federal Rebates (iMHZEV) ]],EV_DB[[#This Row],[ON Vehicle Rebates]]),PRODUCT(EV_DB[[#This Row],[Cost, $MSRP CAD]],0.75)) -> 75000 | AG19: =MIN(EV_DB[[#This Row],[Federal Rebates (iMHZEV) ]]+EV_DB[[#This Row],[BC Vehicle Rebates]],PRODUCT(EV_DB[[#This Row],[Cost, $MSRP CAD]],0.75)) -> 142500 | AH19: =MIN(EV_DB[[#This Row],[Federal Rebates (iMHZEV) ]]+EV_DB[[#This Row],[QC Vehicle Rebates]],PRODUCT(EV_DB[[#This Row],[Cost, $MSRP CAD]],0.75)) -> 75000 | AI19: =MIN(MAX(EV_DB[[#This Row],[Federal Rebates (iMHZEV) ]],EV_DB[[#This Row],[AB Vehicle Rebates]]),PRODUCT(EV_DB[[#This Row],[Cost, $MSRP CAD]],0.75)) -> 75000 | AJ19: =MIN(MAX(EV_DB[[#This Row],[Federal Rebates (iMHZEV) ]],EV_DB[[#This Row],[SC Vehicle Rebates]]),PRODUCT(EV_DB[[#This Row],[Cost, $MSRP CAD]],0.75)) -> 75000 | AK19: =MIN(MAX(EV_DB[[#This Row],[Federal Rebates (iMHZEV) ]],EV_DB[[#This Row],[NS Vehicle Rebates]]),PRODUCT(EV_DB[[#This Row],[Cost, $MSRP CAD]],0.75)) -> 75000 | AL19: =MIN(MAX(EV_DB[[#This Row],[Federal Rebates (iMHZEV) ]],EV_DB[[#This Row],[NB Vehicle Rebates]]),PRODUCT(EV_DB[[#This Row],[Cost, $MSRP CAD]],0.75)) -> 75000 | AM19: =MIN(MAX(EV_DB[[#This Row],[Federal Rebates (iMHZEV) ]],EV_DB[[#This Row],[MB Vehicle Rebates]]),PRODUCT(EV_DB[[#This Row],[Cost, $MSRP CAD]],0.75)) -> 75000 | AN19: =MIN(MAX(EV_DB[[#This Row],[Federal Rebates (iMHZEV) ]],EV_DB[[#This Row],[PEI Vehicle Rebates]]),PRODUCT(EV_DB[[#This Row],[Cost, $MSRP CAD]],0.75)) -> 75000 | AO19: =MIN(MAX(EV_DB[[#This Row],[Federal Rebates (iMHZEV) ]],EV_DB[[#This Row],[NL Vehicle Rebates]]),PRODUCT(EV_DB[[#This Row],[Cost, $MSRP CAD]],0.75)) -> 75000 | AP19: =MIN(MAX(EV_DB[[#This Row],[Federal Rebates (iMHZEV) ]]+EV_DB[[#This Row],[YT Vehicle Rebates]]),PRODUCT(EV_DB[[#This Row],[Cost, $MSRP CAD]],0.75)) -> 75000 | AQ19: =MIN(MAX(EV_DB[[#This Row],[Federal Rebates (iMHZEV) ]],EV_DB[[#This Row],[NU Vehicle Rebates]]),PRODUCT(EV_DB[[#This Row],[Cost, $MSRP CAD]],0.75)) -> 75000 | AR19: =MIN(MAX(EV_DB[[#This Row],[Federal Rebates (iMHZEV) ]],EV_DB[[#This Row],[NT Vehicle Rebates]]),PRODUCT(EV_DB[[#This Row],[Cost, $MSRP CAD]],0.75)) -> 75000
A20: Mullen | B20: Three (USA model) | C20: =EV_DB[[#This Row],[Manufacturer ]]& " " &EV_DB[[#This Row],[Model]] -> Mullen Three (USA model) | D20: Low cab forward | E20: 2024 | F20: 3 | G20: {=_xlfn.IFS(OR(EV_DB[[#This Row],[FHWA Class (2B - 8)]]= "2B", EV_DB[[#This Row],[FHWA Class (2B - 8)]]=3), "Light Duty",OR(EV_DB[[#This Row],[FHWA Class (2B - 8)]]=4,EV_DB[[#This Row],[FHWA Class (2B - 8)]]=5,EV_DB[[#This Row],[FHWA Class (2B - 8)]]=6),"Medium Duty",OR(EV_DB[[#This Row],[FHWA Class (2B - 8)]]=7,EV_DB[[#This Row],[FHWA Class (2B - 8)]]=8), "Heavy Duty")} -> Light Duty | H20: 11000 | I20: 5316 | J20: 93708 | K20: {=_xlfn.IFS(EV_DB[[#This Row],[Category]]="Light Duty",'Maintenance costs table'!$D$4,EV_DB[[#This Row],[Category]]="Medium Duty",'Maintenance costs table'!$D$8,EV_DB[[#This Row],[Category]]="Heavy Duty",'Maintenance costs table'!$D$6)} -> 0.18 | L20: No | M20: 89 kwh | N20: 0.22 | Q20: 201 | R20: {=_xlfn.IFS(EV_DB[[#This Row],[Battery Size, kWh]]>350 & EV_DB[[#This Row],[FHWA Class (2B - 8)]]=8,'iMHZEV table'!$D$4,EV_DB[[#This Row],[Battery Size, kWh]]<=350 & EV_DB[[#This Row],[FHWA Class (2B - 8)]]=8,'iMHZEV table'!$D$5, TRUE, _xlfn.XLOOKUP(EV_DB[[#This Row],[FHWA Class (2B - 8)]],'iMHZEV table'!$A$3:$A$11,'iMHZEV table'!$D$3:$D$11))} -> 40000 | T20: {=_xlfn.IFS(EV_DB[[#This Row],[FHWA Class (2B - 8)]]= "2B",10000,EV_DB[[#This Row],[FHWA Class (2B - 8)]]=3,55000,OR(EV_DB[[#This Row],[FHWA Class (2B - 8)]]=4,EV_DB[[#This Row],[FHWA Class (2B - 8)]]=5), 75000,OR(EV_DB[[#This Row],[FHWA Class (2B - 8)]]=6,EV_DB[[#This Row],[FHWA Class (2B - 8)]]=7),100000,EV_DB[[#This Row],[FHWA Class (2B - 8)]]=8, 150000)} -> 55000 | AF20: =MIN(MAX(EV_DB[[#This Row],[Federal Rebates (iMHZEV) ]],EV_DB[[#This Row],[ON Vehicle Rebates]]),PRODUCT(EV_DB[[#This Row],[Cost, $MSRP CAD]],0.75)) -> 40000 | AG20: =MIN(EV_DB[[#This Row],[Federal Rebates (iMHZEV) ]]+EV_DB[[#This Row],[BC Vehicle Rebates]],PRODUCT(EV_DB[[#This Row],[Cost, $MSRP CAD]],0.75)) -> 70281 | AH20: =MIN(EV_DB[[#This Row],[Federal Rebates (iMHZEV) ]]+EV_DB[[#This Row],[QC Vehicle Rebates]],PRODUCT(EV_DB[[#This Row],[Cost, $MSRP CAD]],0.75)) -> 40000 | AI20: =MIN(MAX(EV_DB[[#This Row],[Federal Rebates (iMHZEV) ]],EV_DB[[#This Row],[AB Vehicle Rebates]]),PRODUCT(EV_DB[[#This Row],[Cost, $MSRP CAD]],0.75)) -> 40000 | AJ20: =MIN(MAX(EV_DB[[#This Row],[Federal Rebates (iMHZEV) ]],EV_DB[[#This Row],[SC Vehicle Rebates]]),PRODUCT(EV_DB[[#This Row],[Cost, $MSRP CAD]],0.75)) -> 40000 | AK20: =MIN(MAX(EV_DB[[#This Row],[Federal Rebates (iMHZEV) ]],EV_DB[[#This Row],[NS Vehicle Rebates]]),PRODUCT(EV_DB[[#This Row],[Cost, $MSRP CAD]],0.75)) -> 40000 | AL20: =MIN(MAX(EV_DB[[#This Row],[Federal Rebates (iMHZEV) ]],EV_DB[[#This Row],[NB Vehicle Rebates]]),PRODUCT(EV_DB[[#This Row],[Cost, $MSRP CAD]],0.75)) -> 40000 | AM20: =MIN(MAX(EV_DB[[#This Row],[Federal Rebates (iMHZEV) ]],EV_DB[[#This Row],[MB Vehicle Rebates]]),PRODUCT(EV_DB[[#This Row],[Cost, $MSRP CAD]],0.75)) -> 40000 | AN20: =MIN(MAX(EV_DB[[#This Row],[Federal Rebates (iMHZEV) ]],EV_DB[[#This Row],[PEI Vehicle Rebates]]),PRODUCT(EV_DB[[#This Row],[Cost, $MSRP CAD]],0.75)) -> 40000 | AO20: =MIN(MAX(EV_DB[[#This Row],[Federal Rebates (iMHZEV) ]],EV_DB[[#This Row],[NL Vehicle Rebates]]),PRODUCT(EV_DB[[#This Row],[Cost, $MSRP CAD]],0.75)) -> 40000 | AP20: =MIN(MAX(EV_DB[[#This Row],[Federal Rebates (iMHZEV) ]]+EV_DB[[#This Row],[YT Vehicle Rebates]]),PRODUCT(EV_DB[[#This Row],[Cost, $MSRP CAD]],0.75)) -> 40000 | AQ20: =MIN(MAX(EV_DB[[#This Row],[Federal Rebates (iMHZEV) ]],EV_DB[[#This Row],[NU Vehicle Rebates]]),PRODUCT(EV_DB[[#This Row],[Cost, $MSRP CAD]],0.75)) -> 40000 | AR20: =MIN(MAX(EV_DB[[#This Row],[Federal Rebates (iMHZEV) ]],EV_DB[[#This Row],[NT Vehicle Rebates]]),PRODUCT(EV_DB[[#This Row],[Cost, $MSRP CAD]],0.75)) -> 40000
A21: Karsan | B21: e-JEST | C21: =EV_DB[[#This Row],[Manufacturer ]]& " " &EV_DB[[#This Row],[Model]] -> Karsan e-JEST | D21: Passanger van | E21: 2024 | F21: 3 | G21: {=_xlfn.IFS(OR(EV_DB[[#This Row],[FHWA Class (2B - 8)]]= "2B", EV_DB[[#This Row],[FHWA Class (2B - 8)]]=3), "Light Duty",OR(EV_DB[[#This Row],[FHWA Class (2B - 8)]]=4,EV_DB[[#This Row],[FHWA Class (2B - 8)]]=5,EV_DB[[#This Row],[FHWA Class (2B - 8)]]=6),"Medium Duty",OR(EV_DB[[#This Row],[FHWA Class (2B - 8)]]=7,EV_DB[[#This Row],[FHWA Class (2B - 8)]]=8), "Heavy Duty")} -> Light Duty | H21: 11000 | I21: 5500 | J21: 375000 | K21: {=_xlfn.IFS(EV_DB[[#This Row],[Category]]="Light Duty",'Maintenance costs table'!$D$4,EV_DB[[#This Row],[Category]]="Medium Duty",'Maintenance costs table'!$D$8,EV_DB[[#This Row],[Category]]="Heavy Duty",'Maintenance costs table'!$D$6)} -> 0.18 | L21: No | M21: 88 kWh | N21: 0.2 | O21: AC Type 2: 22 kW - 4 hr DC Combo 2: 80 kW - 65 min | Q21: 210 | R21: {=_xlfn.IFS(EV_DB[[#This Row],[Battery Size, kWh]]>350 & EV_DB[[#This Row],[FHWA Class (2B - 8)]]=8,'iMHZEV table'!$D$4,EV_DB[[#This Row],[Battery Size, kWh]]<=350 & EV_DB[[#This Row],[FHWA Class (2B - 8)]]=8,'iMHZEV table'!$D$5, TRUE, _xlfn.XLOOKUP(EV_DB[[#This Row],[FHWA Class (2B - 8)]],'iMHZEV table'!$A$3:$A$11,'iMHZEV table'!$D$3:$D$11))} -> 40000 | T21: {=_xlfn.IFS(EV_DB[[#This Row],[FHWA Class (2B - 8)]]= "2B",10000,EV_DB[[#This Row],[FHWA Class (2B - 8)]]=3,55000,OR(EV_DB[[#This Row],[FHWA Class (2B - 8)]]=4,EV_DB[[#This Row],[FHWA Class (2B - 8)]]=5), 75000,OR(EV_DB[[#This Row],[FHWA Class (2B - 8)]]=6,EV_DB[[#This Row],[FHWA Class (2B - 8)]]=7),100000,EV_DB[[#This Row],[FHWA Class (2B - 8)]]=8, 150000)} -> 55000 | AF21: =MIN(MAX(EV_DB[[#This Row],[Federal Rebates (iMHZEV) ]],EV_DB[[#This Row],[ON Vehicle Rebates]]),PRODUCT(EV_DB[[#This Row],[Cost, $MSRP CAD]],0.75)) -> 40000 | AG21: =MIN(EV_DB[[#This Row],[Federal Rebates (iMHZEV) ]]+EV_DB[[#This Row],[BC Vehicle Rebates]],PRODUCT(EV_DB[[#This Row],[Cost, $MSRP CAD]],0.75)) -> 95000 | AH21: =MIN(EV_DB[[#This Row],[Federal Rebates (iMHZEV) ]]+EV_DB[[#This Row],[QC Vehicle Rebates]],PRODUCT(EV_DB[[#This Row],[Cost, $MSRP CAD]],0.75)) -> 40000 | AI21: =MIN(MAX(EV_DB[[#This Row],[Federal Rebates (iMHZEV) ]],EV_DB[[#This Row],[AB Vehicle Rebates]]),PRODUCT(EV_DB[[#This Row],[Cost, $MSRP CAD]],0.75)) -> 40000 | AJ21: =MIN(MAX(EV_DB[[#This Row],[Federal Rebates (iMHZEV) ]],EV_DB[[#This Row],[SC Vehicle Rebates]]),PRODUCT(EV_DB[[#This Row],[Cost, $MSRP CAD]],0.75)) -> 40000 | AK21: =MIN(MAX(EV_DB[[#This Row],[Federal Rebates (iMHZEV) ]],EV_DB[[#This Row],[NS Vehicle Rebates]]),PRODUCT(EV_DB[[#This Row],[Cost, $MSRP CAD]],0.75)) -> 40000 | AL21: =MIN(MAX(EV_DB[[#This Row],[Federal Rebates (iMHZEV) ]],EV_DB[[#This Row],[NB Vehicle Rebates]]),PRODUCT(EV_DB[[#This Row],[Cost, $MSRP CAD]],0.75)) -> 40000 | AM21: =MIN(MAX(EV_DB[[#This Row],[Federal Rebates (iMHZEV) ]],EV_DB[[#This Row],[MB Vehicle Rebates]]),PRODUCT(EV_DB[[#This Row],[Cost, $MSRP CAD]],0.75)) -> 40000 | AN21: =MIN(MAX(EV_DB[[#This Row],[Federal Rebates (iMHZEV) ]],EV_DB[[#This Row],[PEI Vehicle Rebates]]),PRODUCT(EV_DB[[#This Row],[Cost, $MSRP CAD]],0.75)) -> 40000 | AO21: =MIN(MAX(EV_DB[[#This Row],[Federal Rebates (iMHZEV) ]],EV_DB[[#This Row],[NL Vehicle Rebates]]),PRODUCT(EV_DB[[#This Row],[Cost, $MSRP CAD]],0.75)) -> 40000 | AP21: =MIN(MAX(EV_DB[[#This Row],[Federal Rebates (iMHZEV) ]]+EV_DB[[#This Row],[YT Vehicle Rebates]]),PRODUCT(EV_DB[[#This Row],[Cost, $MSRP CAD]],0.75)) -> 40000 | AQ21: =MIN(MAX(EV_DB[[#This Row],[Federal Rebates (iMHZEV) ]],EV_DB[[#This Row],[NU Vehicle Rebates]]),PRODUCT(EV_DB[[#This Row],[Cost, $MSRP CAD]],0.75)) -> 40000 | AR21: =MIN(MAX(EV_DB[[#This Row],[Federal Rebates (iMHZEV) ]],EV_DB[[#This Row],[NT Vehicle Rebates]]),PRODUCT(EV_DB[[#This Row],[Cost, $MSRP CAD]],0.75)) -> 40000
A22: Vicnity | B22: VM 1200 | C22: =EV_DB[[#This Row],[Manufacturer ]]& " " &EV_DB[[#This Row],[Model]] -> Vicnity VM 1200 | D22: Chassis Cab | E22: 2024 | F22: 3 | G22: {=_xlfn.IFS(OR(EV_DB[[#This Row],[FHWA Class (2B - 8)]]= "2B", EV_DB[[#This Row],[FHWA Class (2B - 8)]]=3), "Light Duty",OR(EV_DB[[#This Row],[FHWA Class (2B - 8)]]=4,EV_DB[[#This Row],[FHWA Class (2B - 8)]]=5,EV_DB[[#This Row],[FHWA Class (2B - 8)]]=6),"Medium Duty",OR(EV_DB[[#This Row],[FHWA Class (2B - 8)]]=7,EV_DB[[#This Row],[FHWA Class (2B - 8)]]=8), "Heavy Duty")} -> Light Duty | H22: 12000 | I22: 6000 | J22: 159900 | K22: {=_xlfn.IFS(EV_DB[[#This Row],[Category]]="Light Duty",'Maintenance costs table'!$D$4,EV_DB[[#This Row],[Category]]="Medium Duty",'Maintenance costs table'!$D$8,EV_DB[[#This Row],[Category]]="Heavy Duty",'Maintenance costs table'!$D$6)} -> 0.18 | L22: No | M22: Up to 150 kWh | N22: 0.29 | Q22: 289 | R22: {=_xlfn.IFS(EV_DB[[#This Row],[Battery Size, kWh]]>350 & EV_DB[[#This Row],[FHWA Class (2B - 8)]]=8,'iMHZEV table'!$D$4,EV_DB[[#This Row],[Battery Size, kWh]]<=350 & EV_DB[[#This Row],[FHWA Class (2B - 8)]]=8,'iMHZEV table'!$D$5, TRUE, _xlfn.XLOOKUP(EV_DB[[#This Row],[FHWA Class (2B - 8)]],'iMHZEV table'!$A$3:$A$11,'iMHZEV table'!$D$3:$D$11))} -> 40000 | T22: {=_xlfn.IFS(EV_DB[[#This Row],[FHWA Class (2B - 8)]]= "2B",10000,EV_DB[[#This Row],[FHWA Class (2B - 8)]]=3,55000,OR(EV_DB[[#This Row],[FHWA Class (2B - 8)]]=4,EV_DB[[#This Row],[FHWA Class (2B - 8)]]=5), 75000,OR(EV_DB[[#This Row],[FHWA Class (2B - 8)]]=6,EV_DB[[#This Row],[FHWA Class (2B - 8)]]=7),100000,EV_DB[[#This Row],[FHWA Class (2B - 8)]]=8, 150000)} -> 55000 | AF22: =MIN(MAX(EV_DB[[#This Row],[Federal Rebates (iMHZEV) ]],EV_DB[[#This Row],[ON Vehicle Rebates]]),PRODUCT(EV_DB[[#This Row],[Cost, $MSRP CAD]],0.75)) -> 40000 | AG22: =MIN(EV_DB[[#This Row],[Federal Rebates (iMHZEV) ]]+EV_DB[[#This Row],[BC Vehicle Rebates]],PRODUCT(EV_DB[[#This Row],[Cost, $MSRP CAD]],0.75)) -> 95000 | AH22: =MIN(EV_DB[[#This Row],[Federal Rebates (iMHZEV) ]]+EV_DB[[#This Row],[QC Vehicle Rebates]],PRODUCT(EV_DB[[#This Row],[Cost, $MSRP CAD]],0.75)) -> 40000 | AI22: =MIN(MAX(EV_DB[[#This Row],[Federal Rebates (iMHZEV) ]],EV_DB[[#This Row],[AB Vehicle Rebates]]),PRODUCT(EV_DB[[#This Row],[Cost, $MSRP CAD]],0.75)) -> 40000 | AJ22: =MIN(MAX(EV_DB[[#This Row],[Federal Rebates (iMHZEV) ]],EV_DB[[#This Row],[SC Vehicle Rebates]]),PRODUCT(EV_DB[[#This Row],[Cost, $MSRP CAD]],0.75)) -> 40000 | AK22: =MIN(MAX(EV_DB[[#This Row],[Federal Rebates (iMHZEV) ]],EV_DB[[#This Row],[NS Vehicle Rebates]]),PRODUCT(EV_DB[[#This Row],[Cost, $MSRP CAD]],0.75)) -> 40000 | AL22: =MIN(MAX(EV_DB[[#This Row],[Federal Rebates (iMHZEV) ]],EV_DB[[#This Row],[NB Vehicle Rebates]]),PRODUCT(EV_DB[[#This Row],[Cost, $MSRP CAD]],0.75)) -> 40000 | AM22: =MIN(MAX(EV_DB[[#This Row],[Federal Rebates (iMHZEV) ]],EV_DB[[#This Row],[MB Vehicle Rebates]]),PRODUCT(EV_DB[[#This Row],[Cost, $MSRP CAD]],0.75)) -> 40000 | AN22: =MIN(MAX(EV_DB[[#This Row],[Federal Rebates (iMHZEV) ]],EV_DB[[#This Row],[PEI Vehicle Rebates]]),PRODUCT(EV_DB[[#This Row],[Cost, $MSRP CAD]],0.75)) -> 40000 | AO22: =MIN(MAX(EV_DB[[#This Row],[Federal Rebates (iMHZEV) ]],EV_DB[[#This Row],[NL Vehicle Rebates]]),PRODUCT(EV_DB[[#This Row],[Cost, $MSRP CAD]],0.75)) -> 40000 | AP22: =MIN(MAX(EV_DB[[#This Row],[Federal Rebates (iMHZEV) ]]+EV_DB[[#This Row],[YT Vehicle Rebates]]),PRODUCT(EV_DB[[#This Row],[Cost, $MSRP CAD]],0.75)) -> 40000 | AQ22: =MIN(MAX(EV_DB[[#This Row],[Federal Rebates (iMHZEV) ]],EV_DB[[#This Row],[NU Vehicle Rebates]]),PRODUCT(EV_DB[[#This Row],[Cost, $MSRP CAD]],0.75)) -> 40000 | AR22: =MIN(MAX(EV_DB[[#This Row],[Federal Rebates (iMHZEV) ]],EV_DB[[#This Row],[NT Vehicle Rebates]]),PRODUCT(EV_DB[[#This Row],[Cost, $MSRP CAD]],0.75)) -> 40000
A23: Motiv Power Systems | B23: EPIC F-59 | C23: =EV_DB[[#This Row],[Manufacturer ]]& " " &EV_DB[[#This Row],[Model]] -> Motiv Power Systems EPIC F-59 | D23: Step Van | E23: 2024 | F23: 5 | G23: {=_xlfn.IFS(OR(EV_DB[[#This Row],[FHWA Class (2B - 8)]]= "2B", EV_DB[[#This Row],[FHWA Class (2B - 8)]]=3), "Light Duty",OR(EV_DB[[#This Row],[FHWA Class (2B - 8)]]=4,EV_DB[[#This Row],[FHWA Class (2B - 8)]]=5,EV_DB[[#This Row],[FHWA Class (2B - 8)]]=6),"Medium Duty",OR(EV_DB[[#This Row],[FHWA Class (2B - 8)]]=7,EV_DB[[#This Row],[FHWA Class (2B - 8)]]=8), "Heavy Duty")} -> Medium Duty | H23: 19500 | I23: 10000 | J23: 200000 | K23: {=_xlfn.IFS(EV_DB[[#This Row],[Category]]="Light Duty",'Maintenance costs table'!$D$4,EV_DB[[#This Row],[Category]]="Medium Duty",'Maintenance costs table'!$D$8,EV_DB[[#This Row],[Category]]="Heavy Duty",'Maintenance costs table'!$D$6)} -> 0.25 | L23: No | M23: 127 kWh | N23: 0.28 | O23: 6.5 hours at 80 amps, 19.2 kW | Q23: 169 | R23: {=_xlfn.IFS(EV_DB[[#This Row],[Battery Size, kWh]]>350 & EV_DB[[#This Row],[FHWA Class (2B - 8)]]=8,'iMHZEV table'!$D$4,EV_DB[[#This Row],[Battery Size, kWh]]<=350 & EV_DB[[#This Row],[FHWA Class (2B - 8)]]=8,'iMHZEV table'!$D$5, TRUE, _xlfn.XLOOKUP(EV_DB[[#This Row],[FHWA Class (2B - 8)]],'iMHZEV table'!$A$3:$A$11,'iMHZEV table'!$D$3:$D$11))} -> 75000 | T23: {=_xlfn.IFS(EV_DB[[#This Row],[FHWA Class (2B - 8)]]= "2B",10000,EV_DB[[#This Row],[FHWA Class (2B - 8)]]=3,55000,OR(EV_DB[[#This Row],[FHWA Class (2B - 8)]]=4,EV_DB[[#This Row],[FHWA Class (2B - 8)]]=5), 75000,OR(EV_DB[[#This Row],[FHWA Class (2B - 8)]]=6,EV_DB[[#This Row],[FHWA Class (2B - 8)]]=7),100000,EV_DB[[#This Row],[FHWA Class (2B - 8)]]=8, 150000)} -> 75000 | AF23: =MIN(MAX(EV_DB[[#This Row],[Federal Rebates (iMHZEV) ]],EV_DB[[#This Row],[ON Vehicle Rebates]]),PRODUCT(EV_DB[[#This Row],[Cost, $MSRP CAD]],0.75)) -> 75000 | AG23: =MIN(EV_DB[[#This Row],[Federal Rebates (iMHZEV) ]]+EV_DB[[#This Row],[BC Vehicle Rebates]],PRODUCT(EV_DB[[#This Row],[Cost, $MSRP CAD]],0.75)) -> 150000 | AH23: =MIN(EV_DB[[#This Row],[Federal Rebates (iMHZEV) ]]+EV_DB[[#This Row],[QC Vehicle Rebates]],PRODUCT(EV_DB[[#This Row],[Cost, $MSRP CAD]],0.75)) -> 75000 | AI23: =MIN(MAX(EV_DB[[#This Row],[Federal Rebates (iMHZEV) ]],EV_DB[[#This Row],[AB Vehicle Rebates]]),PRODUCT(EV_DB[[#This Row],[Cost, $MSRP CAD]],0.75)) -> 75000 | AJ23: =MIN(MAX(EV_DB[[#This Row],[Federal Rebates (iMHZEV) ]],EV_DB[[#This Row],[SC Vehicle Rebates]]),PRODUCT(EV_DB[[#This Row],[Cost, $MSRP CAD]],0.75)) -> 75000 | AK23: =MIN(MAX(EV_DB[[#This Row],[Federal Rebates (iMHZEV) ]],EV_DB[[#This Row],[NS Vehicle Rebates]]),PRODUCT(EV_DB[[#This Row],[Cost, $MSRP CAD]],0.75)) -> 75000 | AL23: =MIN(MAX(EV_DB[[#This Row],[Federal Rebates (iMHZEV) ]],EV_DB[[#This Row],[NB Vehicle Rebates]]),PRODUCT(EV_DB[[#This Row],[Cost, $MSRP CAD]],0.75)) -> 75000 | AM23: =MIN(MAX(EV_DB[[#This Row],[Federal Rebates (iMHZEV) ]],EV_DB[[#This Row],[MB Vehicle Rebates]]),PRODUCT(EV_DB[[#This Row],[Cost, $MSRP CAD]],0.75)) -> 75000 | AN23: =MIN(MAX(EV_DB[[#This Row],[Federal Rebates (iMHZEV) ]],EV_DB[[#This Row],[PEI Vehicle Rebates]]),PRODUCT(EV_DB[[#This Row],[Cost, $MSRP CAD]],0.75)) -> 75000 | AO23: =MIN(MAX(EV_DB[[#This Row],[Federal Rebates (iMHZEV) ]],EV_DB[[#This Row],[NL Vehicle Rebates]]),PRODUCT(EV_DB[[#This Row],[Cost, $MSRP CAD]],0.75)) -> 75000 | AP23: =MIN(MAX(EV_DB[[#This Row],[Federal Rebates (iMHZEV) ]]+EV_DB[[#This Row],[YT Vehicle Rebates]]),PRODUCT(EV_DB[[#This Row],[Cost, $MSRP CAD]],0.75)) -> 75000 | AQ23: =MIN(MAX(EV_DB[[#This Row],[Federal Rebates (iMHZEV) ]],EV_DB[[#This Row],[NU Vehicle Rebates]]),PRODUCT(EV_DB[[#This Row],[Cost, $MSRP CAD]],0.75)) -> 75000 | AR23: =MIN(MAX(EV_DB[[#This Row],[Federal Rebates (iMHZEV) ]],EV_DB[[#This Row],[NT Vehicle Rebates]]),PRODUCT(EV_DB[[#This Row],[Cost, $MSRP CAD]],0.75)) -> 75000
A24: Motiv Power Systems | B24: EPIC F-59 | C24: =EV_DB[[#This Row],[Manufacturer ]]& " " &EV_DB[[#This Row],[Model]] -> Motiv Power Systems EPIC F-59 | D24: Step Van | E24: 2024 | F24: 6 | G24: {=_xlfn.IFS(OR(EV_DB[[#This Row],[FHWA Class (2B - 8)]]= "2B", EV_DB[[#This Row],[FHWA Class (2B - 8)]]=3), "Light Duty",OR(EV_DB[[#This Row],[FHWA Class (2B - 8)]]=4,EV_DB[[#This Row],[FHWA Class (2B - 8)]]=5,EV_DB[[#This Row],[FHWA Class (2B - 8)]]=6),"Medium Duty",OR(EV_DB[[#This Row],[FHWA Class (2B - 8)]]=7,EV_DB[[#This Row],[FHWA Class (2B - 8)]]=8), "Heavy Duty")} -> Medium Duty | H24: 19500 | I24: 8900 | J24: 200000 | K24: {=_xlfn.IFS(EV_DB[[#This Row],[Category]]="Light Duty",'Maintenance costs table'!$D$4,EV_DB[[#This Row],[Category]]="Medium Duty",'Maintenance costs table'!$D$8,EV_DB[[#This Row],[Category]]="Heavy Duty",'Maintenance costs table'!$D$6)} -> 0.25 | L24: No | M24: 127 kwh | N24: 0.28 | O24: 6.5 hours at 80 amps, 19.2 kW | Q24: 169 | R24: {=_xlfn.IFS(EV_DB[[#This Row],[Battery Size, kWh]]>350 & EV_DB[[#This Row],[FHWA Class (2B - 8)]]=8,'iMHZEV table'!$D$4,EV_DB[[#This Row],[Battery Size, kWh]]<=350 & EV_DB[[#This Row],[FHWA Class (2B - 8)]]=8,'iMHZEV table'!$D$5, TRUE, _xlfn.XLOOKUP(EV_DB[[#This Row],[FHWA Class (2B - 8)]],'iMHZEV table'!$A$3:$A$11,'iMHZEV table'!$D$3:$D$11))} -> 100000 | T24: {=_xlfn.IFS(EV_DB[[#This Row],[FHWA Class (2B - 8)]]= "2B",10000,EV_DB[[#This Row],[FHWA Class (2B - 8)]]=3,55000,OR(EV_DB[[#This Row],[FHWA Class (2B - 8)]]=4,EV_DB[[#This Row],[FHWA Class (2B - 8)]]=5), 75000,OR(EV_DB[[#This Row],[FHWA Class (2B - 8)]]=6,EV_DB[[#This Row],[FHWA Class (2B - 8)]]=7),100000,EV_DB[[#This Row],[FHWA Class (2B - 8)]]=8, 150000)} -> 100000 | AF24: =MIN(MAX(EV_DB[[#This Row],[Federal Rebates (iMHZEV) ]],EV_DB[[#This Row],[ON Vehicle Rebates]]),PRODUCT(EV_DB[[#This Row],[Cost, $MSRP CAD]],0.75)) -> 100000 | AG24: =MIN(EV_DB[[#This Row],[Federal Rebates (iMHZEV) ]]+EV_DB[[#This Row],[BC Vehicle Rebates]],PRODUCT(EV_DB[[#This Row],[Cost, $MSRP CAD]],0.75)) -> 150000 | AH24: =MIN(EV_DB[[#This Row],[Federal Rebates (iMHZEV) ]]+EV_DB[[#This Row],[QC Vehicle Rebates]],PRODUCT(EV_DB[[#This Row],[Cost, $MSRP CAD]],0.75)) -> 100000 | AI24: =MIN(MAX(EV_DB[[#This Row],[Federal Rebates (iMHZEV) ]],EV_DB[[#This Row],[AB Vehicle Rebates]]),PRODUCT(EV_DB[[#This Row],[Cost, $MSRP CAD]],0.75)) -> 100000 | AJ24: =MIN(MAX(EV_DB[[#This Row],[Federal Rebates (iMHZEV) ]],EV_DB[[#This Row],[SC Vehicle Rebates]]),PRODUCT(EV_DB[[#This Row],[Cost, $MSRP CAD]],0.75)) -> 100000 | AK24: =MIN(MAX(EV_DB[[#This Row],[Federal Rebates (iMHZEV) ]],EV_DB[[#This Row],[NS Vehicle Rebates]]),PRODUCT(EV_DB[[#This Row],[Cost, $MSRP CAD]],0.75)) -> 100000 | AL24: =MIN(MAX(EV_DB[[#This Row],[Federal Rebates (iMHZEV) ]],EV_DB[[#This Row],[NB Vehicle Rebates]]),PRODUCT(EV_DB[[#This Row],[Cost, $MSRP CAD]],0.75)) -> 100000 | AM24: =MIN(MAX(EV_DB[[#This Row],[Federal Rebates (iMHZEV) ]],EV_DB[[#This Row],[MB Vehicle Rebates]]),PRODUCT(EV_DB[[#This Row],[Cost, $MSRP CAD]],0.75)) -> 100000 | AN24: =MIN(MAX(EV_DB[[#This Row],[Federal Rebates (iMHZEV) ]],EV_DB[[#This Row],[PEI Vehicle Rebates]]),PRODUCT(EV_DB[[#This Row],[Cost, $MSRP CAD]],0.75)) -> 100000 | AO24: =MIN(MAX(EV_DB[[#This Row],[Federal Rebates (iMHZEV) ]],EV_DB[[#This Row],[NL Vehicle Rebates]]),PRODUCT(EV_DB[[#This Row],[Cost, $MSRP CAD]],0.75)) -> 100000 | AP24: =MIN(MAX(EV_DB[[#This Row],[Federal Rebates (iMHZEV) ]]+EV_DB[[#This Row],[YT Vehicle Rebates]]),PRODUCT(EV_DB[[#This Row],[Cost, $MSRP CAD]],0.75)) -> 100000 | AQ24: =MIN(MAX(EV_DB[[#This Row],[Federal Rebates (iMHZEV) ]],EV_DB[[#This Row],[NU Vehicle Rebates]]),PRODUCT(EV_DB[[#This Row],[Cost, $MSRP CAD]],0.75)) -> 100000 | AR24: =MIN(MAX(EV_DB[[#This Row],[Federal Rebates (iMHZEV) ]],EV_DB[[#This Row],[NT Vehicle Rebates]]),PRODUCT(EV_DB[[#This Row],[Cost, $MSRP CAD]],0.75)) -> 100000
A25: Motiv Power Systems | B25: EPIC 4/E-450 | C25: =EV_DB[[#This Row],[Manufacturer ]]& " " &EV_DB[[#This Row],[Model]] -> Motiv Power Systems EPIC 4/E-450 | D25: Box Truck / Work Truck | E25: 2023 | F25: 4 | G25: {=_xlfn.IFS(OR(EV_DB[[#This Row],[FHWA Class (2B - 8)]]= "2B", EV_DB[[#This Row],[FHWA Class (2B - 8)]]=3), "Light Duty",OR(EV_DB[[#This Row],[FHWA Class (2B - 8)]]=4,EV_DB[[#This Row],[FHWA Class (2B - 8)]]=5,EV_DB[[#This Row],[FHWA Class (2B - 8)]]=6),"Medium Duty",OR(EV_DB[[#This Row],[FHWA Class (2B - 8)]]=7,EV_DB[[#This Row],[FHWA Class (2B - 8)]]=8), "Heavy Duty")} -> Medium Duty | H25: 14500 | I25: 6000 | J25: 180000 | K25: {=_xlfn.IFS(EV_DB[[#This Row],[Category]]="Light Duty",'Maintenance costs table'!$D$4,EV_DB[[#This Row],[Category]]="Medium Duty",'Maintenance costs table'!$D$8,EV_DB[[#This Row],[Category]]="Heavy Duty",'Maintenance costs table'!$D$6)} -> 0.25 | L25: No | M25: 127 kWh | N25: 0.26 | O25: 6.5 hours at 80 amps, 19.2 kW | Q25: 169 | R25: {=_xlfn.IFS(EV_DB[[#This Row],[Battery Size, kWh]]>350 & EV_DB[[#This Row],[FHWA Class (2B - 8)]]=8,'iMHZEV table'!$D$4,EV_DB[[#This Row],[Battery Size, kWh]]<=350 & EV_DB[[#This Row],[FHWA Class (2B - 8)]]=8,'iMHZEV table'!$D$5, TRUE, _xlfn.XLOOKUP(EV_DB[[#This Row],[FHWA Class (2B - 8)]],'iMHZEV table'!$A$3:$A$11,'iMHZEV table'!$D$3:$D$11))} -> 75000 | T25: {=_xlfn.IFS(EV_DB[[#This Row],[FHWA Class (2B - 8)]]= "2B",10000,EV_DB[[#This Row],[FHWA Class (2B - 8)]]=3,55000,OR(EV_DB[[#This Row],[FHWA Class (2B - 8)]]=4,EV_DB[[#This Row],[FHWA Class (2B - 8)]]=5), 75000,OR(EV_DB[[#This Row],[FHWA Class (2B - 8)]]=6,EV_DB[[#This Row],[FHWA Class (2B - 8)]]=7),100000,EV_DB[[#This Row],[FHWA Class (2B - 8)]]=8, 150000)} -> 75000 | AF25: =MIN(MAX(EV_DB[[#This Row],[Federal Rebates (iMHZEV) ]],EV_DB[[#This Row],[ON Vehicle Rebates]]),PRODUCT(EV_DB[[#This Row],[Cost, $MSRP CAD]],0.75)) -> 75000 | AG25: =MIN(EV_DB[[#This Row],[Federal Rebates (iMHZEV) ]]+EV_DB[[#This Row],[BC Vehicle Rebates]],PRODUCT(EV_DB[[#This Row],[Cost, $MSRP CAD]],0.75)) -> 135000 | AH25: =MIN(EV_DB[[#This Row],[Federal Rebates (iMHZEV) ]]+EV_DB[[#This Row],[QC Vehicle Rebates]],PRODUCT(EV_DB[[#This Row],[Cost, $MSRP CAD]],0.75)) -> 75000 | AI25: =MIN(MAX(EV_DB[[#This Row],[Federal Rebates (iMHZEV) ]],EV_DB[[#This Row],[AB Vehicle Rebates]]),PRODUCT(EV_DB[[#This Row],[Cost, $MSRP CAD]],0.75)) -> 75000 | AJ25: =MIN(MAX(EV_DB[[#This Row],[Federal Rebates (iMHZEV) ]],EV_DB[[#This Row],[SC Vehicle Rebates]]),PRODUCT(EV_DB[[#This Row],[Cost, $MSRP CAD]],0.75)) -> 75000 | AK25: =MIN(MAX(EV_DB[[#This Row],[Federal Rebates (iMHZEV) ]],EV_DB[[#This Row],[NS Vehicle Rebates]]),PRODUCT(EV_DB[[#This Row],[Cost, $MSRP CAD]],0.75)) -> 75000 | AL25: =MIN(MAX(EV_DB[[#This Row],[Federal Rebates (iMHZEV) ]],EV_DB[[#This Row],[NB Vehicle Rebates]]),PRODUCT(EV_DB[[#This Row],[Cost, $MSRP CAD]],0.75)) -> 75000 | AM25: =MIN(MAX(EV_DB[[#This Row],[Federal Rebates (iMHZEV) ]],EV_DB[[#This Row],[MB Vehicle Rebates]]),PRODUCT(EV_DB[[#This Row],[Cost, $MSRP CAD]],0.75)) -> 75000 | AN25: =MIN(MAX(EV_DB[[#This Row],[Federal Rebates (iMHZEV) ]],EV_DB[[#This Row],[PEI Vehicle Rebates]]),PRODUCT(EV_DB[[#This Row],[Cost, $MSRP CAD]],0.75)) -> 75000 | AO25: =MIN(MAX(EV_DB[[#This Row],[Federal Rebates (iMHZEV) ]],EV_DB[[#This Row],[NL Vehicle Rebates]]),PRODUCT(EV_DB[[#This Row],[Cost, $MSRP CAD]],0.75)) -> 75000 | AP25: =MIN(MAX(EV_DB[[#This Row],[Federal Rebates (iMHZEV) ]]+EV_DB[[#This Row],[YT Vehicle Rebates]]),PRODUCT(EV_DB[[#This Row],[Cost, $MSRP CAD]],0.75)) -> 75000 | AQ25: =MIN(MAX(EV_DB[[#This Row],[Federal Rebates (iMHZEV) ]],EV_DB[[#This Row],[NU Vehicle Rebates]]),PRODUCT(EV_DB[[#This Row],[Cost, $MSRP CAD]],0.75)) -> 75000 | AR25: =MIN(MAX(EV_DB[[#This Row],[Federal Rebates (iMHZEV) ]],EV_DB[[#This Row],[NT Vehicle Rebates]]),PRODUCT(EV_DB[[#This Row],[Cost, $MSRP CAD]],0.75)) -> 75000
A26: Micro Bird Commercial | B26: G5 Electric | C26: =EV_DB[[#This Row],[Manufacturer ]]& " " &EV_DB[[#This Row],[Model]] -> Micro Bird Commercial G5 Electric | D26: Shuttle Bus | E26: 2023 | F26: 4 | G26: {=_xlfn.IFS(OR(EV_DB[[#This Row],[FHWA Class (2B - 8)]]= "2B", EV_DB[[#This Row],[FHWA Class (2B - 8)]]=3), "Light Duty",OR(EV_DB[[#This Row],[FHWA Class (2B - 8)]]=4,EV_DB[[#This Row],[FHWA Class (2B - 8)]]=5,EV_DB[[#This Row],[FHWA Class (2B - 8)]]=6),"Medium Duty",OR(EV_DB[[#This Row],[FHWA Class (2B - 8)]]=7,EV_DB[[#This Row],[FHWA Class (2B - 8)]]=8), "Heavy Duty")} -> Medium Duty | H26: 14500 | I26: 6000 | J26: 390000 | K26: {=_xlfn.IFS(EV_DB[[#This Row],[Category]]="Light Duty",'Maintenance costs table'!$D$4,EV_DB[[#This Row],[Category]]="Medium Duty",'Maintenance costs table'!$D$8,EV_DB[[#This Row],[Category]]="Heavy Duty",'Maintenance costs table'!$D$6)} -> 0.25 | L26: No | M26: 88 kWh | N26: 0.22 | O26: Level 2: 13.2 kW / Level 3: 50kW | P26: 350 | Q26: 160 | R26: {=_xlfn.IFS(EV_DB[[#This Row],[Battery Size, kWh]]>350 & EV_DB[[#This Row],[FHWA Class (2B - 8)]]=8,'iMHZEV table'!$D$4,EV_DB[[#This Row],[Battery Size, kWh]]<=350 & EV_DB[[#This Row],[FHWA Class (2B - 8)]]=8,'iMHZEV table'!$D$5, TRUE, _xlfn.XLOOKUP(EV_DB[[#This Row],[FHWA Class (2B - 8)]],'iMHZEV table'!$A$3:$A$11,'iMHZEV table'!$D$3:$D$11))} -> 75000 | T26: {=_xlfn.IFS(EV_DB[[#This Row],[FHWA Class (2B - 8)]]= "2B",10000,EV_DB[[#This Row],[FHWA Class (2B - 8)]]=3,55000,OR(EV_DB[[#This Row],[FHWA Class (2B - 8)]]=4,EV_DB[[#This Row],[FHWA Class (2B - 8)]]=5), 75000,OR(EV_DB[[#This Row],[FHWA Class (2B - 8)]]=6,EV_DB[[#This Row],[FHWA Class (2B - 8)]]=7),100000,EV_DB[[#This Row],[FHWA Class (2B - 8)]]=8, 150000)} -> 75000 | AF26: =MIN(MAX(EV_DB[[#This Row],[Federal Rebates (iMHZEV) ]],EV_DB[[#This Row],[ON Vehicle Rebates]]),PRODUCT(EV_DB[[#This Row],[Cost, $MSRP CAD]],0.75)) -> 75000 | AG26: =MIN(EV_DB[[#This Row],[Federal Rebates (iMHZEV) ]]+EV_DB[[#This Row],[BC Vehicle Rebates]],PRODUCT(EV_DB[[#This Row],[Cost, $MSRP CAD]],0.75)) -> 150000 | AH26: =MIN(EV_DB[[#This Row],[Federal Rebates (iMHZEV) ]]+EV_DB[[#This Row],[QC Vehicle Rebates]],PRODUCT(EV_DB[[#This Row],[Cost, $MSRP CAD]],0.75)) -> 75000 | AI26: =MIN(MAX(EV_DB[[#This Row],[Federal Rebates (iMHZEV) ]],EV_DB[[#This Row],[AB Vehicle Rebates]]),PRODUCT(EV_DB[[#This Row],[Cost, $MSRP CAD]],0.75)) -> 75000 | AJ26: =MIN(MAX(EV_DB[[#This Row],[Federal Rebates (iMHZEV) ]],EV_DB[[#This Row],[SC Vehicle Rebates]]),PRODUCT(EV_DB[[#This Row],[Cost, $MSRP CAD]],0.75)) -> 75000 | AK26: =MIN(MAX(EV_DB[[#This Row],[Federal Rebates (iMHZEV) ]],EV_DB[[#This Row],[NS Vehicle Rebates]]),PRODUCT(EV_DB[[#This Row],[Cost, $MSRP CAD]],0.75)) -> 75000 | AL26: =MIN(MAX(EV_DB[[#This Row],[Federal Rebates (iMHZEV) ]],EV_DB[[#This Row],[NB Vehicle Rebates]]),PRODUCT(EV_DB[[#This Row],[Cost, $MSRP CAD]],0.75)) -> 75000 | AM26: =MIN(MAX(EV_DB[[#This Row],[Federal Rebates (iMHZEV) ]],EV_DB[[#This Row],[MB Vehicle Rebates]]),PRODUCT(EV_DB[[#This Row],[Cost, $MSRP CAD]],0.75)) -> 75000 | AN26: =MIN(MAX(EV_DB[[#This Row],[Federal Rebates (iMHZEV) ]],EV_DB[[#This Row],[PEI Vehicle Rebates]]),PRODUCT(EV_DB[[#This Row],[Cost, $MSRP CAD]],0.75)) -> 75000 | AO26: =MIN(MAX(EV_DB[[#This Row],[Federal Rebates (iMHZEV) ]],EV_DB[[#This Row],[NL Vehicle Rebates]]),PRODUCT(EV_DB[[#This Row],[Cost, $MSRP CAD]],0.75)) -> 75000 | AP26: =MIN(MAX(EV_DB[[#This Row],[Federal Rebates (iMHZEV) ]]+EV_DB[[#This Row],[YT Vehicle Rebates]]),PRODUCT(EV_DB[[#This Row],[Cost, $MSRP CAD]],0.75)) -> 75000 | AQ26: =MIN(MAX(EV_DB[[#This Row],[Federal Rebates (iMHZEV) ]],EV_DB[[#This Row],[NU Vehicle Rebates]]),PRODUCT(EV_DB[[#This Row],[Cost, $MSRP CAD]],0.75)) -> 75000 | AR26: =MIN(MAX(EV_DB[[#This Row],[Federal Rebates (iMHZEV) ]],EV_DB[[#This Row],[NT Vehicle Rebates]]),PRODUCT(EV_DB[[#This Row],[Cost, $MSRP CAD]],0.75)) -> 75000
A27: GreenPower Motor Company | B27: EV Star CC | C27: =EV_DB[[#This Row],[Manufacturer ]]& " " &EV_DB[[#This Row],[Model]] -> GreenPower Motor Company EV Star CC | D27: Box truck | E27: 2023 | F27: 5 | G27: {=_xlfn.IFS(OR(EV_DB[[#This Row],[FHWA Class (2B - 8)]]= "2B", EV_DB[[#This Row],[FHWA Class (2B - 8)]]=3), "Light Duty",OR(EV_DB[[#This Row],[FHWA Class (2B - 8)]]=4,EV_DB[[#This Row],[FHWA Class (2B - 8)]]=5,EV_DB[[#This Row],[FHWA Class (2B - 8)]]=6),"Medium Duty",OR(EV_DB[[#This Row],[FHWA Class (2B - 8)]]=7,EV_DB[[#This Row],[FHWA Class (2B - 8)]]=8), "Heavy Duty")} -> Medium Duty | H27: 14300 | I27: 7000 | J27: 212900 | K27: {=_xlfn.IFS(EV_DB[[#This Row],[Category]]="Light Duty",'Maintenance costs table'!$D$4,EV_DB[[#This Row],[Category]]="Medium Duty",'Maintenance costs table'!$D$8,EV_DB[[#This Row],[Category]]="Heavy Duty",'Maintenance costs table'!$D$6)} -> 0.25 | L27: No | M27: 118 kWh | N27: 0.26 | O27: Dual (AC/DC) Level-2, J1772, 19.2 kW AC, ~8 hrs DCFC, CCS-1, 60 kW, ~2 hrs Wireless DC (option), 60 kW, ~2 hrs | P27: 576 | Q27: 400 | R27: {=_xlfn.IFS(EV_DB[[#This Row],[Battery Size, kWh]]>350 & EV_DB[[#This Row],[FHWA Class (2B - 8)]]=8,'iMHZEV table'!$D$4,EV_DB[[#This Row],[Battery Size, kWh]]<=350 & EV_DB[[#This Row],[FHWA Class (2B - 8)]]=8,'iMHZEV table'!$D$5, TRUE, _xlfn.XLOOKUP(EV_DB[[#This Row],[FHWA Class (2B - 8)]],'iMHZEV table'!$A$3:$A$11,'iMHZEV table'!$D$3:$D$11))} -> 75000 | T27: {=_xlfn.IFS(EV_DB[[#This Row],[FHWA Class (2B - 8)]]= "2B",10000,EV_DB[[#This Row],[FHWA Class (2B - 8)]]=3,55000,OR(EV_DB[[#This Row],[FHWA Class (2B - 8)]]=4,EV_DB[[#This Row],[FHWA Class (2B - 8)]]=5), 75000,OR(EV_DB[[#This Row],[FHWA Class (2B - 8)]]=6,EV_DB[[#This Row],[FHWA Class (2B - 8)]]=7),100000,EV_DB[[#This Row],[FHWA Class (2B - 8)]]=8, 150000)} -> 75000 | AF27: =MIN(MAX(EV_DB[[#This Row],[Federal Rebates (iMHZEV) ]],EV_DB[[#This Row],[ON Vehicle Rebates]]),PRODUCT(EV_DB[[#This Row],[Cost, $MSRP CAD]],0.75)) -> 75000 | AG27: =MIN(EV_DB[[#This Row],[Federal Rebates (iMHZEV) ]]+EV_DB[[#This Row],[BC Vehicle Rebates]],PRODUCT(EV_DB[[#This Row],[Cost, $MSRP CAD]],0.75)) -> 150000 | AH27: =MIN(EV_DB[[#This Row],[Federal Rebates (iMHZEV) ]]+EV_DB[[#This Row],[QC Vehicle Rebates]],PRODUCT(EV_DB[[#This Row],[Cost, $MSRP CAD]],0.75)) -> 75000 | AI27: =MIN(MAX(EV_DB[[#This Row],[Federal Rebates (iMHZEV) ]],EV_DB[[#This Row],[AB Vehicle Rebates]]),PRODUCT(EV_DB[[#This Row],[Cost, $MSRP CAD]],0.75)) -> 75000 | AJ27: =MIN(MAX(EV_DB[[#This Row],[Federal Rebates (iMHZEV) ]],EV_DB[[#This Row],[SC Vehicle Rebates]]),PRODUCT(EV_DB[[#This Row],[Cost, $MSRP CAD]],0.75)) -> 75000 | AK27: =MIN(MAX(EV_DB[[#This Row],[Federal Rebates (iMHZEV) ]],EV_DB[[#This Row],[NS Vehicle Rebates]]),PRODUCT(EV_DB[[#This Row],[Cost, $MSRP CAD]],0.75)) -> 75000 | AL27: =MIN(MAX(EV_DB[[#This Row],[Federal Rebates (iMHZEV) ]],EV_DB[[#This Row],[NB Vehicle Rebates]]),PRODUCT(EV_DB[[#This Row],[Cost, $MSRP CAD]],0.75)) -> 75000 | AM27: =MIN(MAX(EV_DB[[#This Row],[Federal Rebates (iMHZEV) ]],EV_DB[[#This Row],[MB Vehicle Rebates]]),PRODUCT(EV_DB[[#This Row],[Cost, $MSRP CAD]],0.75)) -> 75000 | AN27: =MIN(MAX(EV_DB[[#This Row],[Federal Rebates (iMHZEV) ]],EV_DB[[#This Row],[PEI Vehicle Rebates]]),PRODUCT(EV_DB[[#This Row],[Cost, $MSRP CAD]],0.75)) -> 75000 | AO27: =MIN(MAX(EV_DB[[#This Row],[Federal Rebates (iMHZEV) ]],EV_DB[[#This Row],[NL Vehicle Rebates]]),PRODUCT(EV_DB[[#This Row],[Cost, $MSRP CAD]],0.75)) -> 75000 | AP27: =MIN(MAX(EV_DB[[#This Row],[Federal Rebates (iMHZEV) ]]+EV_DB[[#This Row],[YT Vehicle Rebates]]),PRODUCT(EV_DB[[#This Row],[Cost, $MSRP CAD]],0.75)) -> 75000 | AQ27: =MIN(MAX(EV_DB[[#This Row],[Federal Rebates (iMHZEV) ]],EV_DB[[#This Row],[NU Vehicle Rebates]]),PRODUCT(EV_DB[[#This Row],[Cost, $MSRP CAD]],0.75)) -> 75000 | AR27: =MIN(MAX(EV_DB[[#This Row],[Federal Rebates (iMHZEV) ]],EV_DB[[#This Row],[NT Vehicle Rebates]]),PRODUCT(EV_DB[[#This Row],[Cost, $MSRP CAD]],0.75)) -> 75000
A28: BYD | B28: 6F | C28: =EV_DB[[#This Row],[Manufacturer ]]& " " &EV_DB[[#This Row],[Model]] -> BYD 6F | D28: Truck | E28: 2024 | F28: 6 | G28: {=_xlfn.IFS(OR(EV_DB[[#This Row],[FHWA Class (2B - 8)]]= "2B", EV_DB[[#This Row],[FHWA Class (2B - 8)]]=3), "Light Duty",OR(EV_DB[[#This Row],[FHWA Class (2B - 8)]]=4,EV_DB[[#This Row],[FHWA Class (2B - 8)]]=5,EV_DB[[#This Row],[FHWA Class (2B - 8)]]=6),"Medium Duty",OR(EV_DB[[#This Row],[FHWA Class (2B - 8)]]=7,EV_DB[[#This Row],[FHWA Class (2B - 8)]]=8), "Heavy Duty")} -> Medium Duty | H28: (19,501-26,000) | I28: 15639 | J28: 300000 | K28: {=_xlfn.IFS(EV_DB[[#This Row],[Category]]="Light Duty",'Maintenance costs table'!$D$4,EV_DB[[#This Row],[Category]]="Medium Duty",'Maintenance costs table'!$D$8,EV_DB[[#This Row],[Category]]="Heavy Duty",'Maintenance costs table'!$D$6)} -> 0.25 | L28: No | M28: 281 kWh 343 kWh | N28: 0.3 | O28: DC charging: 150 kW | Q28: 250 | R28: {=_xlfn.IFS(EV_DB[[#This Row],[Battery Size, kWh]]>350 & EV_DB[[#This Row],[FHWA Class (2B - 8)]]=8,'iMHZEV table'!$D$4,EV_DB[[#This Row],[Battery Size, kWh]]<=350 & EV_DB[[#This Row],[FHWA Class (2B - 8)]]=8,'iMHZEV table'!$D$5, TRUE, _xlfn.XLOOKUP(EV_DB[[#This Row],[FHWA Class (2B - 8)]],'iMHZEV table'!$A$3:$A$11,'iMHZEV table'!$D$3:$D$11))} -> 100000 | T28: {=_xlfn.IFS(EV_DB[[#This Row],[FHWA Class (2B - 8)]]= "2B",10000,EV_DB[[#This Row],[FHWA Class (2B - 8)]]=3,55000,OR(EV_DB[[#This Row],[FHWA Class (2B - 8)]]=4,EV_DB[[#This Row],[FHWA Class (2B - 8)]]=5), 75000,OR(EV_DB[[#This Row],[FHWA Class (2B - 8)]]=6,EV_DB[[#This Row],[FHWA Class (2B - 8)]]=7),100000,EV_DB[[#This Row],[FHWA Class (2B - 8)]]=8, 150000)} -> 100000 | AF28: =MIN(MAX(EV_DB[[#This Row],[Federal Rebates (iMHZEV) ]],EV_DB[[#This Row],[ON Vehicle Rebates]]),PRODUCT(EV_DB[[#This Row],[Cost, $MSRP CAD]],0.75)) -> 100000 | AG28: =MIN(EV_DB[[#This Row],[Federal Rebates (iMHZEV) ]]+EV_DB[[#This Row],[BC Vehicle Rebates]],PRODUCT(EV_DB[[#This Row],[Cost, $MSRP CAD]],0.75)) -> 200000 | AH28: =MIN(EV_DB[[#This Row],[Federal Rebates (iMHZEV) ]]+EV_DB[[#This Row],[QC Vehicle Rebates]],PRODUCT(EV_DB[[#This Row],[Cost, $MSRP CAD]],0.75)) -> 100000 | AI28: =MIN(MAX(EV_DB[[#This Row],[Federal Rebates (iMHZEV) ]],EV_DB[[#This Row],[AB Vehicle Rebates]]),PRODUCT(EV_DB[[#This Row],[Cost, $MSRP CAD]],0.75)) -> 100000 | AJ28: =MIN(MAX(EV_DB[[#This Row],[Federal Rebates (iMHZEV) ]],EV_DB[[#This Row],[SC Vehicle Rebates]]),PRODUCT(EV_DB[[#This Row],[Cost, $MSRP CAD]],0.75)) -> 100000 | AK28: =MIN(MAX(EV_DB[[#This Row],[Federal Rebates (iMHZEV) ]],EV_DB[[#This Row],[NS Vehicle Rebates]]),PRODUCT(EV_DB[[#This Row],[Cost, $MSRP CAD]],0.75)) -> 100000 | AL28: =MIN(MAX(EV_DB[[#This Row],[Federal Rebates (iMHZEV) ]],EV_DB[[#This Row],[NB Vehicle Rebates]]),PRODUCT(EV_DB[[#This Row],[Cost, $MSRP CAD]],0.75)) -> 100000 | AM28: =MIN(MAX(EV_DB[[#This Row],[Federal Rebates (iMHZEV) ]],EV_DB[[#This Row],[MB Vehicle Rebates]]),PRODUCT(EV_DB[[#This Row],[Cost, $MSRP CAD]],0.75)) -> 100000 | AN28: =MIN(MAX(EV_DB[[#This Row],[Federal Rebates (iMHZEV) ]],EV_DB[[#This Row],[PEI Vehicle Rebates]]),PRODUCT(EV_DB[[#This Row],[Cost, $MSRP CAD]],0.75)) -> 100000 | AO28: =MIN(MAX(EV_DB[[#This Row],[Federal Rebates (iMHZEV) ]],EV_DB[[#This Row],[NL Vehicle Rebates]]),PRODUCT(EV_DB[[#This Row],[Cost, $MSRP CAD]],0.75)) -> 100000 | AP28: =MIN(MAX(EV_DB[[#This Row],[Federal Rebates (iMHZEV) ]]+EV_DB[[#This Row],[YT Vehicle Rebates]]),PRODUCT(EV_DB[[#This Row],[Cost, $MSRP CAD]],0.75)) -> 100000 | AQ28: =MIN(MAX(EV_DB[[#This Row],[Federal Rebates (iMHZEV) ]],EV_DB[[#This Row],[NU Vehicle Rebates]]),PRODUCT(EV_DB[[#This Row],[Cost, $MSRP CAD]],0.75)) -> 100000 | AR28: =MIN(MAX(EV_DB[[#This Row],[Federal Rebates (iMHZEV) ]],EV_DB[[#This Row],[NT Vehicle Rebates]]),PRODUCT(EV_DB[[#This Row],[Cost, $MSRP CAD]],0.75)) -> 100000
A29: XOS | B29: SV 20' | C29: =EV_DB[[#This Row],[Manufacturer ]]& " " &EV_DB[[#This Row],[Model]] -> XOS SV 20' | D29: Step Van | E29: 2023 | F29: 6 | G29: {=_xlfn.IFS(OR(EV_DB[[#This Row],[FHWA Class (2B - 8)]]= "2B", EV_DB[[#This Row],[FHWA Class (2B - 8)]]=3), "Light Duty",OR(EV_DB[[#This Row],[FHWA Class (2B - 8)]]=4,EV_DB[[#This Row],[FHWA Class (2B - 8)]]=5,EV_DB[[#This Row],[FHWA Class (2B - 8)]]=6),"Medium Duty",OR(EV_DB[[#This Row],[FHWA Class (2B - 8)]]=7,EV_DB[[#This Row],[FHWA Class (2B - 8)]]=8), "Heavy Duty")} -> Medium Duty | H29: 19,500 - 23,000 | I29: 16000 | J29: 334000 | K29: {=_xlfn.IFS(EV_DB[[#This Row],[Category]]="Light Duty",'Maintenance costs table'!$D$4,EV_DB[[#This Row],[Category]]="Medium Duty",'Maintenance costs table'!$D$8,EV_DB[[#This Row],[Category]]="Heavy Duty",'Maintenance costs table'!$D$6)} -> 0.25 | L29: No | M29: 280 kWh | N29: 0.28 | O29: • 0 - 80% Charge-time** • DC: 65 Minutes • L2: 5.5 Hours | Q29: 241 | R29: {=_xlfn.IFS(EV_DB[[#This Row],[Battery Size, kWh]]>350 & EV_DB[[#This Row],[FHWA Class (2B - 8)]]=8,'iMHZEV table'!$D$4,EV_DB[[#This Row],[Battery Size, kWh]]<=350 & EV_DB[[#This Row],[FHWA Class (2B - 8)]]=8,'iMHZEV table'!$D$5, TRUE, _xlfn.XLOOKUP(EV_DB[[#This Row],[FHWA Class (2B - 8)]],'iMHZEV table'!$A$3:$A$11,'iMHZEV table'!$D$3:$D$11))} -> 100000 | T29: {=_xlfn.IFS(EV_DB[[#This Row],[FHWA Class (2B - 8)]]= "2B",10000,EV_DB[[#This Row],[FHWA Class (2B - 8)]]=3,55000,OR(EV_DB[[#This Row],[FHWA Class (2B - 8)]]=4,EV_DB[[#This Row],[FHWA Class (2B - 8)]]=5), 75000,OR(EV_DB[[#This Row],[FHWA Class (2B - 8)]]=6,EV_DB[[#This Row],[FHWA Class (2B - 8)]]=7),100000,EV_DB[[#This Row],[FHWA Class (2B - 8)]]=8, 150000)} -> 100000 | AF29: =MIN(MAX(EV_DB[[#This Row],[Federal Rebates (iMHZEV) ]],EV_DB[[#This Row],[ON Vehicle Rebates]]),PRODUCT(EV_DB[[#This Row],[Cost, $MSRP CAD]],0.75)) -> 100000 | AG29: =MIN(EV_DB[[#This Row],[Federal Rebates (iMHZEV) ]]+EV_DB[[#This Row],[BC Vehicle Rebates]],PRODUCT(EV_DB[[#This Row],[Cost, $MSRP CAD]],0.75)) -> 200000 | AH29: =MIN(EV_DB[[#This Row],[Federal Rebates (iMHZEV) ]]+EV_DB[[#This Row],[QC Vehicle Rebates]],PRODUCT(EV_DB[[#This Row],[Cost, $MSRP CAD]],0.75)) -> 100000 | AI29: =MIN(MAX(EV_DB[[#This Row],[Federal Rebates (iMHZEV) ]],EV_DB[[#This Row],[AB Vehicle Rebates]]),PRODUCT(EV_DB[[#This Row],[Cost, $MSRP CAD]],0.75)) -> 100000 | AJ29: =MIN(MAX(EV_DB[[#This Row],[Federal Rebates (iMHZEV) ]],EV_DB[[#This Row],[SC Vehicle Rebates]]),PRODUCT(EV_DB[[#This Row],[Cost, $MSRP CAD]],0.75)) -> 100000 | AK29: =MIN(MAX(EV_DB[[#This Row],[Federal Rebates (iMHZEV) ]],EV_DB[[#This Row],[NS Vehicle Rebates]]),PRODUCT(EV_DB[[#This Row],[Cost, $MSRP CAD]],0.75)) -> 100000 | AL29: =MIN(MAX(EV_DB[[#This Row],[Federal Rebates (iMHZEV) ]],EV_DB[[#This Row],[NB Vehicle Rebates]]),PRODUCT(EV_DB[[#This Row],[Cost, $MSRP CAD]],0.75)) -> 100000 | AM29: =MIN(MAX(EV_DB[[#This Row],[Federal Rebates (iMHZEV) ]],EV_DB[[#This Row],[MB Vehicle Rebates]]),PRODUCT(EV_DB[[#This Row],[Cost, $MSRP CAD]],0.75)) -> 100000 | AN29: =MIN(MAX(EV_DB[[#This Row],[Federal Rebates (iMHZEV) ]],EV_DB[[#This Row],[PEI Vehicle Rebates]]),PRODUCT(EV_DB[[#This Row],[Cost, $MSRP CAD]],0.75)) -> 100000 | AO29: =MIN(MAX(EV_DB[[#This Row],[Federal Rebates (iMHZEV) ]],EV_DB[[#This Row],[NL Vehicle Rebates]]),PRODUCT(EV_DB[[#This Row],[Cost, $MSRP CAD]],0.75)) -> 100000 | AP29: =MIN(MAX(EV_DB[[#This Row],[Federal Rebates (iMHZEV) ]]+EV_DB[[#This Row],[YT Vehicle Rebates]]),PRODUCT(EV_DB[[#This Row],[Cost, $MSRP CAD]],0.75)) -> 100000 | AQ29: =MIN(MAX(EV_DB[[#This Row],[Federal Rebates (iMHZEV) ]],EV_DB[[#This Row],[NU Vehicle Rebates]]),PRODUCT(EV_DB[[#This Row],[Cost, $MSRP CAD]],0.75)) -> 100000 | AR29: =MIN(MAX(EV_DB[[#This Row],[Federal Rebates (iMHZEV) ]],EV_DB[[#This Row],[NT Vehicle Rebates]]),PRODUCT(EV_DB[[#This Row],[Cost, $MSRP CAD]],0.75)) -> 100000
A30: EVT Motors | B30: High Roof Logistics Van | C30: =EV_DB[[#This Row],[Manufacturer ]]& " " &EV_DB[[#This Row],[Model]] -> EVT Motors High Roof Logistics Van | D30: Van | E30: 2023 | F30: 4 | G30: {=_xlfn.IFS(OR(EV_DB[[#This Row],[FHWA Class (2B - 8)]]= "2B", EV_DB[[#This Row],[FHWA Class (2B - 8)]]=3), "Light Duty",OR(EV_DB[[#This Row],[FHWA Class (2B - 8)]]=4,EV_DB[[#This Row],[FHWA Class (2B - 8)]]=5,EV_DB[[#This Row],[FHWA Class (2B - 8)]]=6),"Medium Duty",OR(EV_DB[[#This Row],[FHWA Class (2B - 8)]]=7,EV_DB[[#This Row],[FHWA Class (2B - 8)]]=8), "Heavy Duty")} -> Medium Duty | H30: 14200 | I30: 7800 | J30: 200000 | K30: {=_xlfn.IFS(EV_DB[[#This Row],[Category]]="Light Duty",'Maintenance costs table'!$D$4,EV_DB[[#This Row],[Category]]="Medium Duty",'Maintenance costs table'!$D$8,EV_DB[[#This Row],[Category]]="Heavy Duty",'Maintenance costs table'!$D$6)} -> 0.25 | L30: No | M30: 106.2 kWh | N30: 0.27 | Q30: 273 | R30: {=_xlfn.IFS(EV_DB[[#This Row],[Battery Size, kWh]]>350 & EV_DB[[#This Row],[FHWA Class (2B - 8)]]=8,'iMHZEV table'!$D$4,EV_DB[[#This Row],[Battery Size, kWh]]<=350 & EV_DB[[#This Row],[FHWA Class (2B - 8)]]=8,'iMHZEV table'!$D$5, TRUE, _xlfn.XLOOKUP(EV_DB[[#This Row],[FHWA Class (2B - 8)]],'iMHZEV table'!$A$3:$A$11,'iMHZEV table'!$D$3:$D$11))} -> 75000 | T30: {=_xlfn.IFS(EV_DB[[#This Row],[FHWA Class (2B - 8)]]= "2B",10000,EV_DB[[#This Row],[FHWA Class (2B - 8)]]=3,55000,OR(EV_DB[[#This Row],[FHWA Class (2B - 8)]]=4,EV_DB[[#This Row],[FHWA Class (2B - 8)]]=5), 75000,OR(EV_DB[[#This Row],[FHWA Class (2B - 8)]]=6,EV_DB[[#This Row],[FHWA Class (2B - 8)]]=7),100000,EV_DB[[#This Row],[FHWA Class (2B - 8)]]=8, 150000)} -> 75000 | AF30: =MIN(MAX(EV_DB[[#This Row],[Federal Rebates (iMHZEV) ]],EV_DB[[#This Row],[ON Vehicle Rebates]]),PRODUCT(EV_DB[[#This Row],[Cost, $MSRP CAD]],0.75)) -> 75000 | AG30: =MIN(EV_DB[[#This Row],[Federal Rebates (iMHZEV) ]]+EV_DB[[#This Row],[BC Vehicle Rebates]],PRODUCT(EV_DB[[#This Row],[Cost, $MSRP CAD]],0.75)) -> 150000 | AH30: =MIN(EV_DB[[#This Row],[Federal Rebates (iMHZEV) ]]+EV_DB[[#This Row],[QC Vehicle Rebates]],PRODUCT(EV_DB[[#This Row],[Cost, $MSRP CAD]],0.75)) -> 75000 | AI30: =MIN(MAX(EV_DB[[#This Row],[Federal Rebates (iMHZEV) ]],EV_DB[[#This Row],[AB Vehicle Rebates]]),PRODUCT(EV_DB[[#This Row],[Cost, $MSRP CAD]],0.75)) -> 75000 | AJ30: =MIN(MAX(EV_DB[[#This Row],[Federal Rebates (iMHZEV) ]],EV_DB[[#This Row],[SC Vehicle Rebates]]),PRODUCT(EV_DB[[#This Row],[Cost, $MSRP CAD]],0.75)) -> 75000 | AK30: =MIN(MAX(EV_DB[[#This Row],[Federal Rebates (iMHZEV) ]],EV_DB[[#This Row],[NS Vehicle Rebates]]),PRODUCT(EV_DB[[#This Row],[Cost, $MSRP CAD]],0.75)) -> 75000 | AL30: =MIN(MAX(EV_DB[[#This Row],[Federal Rebates (iMHZEV) ]],EV_DB[[#This Row],[NB Vehicle Rebates]]),PRODUCT(EV_DB[[#This Row],[Cost, $MSRP CAD]],0.75)) -> 75000 | AM30: =MIN(MAX(EV_DB[[#This Row],[Federal Rebates (iMHZEV) ]],EV_DB[[#This Row],[MB Vehicle Rebates]]),PRODUCT(EV_DB[[#This Row],[Cost, $MSRP CAD]],0.75)) -> 75000 | AN30: =MIN(MAX(EV_DB[[#This Row],[Federal Rebates (iMHZEV) ]],EV_DB[[#This Row],[PEI Vehicle Rebates]]),PRODUCT(EV_DB[[#This Row],[Cost, $MSRP CAD]],0.75)) -> 75000 | AO30: =MIN(MAX(EV_DB[[#This Row],[Federal Rebates (iMHZEV) ]],EV_DB[[#This Row],[NL Vehicle Rebates]]),PRODUCT(EV_DB[[#This Row],[Cost, $MSRP CAD]],0.75)) -> 75000 | AP30: =MIN(MAX(EV_DB[[#This Row],[Federal Rebates (iMHZEV) ]]+EV_DB[[#This Row],[YT Vehicle Rebates]]),PRODUCT(EV_DB[[#This Row],[Cost, $MSRP CAD]],0.75)) -> 75000 | AQ30: =MIN(MAX(EV_DB[[#This Row],[Federal Rebates (iMHZEV) ]],EV_DB[[#This Row],[NU Vehicle Rebates]]),PRODUCT(EV_DB[[#This Row],[Cost, $MSRP CAD]],0.75)) -> 75000 | AR30: =MIN(MAX(EV_DB[[#This Row],[Federal Rebates (iMHZEV) ]],EV_DB[[#This Row],[NT Vehicle Rebates]]),PRODUCT(EV_DB[[#This Row],[Cost, $MSRP CAD]],0.75)) -> 75000
A31: Freightliner | B31: MT50e | C31: =EV_DB[[#This Row],[Manufacturer ]]& " " &EV_DB[[#This Row],[Model]] -> Freightliner MT50e | D31: Step Van Urban delivery | E31: 2024 | F31: 5 | G31: {=_xlfn.IFS(OR(EV_DB[[#This Row],[FHWA Class (2B - 8)]]= "2B", EV_DB[[#This Row],[FHWA Class (2B - 8)]]=3), "Light Duty",OR(EV_DB[[#This Row],[FHWA Class (2B - 8)]]=4,EV_DB[[#This Row],[FHWA Class (2B - 8)]]=5,EV_DB[[#This Row],[FHWA Class (2B - 8)]]=6),"Medium Duty",OR(EV_DB[[#This Row],[FHWA Class (2B - 8)]]=7,EV_DB[[#This Row],[FHWA Class (2B - 8)]]=8), "Heavy Duty")} -> Medium Duty | H31: 16,000 - 22,000 | I31: 19800 | J31: 262595 | K31: {=_xlfn.IFS(EV_DB[[#This Row],[Category]]="Light Duty",'Maintenance costs table'!$D$4,EV_DB[[#This Row],[Category]]="Medium Duty",'Maintenance costs table'!$D$8,EV_DB[[#This Row],[Category]]="Heavy Duty",'Maintenance costs table'!$D$6)} -> 0.25 | L31: No | M31: 246 kWh | N31: 0.29 | Q31: 290 | R31: {=_xlfn.IFS(EV_DB[[#This Row],[Battery Size, kWh]]>350 & EV_DB[[#This Row],[FHWA Class (2B - 8)]]=8,'iMHZEV table'!$D$4,EV_DB[[#This Row],[Battery Size, kWh]]<=350 & EV_DB[[#This Row],[FHWA Class (2B - 8)]]=8,'iMHZEV table'!$D$5, TRUE, _xlfn.XLOOKUP(EV_DB[[#This Row],[FHWA Class (2B - 8)]],'iMHZEV table'!$A$3:$A$11,'iMHZEV table'!$D$3:$D$11))} -> 75000 | T31: {=_xlfn.IFS(EV_DB[[#This Row],[FHWA Class (2B - 8)]]= "2B",10000,EV_DB[[#This Row],[FHWA Class (2B - 8)]]=3,55000,OR(EV_DB[[#This Row],[FHWA Class (2B - 8)]]=4,EV_DB[[#This Row],[FHWA Class (2B - 8)]]=5), 75000,OR(EV_DB[[#This Row],[FHWA Class (2B - 8)]]=6,EV_DB[[#This Row],[FHWA Class (2B - 8)]]=7),100000,EV_DB[[#This Row],[FHWA Class (2B - 8)]]=8, 150000)} -> 75000 | AF31: =MIN(MAX(EV_DB[[#This Row],[Federal Rebates (iMHZEV) ]],EV_DB[[#This Row],[ON Vehicle Rebates]]),PRODUCT(EV_DB[[#This Row],[Cost, $MSRP CAD]],0.75)) -> 75000 | AG31: =MIN(EV_DB[[#This Row],[Federal Rebates (iMHZEV) ]]+EV_DB[[#This Row],[BC Vehicle Rebates]],PRODUCT(EV_DB[[#This Row],[Cost, $MSRP CAD]],0.75)) -> 150000 | AH31: =MIN(EV_DB[[#This Row],[Federal Rebates (iMHZEV) ]]+EV_DB[[#This Row],[QC Vehicle Rebates]],PRODUCT(EV_DB[[#This Row],[Cost, $MSRP CAD]],0.75)) -> 75000 | AI31: =MIN(MAX(EV_DB[[#This Row],[Federal Rebates (iMHZEV) ]],EV_DB[[#This Row],[AB Vehicle Rebates]]),PRODUCT(EV_DB[[#This Row],[Cost, $MSRP CAD]],0.75)) -> 75000 | AJ31: =MIN(MAX(EV_DB[[#This Row],[Federal Rebates (iMHZEV) ]],EV_DB[[#This Row],[SC Vehicle Rebates]]),PRODUCT(EV_DB[[#This Row],[Cost, $MSRP CAD]],0.75)) -> 75000 | AK31: =MIN(MAX(EV_DB[[#This Row],[Federal Rebates (iMHZEV) ]],EV_DB[[#This Row],[NS Vehicle Rebates]]),PRODUCT(EV_DB[[#This Row],[Cost, $MSRP CAD]],0.75)) -> 75000 | AL31: =MIN(MAX(EV_DB[[#This Row],[Federal Rebates (iMHZEV) ]],EV_DB[[#This Row],[NB Vehicle Rebates]]),PRODUCT(EV_DB[[#This Row],[Cost, $MSRP CAD]],0.75)) -> 75000 | AM31: =MIN(MAX(EV_DB[[#This Row],[Federal Rebates (iMHZEV) ]],EV_DB[[#This Row],[MB Vehicle Rebates]]),PRODUCT(EV_DB[[#This Row],[Cost, $MSRP CAD]],0.75)) -> 75000 | AN31: =MIN(MAX(EV_DB[[#This Row],[Federal Rebates (iMHZEV) ]],EV_DB[[#This Row],[PEI Vehicle Rebates]]),PRODUCT(EV_DB[[#This Row],[Cost, $MSRP CAD]],0.75)) -> 75000 | AO31: =MIN(MAX(EV_DB[[#This Row],[Federal Rebates (iMHZEV) ]],EV_DB[[#This Row],[NL Vehicle Rebates]]),PRODUCT(EV_DB[[#This Row],[Cost, $MSRP CAD]],0.75)) -> 75000 | AP31: =MIN(MAX(EV_DB[[#This Row],[Federal Rebates (iMHZEV) ]]+EV_DB[[#This Row],[YT Vehicle Rebates]]),PRODUCT(EV_DB[[#This Row],[Cost, $MSRP CAD]],0.75)) -> 75000 | AQ31: =MIN(MAX(EV_DB[[#This Row],[Federal Rebates (iMHZEV) ]],EV_DB[[#This Row],[NU Vehicle Rebates]]),PRODUCT(EV_DB[[#This Row],[Cost, $MSRP CAD]],0.75)) -> 75000 | AR31: =MIN(MAX(EV_DB[[#This Row],[Federal Rebates (iMHZEV) ]],EV_DB[[#This Row],[NT Vehicle Rebates]]),PRODUCT(EV_DB[[#This Row],[Cost, $MSRP CAD]],0.75)) -> 75000
A32: Freightliner | B32: MT50e | C32: Freightliner MT50e | D32: Step Van Urban delivery | E32: 2024 | F32: 6 | G32: {=_xlfn.IFS(OR(EV_DB[[#This Row],[FHWA Class (2B - 8)]]= "2B", EV_DB[[#This Row],[FHWA Class (2B - 8)]]=3), "Light Duty",OR(EV_DB[[#This Row],[FHWA Class (2B - 8)]]=4,EV_DB[[#This Row],[FHWA Class (2B - 8)]]=5,EV_DB[[#This Row],[FHWA Class (2B - 8)]]=6),"Medium Duty",OR(EV_DB[[#This Row],[FHWA Class (2B - 8)]]=7,EV_DB[[#This Row],[FHWA Class (2B - 8)]]=8), "Heavy Duty")} -> Medium Duty | H32: 23000 | I32: 19800 | J32: 272595 | K32: {=_xlfn.IFS(EV_DB[[#This Row],[Category]]="Light Duty",'Maintenance costs table'!$D$4,EV_DB[[#This Row],[Category]]="Medium Duty",'Maintenance costs table'!$D$8,EV_DB[[#This Row],[Category]]="Heavy Duty",'Maintenance costs table'!$D$6)} -> 0.25 | L32: No | M32: 246 kWh | N32: 0.29 | Q32: 290 | R32: {=_xlfn.IFS(EV_DB[[#This Row],[Battery Size, kWh]]>350 & EV_DB[[#This Row],[FHWA Class (2B - 8)]]=8,'iMHZEV table'!$D$4,EV_DB[[#This Row],[Battery Size, kWh]]<=350 & EV_DB[[#This Row],[FHWA Class (2B - 8)]]=8,'iMHZEV table'!$D$5, TRUE, _xlfn.XLOOKUP(EV_DB[[#This Row],[FHWA Class (2B - 8)]],'iMHZEV table'!$A$3:$A$11,'iMHZEV table'!$D$3:$D$11))} -> 100000 | T32: {=_xlfn.IFS(EV_DB[[#This Row],[FHWA Class (2B - 8)]]= "2B",10000,EV_DB[[#This Row],[FHWA Class (2B - 8)]]=3,55000,OR(EV_DB[[#This Row],[FHWA Class (2B - 8)]]=4,EV_DB[[#This Row],[FHWA Class (2B - 8)]]=5), 75000,OR(EV_DB[[#This Row],[FHWA Class (2B - 8)]]=6,EV_DB[[#This Row],[FHWA Class (2B - 8)]]=7),100000,EV_DB[[#This Row],[FHWA Class (2B - 8)]]=8, 150000)} -> 100000 | AF32: =MIN(MAX(EV_DB[[#This Row],[Federal Rebates (iMHZEV) ]],EV_DB[[#This Row],[ON Vehicle Rebates]]),PRODUCT(EV_DB[[#This Row],[Cost, $MSRP CAD]],0.75)) -> 100000 | AG32: =MIN(EV_DB[[#This Row],[Federal Rebates (iMHZEV) ]]+EV_DB[[#This Row],[BC Vehicle Rebates]],PRODUCT(EV_DB[[#This Row],[Cost, $MSRP CAD]],0.75)) -> 200000 | AH32: =MIN(EV_DB[[#This Row],[Federal Rebates (iMHZEV) ]]+EV_DB[[#This Row],[QC Vehicle Rebates]],PRODUCT(EV_DB[[#This Row],[Cost, $MSRP CAD]],0.75)) -> 100000 | AI32: =MIN(MAX(EV_DB[[#This Row],[Federal Rebates (iMHZEV) ]],EV_DB[[#This Row],[AB Vehicle Rebates]]),PRODUCT(EV_DB[[#This Row],[Cost, $MSRP CAD]],0.75)) -> 100000 | AJ32: =MIN(MAX(EV_DB[[#This Row],[Federal Rebates (iMHZEV) ]],EV_DB[[#This Row],[SC Vehicle Rebates]]),PRODUCT(EV_DB[[#This Row],[Cost, $MSRP CAD]],0.75)) -> 100000 | AK32: =MIN(MAX(EV_DB[[#This Row],[Federal Rebates (iMHZEV) ]],EV_DB[[#This Row],[NS Vehicle Rebates]]),PRODUCT(EV_DB[[#This Row],[Cost, $MSRP CAD]],0.75)) -> 100000 | AL32: =MIN(MAX(EV_DB[[#This Row],[Federal Rebates (iMHZEV) ]],EV_DB[[#This Row],[NB Vehicle Rebates]]),PRODUCT(EV_DB[[#This Row],[Cost, $MSRP CAD]],0.75)) -> 100000 | AM32: =MIN(MAX(EV_DB[[#This Row],[Federal Rebates (iMHZEV) ]],EV_DB[[#This Row],[MB Vehicle Rebates]]),PRODUCT(EV_DB[[#This Row],[Cost, $MSRP CAD]],0.75)) -> 100000 | AN32: =MIN(MAX(EV_DB[[#This Row],[Federal Rebates (iMHZEV) ]],EV_DB[[#This Row],[PEI Vehicle Rebates]]),PRODUCT(EV_DB[[#This Row],[Cost, $MSRP CAD]],0.75)) -> 100000 | AO32: =MIN(MAX(EV_DB[[#This Row],[Federal Rebates (iMHZEV) ]],EV_DB[[#This Row],[NL Vehicle Rebates]]),PRODUCT(EV_DB[[#This Row],[Cost, $MSRP CAD]],0.75)) -> 100000 | AP32: =MIN(MAX(EV_DB[[#This Row],[Federal Rebates (iMHZEV) ]]+EV_DB[[#This Row],[YT Vehicle Rebates]]),PRODUCT(EV_DB[[#This Row],[Cost, $MSRP CAD]],0.75)) -> 100000 | AQ32: =MIN(MAX(EV_DB[[#This Row],[Federal Rebates (iMHZEV) ]],EV_DB[[#This Row],[NU Vehicle Rebates]]),PRODUCT(EV_DB[[#This Row],[Cost, $MSRP CAD]],0.75)) -> 100000 | AR32: =MIN(MAX(EV_DB[[#This Row],[Federal Rebates (iMHZEV) ]],EV_DB[[#This Row],[NT Vehicle Rebates]]),PRODUCT(EV_DB[[#This Row],[Cost, $MSRP CAD]],0.75)) -> 100000
A33: Lion | B33: Lion6 | C33: =EV_DB[[#This Row],[Manufacturer ]]& " " &EV_DB[[#This Row],[Model]] -> Lion Lion6 | D33: Commercial trucks | E33: 2024 | F33: 6 | G33: {=_xlfn.IFS(OR(EV_DB[[#This Row],[FHWA Class (2B - 8)]]= "2B", EV_DB[[#This Row],[FHWA Class (2B - 8)]]=3), "Light Duty",OR(EV_DB[[#This Row],[FHWA Class (2B - 8)]]=4,EV_DB[[#This Row],[FHWA Class (2B - 8)]]=5,EV_DB[[#This Row],[FHWA Class (2B - 8)]]=6),"Medium Duty",OR(EV_DB[[#This Row],[FHWA Class (2B - 8)]]=7,EV_DB[[#This Row],[FHWA Class (2B - 8)]]=8), "Heavy Duty")} -> Medium Duty | H33: 26000 | I33: 15500 | J33: 375000 | K33: {=_xlfn.IFS(EV_DB[[#This Row],[Category]]="Light Duty",'Maintenance costs table'!$D$4,EV_DB[[#This Row],[Category]]="Medium Duty",'Maintenance costs table'!$D$8,EV_DB[[#This Row],[Category]]="Heavy Duty",'Maintenance costs table'!$D$6)} -> 0.25 | L33: No | M33: 252 kWh | N33: 0.31 | Q33: 350 | R33: {=_xlfn.IFS(EV_DB[[#This Row],[Battery Size, kWh]]>350 & EV_DB[[#This Row],[FHWA Class (2B - 8)]]=8,'iMHZEV table'!$D$4,EV_DB[[#This Row],[Battery Size, kWh]]<=350 & EV_DB[[#This Row],[FHWA Class (2B - 8)]]=8,'iMHZEV table'!$D$5, TRUE, _xlfn.XLOOKUP(EV_DB[[#This Row],[FHWA Class (2B - 8)]],'iMHZEV table'!$A$3:$A$11,'iMHZEV table'!$D$3:$D$11))} -> 100000 | T33: {=_xlfn.IFS(EV_DB[[#This Row],[FHWA Class (2B - 8)]]= "2B",10000,EV_DB[[#This Row],[FHWA Class (2B - 8)]]=3,55000,OR(EV_DB[[#This Row],[FHWA Class (2B - 8)]]=4,EV_DB[[#This Row],[FHWA Class (2B - 8)]]=5), 75000,OR(EV_DB[[#This Row],[FHWA Class (2B - 8)]]=6,EV_DB[[#This Row],[FHWA Class (2B - 8)]]=7),100000,EV_DB[[#This Row],[FHWA Class (2B - 8)]]=8, 150000)} -> 100000 | AF33: =MIN(MAX(EV_DB[[#This Row],[Federal Rebates (iMHZEV) ]],EV_DB[[#This Row],[ON Vehicle Rebates]]),PRODUCT(EV_DB[[#This Row],[Cost, $MSRP CAD]],0.75)) -> 100000 | AG33: =MIN(EV_DB[[#This Row],[Federal Rebates (iMHZEV) ]]+EV_DB[[#This Row],[BC Vehicle Rebates]],PRODUCT(EV_DB[[#This Row],[Cost, $MSRP CAD]],0.75)) -> 200000 | AH33: =MIN(EV_DB[[#This Row],[Federal Rebates (iMHZEV) ]]+EV_DB[[#This Row],[QC Vehicle Rebates]],PRODUCT(EV_DB[[#This Row],[Cost, $MSRP CAD]],0.75)) -> 100000 | AI33: =MIN(MAX(EV_DB[[#This Row],[Federal Rebates (iMHZEV) ]],EV_DB[[#This Row],[AB Vehicle Rebates]]),PRODUCT(EV_DB[[#This Row],[Cost, $MSRP CAD]],0.75)) -> 100000 | AJ33: =MIN(MAX(EV_DB[[#This Row],[Federal Rebates (iMHZEV) ]],EV_DB[[#This Row],[SC Vehicle Rebates]]),PRODUCT(EV_DB[[#This Row],[Cost, $MSRP CAD]],0.75)) -> 100000 | AK33: =MIN(MAX(EV_DB[[#This Row],[Federal Rebates (iMHZEV) ]],EV_DB[[#This Row],[NS Vehicle Rebates]]),PRODUCT(EV_DB[[#This Row],[Cost, $MSRP CAD]],0.75)) -> 100000 | AL33: =MIN(MAX(EV_DB[[#This Row],[Federal Rebates (iMHZEV) ]],EV_DB[[#This Row],[NB Vehicle Rebates]]),PRODUCT(EV_DB[[#This Row],[Cost, $MSRP CAD]],0.75)) -> 100000 | AM33: =MIN(MAX(EV_DB[[#This Row],[Federal Rebates (iMHZEV) ]],EV_DB[[#This Row],[MB Vehicle Rebates]]),PRODUCT(EV_DB[[#This Row],[Cost, $MSRP CAD]],0.75)) -> 100000 | AN33: =MIN(MAX(EV_DB[[#This Row],[Federal Rebates (iMHZEV) ]],EV_DB[[#This Row],[PEI Vehicle Rebates]]),PRODUCT(EV_DB[[#This Row],[Cost, $MSRP CAD]],0.75)) -> 100000 | AO33: =MIN(MAX(EV_DB[[#This Row],[Federal Rebates (iMHZEV) ]],EV_DB[[#This Row],[NL Vehicle Rebates]]),PRODUCT(EV_DB[[#This Row],[Cost, $MSRP CAD]],0.75)) -> 100000 | AP33: =MIN(MAX(EV_DB[[#This Row],[Federal Rebates (iMHZEV) ]]+EV_DB[[#This Row],[YT Vehicle Rebates]]),PRODUCT(EV_DB[[#This Row],[Cost, $MSRP CAD]],0.75)) -> 100000 | AQ33: =MIN(MAX(EV_DB[[#This Row],[Federal Rebates (iMHZEV) ]],EV_DB[[#This Row],[NU Vehicle Rebates]]),PRODUCT(EV_DB[[#This Row],[Cost, $MSRP CAD]],0.75)) -> 100000 | AR33: =MIN(MAX(EV_DB[[#This Row],[Federal Rebates (iMHZEV) ]],EV_DB[[#This Row],[NT Vehicle Rebates]]),PRODUCT(EV_DB[[#This Row],[Cost, $MSRP CAD]],0.75)) -> 100000
A34: Lion | B34: Lion5 | C34: =EV_DB[[#This Row],[Manufacturer ]]& " " &EV_DB[[#This Row],[Model]] -> Lion Lion5 | D34: Commercial trucks | E34: 2024 | F34: 5 | G34: {=_xlfn.IFS(OR(EV_DB[[#This Row],[FHWA Class (2B - 8)]]= "2B", EV_DB[[#This Row],[FHWA Class (2B - 8)]]=3), "Light Duty",OR(EV_DB[[#This Row],[FHWA Class (2B - 8)]]=4,EV_DB[[#This Row],[FHWA Class (2B - 8)]]=5,EV_DB[[#This Row],[FHWA Class (2B - 8)]]=6),"Medium Duty",OR(EV_DB[[#This Row],[FHWA Class (2B - 8)]]=7,EV_DB[[#This Row],[FHWA Class (2B - 8)]]=8), "Heavy Duty")} -> Medium Duty | H34: 19,500. – 22,500 | I34: 12500 | J34: 320000 | K34: {=_xlfn.IFS(EV_DB[[#This Row],[Category]]="Light Duty",'Maintenance costs table'!$D$4,EV_DB[[#This Row],[Category]]="Medium Duty",'Maintenance costs table'!$D$8,EV_DB[[#This Row],[Category]]="Heavy Duty",'Maintenance costs table'!$D$6)} -> 0.25 | L34: No | M34: 210 kWh | N34: 0.3 | Q34: 305 | R34: {=_xlfn.IFS(EV_DB[[#This Row],[Battery Size, kWh]]>350 & EV_DB[[#This Row],[FHWA Class (2B - 8)]]=8,'iMHZEV table'!$D$4,EV_DB[[#This Row],[Battery Size, kWh]]<=350 & EV_DB[[#This Row],[FHWA Class (2B - 8)]]=8,'iMHZEV table'!$D$5, TRUE, _xlfn.XLOOKUP(EV_DB[[#This Row],[FHWA Class (2B - 8)]],'iMHZEV table'!$A$3:$A$11,'iMHZEV table'!$D$3:$D$11))} -> 75000 | T34: {=_xlfn.IFS(EV_DB[[#This Row],[FHWA Class (2B - 8)]]= "2B",10000,EV_DB[[#This Row],[FHWA Class (2B - 8)]]=3,55000,OR(EV_DB[[#This Row],[FHWA Class (2B - 8)]]=4,EV_DB[[#This Row],[FHWA Class (2B - 8)]]=5), 75000,OR(EV_DB[[#This Row],[FHWA Class (2B - 8)]]=6,EV_DB[[#This Row],[FHWA Class (2B - 8)]]=7),100000,EV_DB[[#This Row],[FHWA Class (2B - 8)]]=8, 150000)} -> 75000 | AF34: =MIN(MAX(EV_DB[[#This Row],[Federal Rebates (iMHZEV) ]],EV_DB[[#This Row],[ON Vehicle Rebates]]),PRODUCT(EV_DB[[#This Row],[Cost, $MSRP CAD]],0.75)) -> 75000 | AG34: =MIN(EV_DB[[#This Row],[Federal Rebates (iMHZEV) ]]+EV_DB[[#This Row],[BC Vehicle Rebates]],PRODUCT(EV_DB[[#This Row],[Cost, $MSRP CAD]],0.75)) -> 150000 | AH34: =MIN(EV_DB[[#This Row],[Federal Rebates (iMHZEV) ]]+EV_DB[[#This Row],[QC Vehicle Rebates]],PRODUCT(EV_DB[[#This Row],[Cost, $MSRP CAD]],0.75)) -> 75000 | AI34: =MIN(MAX(EV_DB[[#This Row],[Federal Rebates (iMHZEV) ]],EV_DB[[#This Row],[AB Vehicle Rebates]]),PRODUCT(EV_DB[[#This Row],[Cost, $MSRP CAD]],0.75)) -> 75000 | AJ34: =MIN(MAX(EV_DB[[#This Row],[Federal Rebates (iMHZEV) ]],EV_DB[[#This Row],[SC Vehicle Rebates]]),PRODUCT(EV_DB[[#This Row],[Cost, $MSRP CAD]],0.75)) -> 75000 | AK34: =MIN(MAX(EV_DB[[#This Row],[Federal Rebates (iMHZEV) ]],EV_DB[[#This Row],[NS Vehicle Rebates]]),PRODUCT(EV_DB[[#This Row],[Cost, $MSRP CAD]],0.75)) -> 75000 | AL34: =MIN(MAX(EV_DB[[#This Row],[Federal Rebates (iMHZEV) ]],EV_DB[[#This Row],[NB Vehicle Rebates]]),PRODUCT(EV_DB[[#This Row],[Cost, $MSRP CAD]],0.75)) -> 75000 | AM34: =MIN(MAX(EV_DB[[#This Row],[Federal Rebates (iMHZEV) ]],EV_DB[[#This Row],[MB Vehicle Rebates]]),PRODUCT(EV_DB[[#This Row],[Cost, $MSRP CAD]],0.75)) -> 75000 | AN34: =MIN(MAX(EV_DB[[#This Row],[Federal Rebates (iMHZEV) ]],EV_DB[[#This Row],[PEI Vehicle Rebates]]),PRODUCT(EV_DB[[#This Row],[Cost, $MSRP CAD]],0.75)) -> 75000 | AO34: =MIN(MAX(EV_DB[[#This Row],[Federal Rebates (iMHZEV) ]],EV_DB[[#This Row],[NL Vehicle Rebates]]),PRODUCT(EV_DB[[#This Row],[Cost, $MSRP CAD]],0.75)) -> 75000 | AP34: =MIN(MAX(EV_DB[[#This Row],[Federal Rebates (iMHZEV) ]]+EV_DB[[#This Row],[YT Vehicle Rebates]]),PRODUCT(EV_DB[[#This Row],[Cost, $MSRP CAD]],0.75)) -> 75000 | AQ34: =MIN(MAX(EV_DB[[#This Row],[Federal Rebates (iMHZEV) ]],EV_DB[[#This Row],[NU Vehicle Rebates]]),PRODUCT(EV_DB[[#This Row],[Cost, $MSRP CAD]],0.75)) -> 75000 | AR34: =MIN(MAX(EV_DB[[#This Row],[Federal Rebates (iMHZEV) ]],EV_DB[[#This Row],[NT Vehicle Rebates]]),PRODUCT(EV_DB[[#This Row],[Cost, $MSRP CAD]],0.75)) -> 75000
A35: International | B35: Navistar eMV | C35: =EV_DB[[#This Row],[Manufacturer ]]& " " &EV_DB[[#This Row],[Model]] -> International Navistar eMV | D35: Truck | E35: 2024 | F35: 6 | G35: {=_xlfn.IFS(OR(EV_DB[[#This Row],[FHWA Class (2B - 8)]]= "2B", EV_DB[[#This Row],[FHWA Class (2B - 8)]]=3), "Light Duty",OR(EV_DB[[#This Row],[FHWA Class (2B - 8)]]=4,EV_DB[[#This Row],[FHWA Class (2B - 8)]]=5,EV_DB[[#This Row],[FHWA Class (2B - 8)]]=6),"Medium Duty",OR(EV_DB[[#This Row],[FHWA Class (2B - 8)]]=7,EV_DB[[#This Row],[FHWA Class (2B - 8)]]=8), "Heavy Duty")} -> Medium Duty | H35: 11,792kg (25,999) 14,968kg (33,000) | I35: 11000 | J35: $354,500 | K35: {=_xlfn.IFS(EV_DB[[#This Row],[Category]]="Light Duty",'Maintenance costs table'!$D$4,EV_DB[[#This Row],[Category]]="Medium Duty",'Maintenance costs table'!$D$8,EV_DB[[#This Row],[Category]]="Heavy Duty",'Maintenance costs table'!$D$6)} -> 0.25 | L35: No | M35: 210 kWh | N35: 0.32 | O35: 125KW/hour capable with a DC charger Vehicle to Grid (V2G) capability standard equipment (DC charger required) SAE J1772 CCS1 AC/DC charging standard | P35: 609 | Q35: 200 | R35: {=_xlfn.IFS(EV_DB[[#This Row],[Battery Size, kWh]]>350 & EV_DB[[#This Row],[FHWA Class (2B - 8)]]=8,'iMHZEV table'!$D$4,EV_DB[[#This Row],[Battery Size, kWh]]<=350 & EV_DB[[#This Row],[FHWA Class (2B - 8)]]=8,'iMHZEV table'!$D$5, TRUE, _xlfn.XLOOKUP(EV_DB[[#This Row],[FHWA Class (2B - 8)]],'iMHZEV table'!$A$3:$A$11,'iMHZEV table'!$D$3:$D$11))} -> 100000 | T35: {=_xlfn.IFS(EV_DB[[#This Row],[FHWA Class (2B - 8)]]= "2B",10000,EV_DB[[#This Row],[FHWA Class (2B - 8)]]=3,55000,OR(EV_DB[[#This Row],[FHWA Class (2B - 8)]]=4,EV_DB[[#This Row],[FHWA Class (2B - 8)]]=5), 75000,OR(EV_DB[[#This Row],[FHWA Class (2B - 8)]]=6,EV_DB[[#This Row],[FHWA Class (2B - 8)]]=7),100000,EV_DB[[#This Row],[FHWA Class (2B - 8)]]=8, 150000)} -> 100000 | AF35: =MIN(MAX(EV_DB[[#This Row],[Federal Rebates (iMHZEV) ]],EV_DB[[#This Row],[ON Vehicle Rebates]]),PRODUCT(EV_DB[[#This Row],[Cost, $MSRP CAD]],0.75)) -> 0.75 | AG35: =MIN(EV_DB[[#This Row],[Federal Rebates (iMHZEV) ]]+EV_DB[[#This Row],[BC Vehicle Rebates]],PRODUCT(EV_DB[[#This Row],[Cost, $MSRP CAD]],0.75)) -> 0.75 | AH35: =MIN(EV_DB[[#This Row],[Federal Rebates (iMHZEV) ]]+EV_DB[[#This Row],[QC Vehicle Rebates]],PRODUCT(EV_DB[[#This Row],[Cost, $MSRP CAD]],0.75)) -> 0.75 | AI35: =MIN(MAX(EV_DB[[#This Row],[Federal Rebates (iMHZEV) ]],EV_DB[[#This Row],[AB Vehicle Rebates]]),PRODUCT(EV_DB[[#This Row],[Cost, $MSRP CAD]],0.75)) -> 0.75 | AJ35: =MIN(MAX(EV_DB[[#This Row],[Federal Rebates (iMHZEV) ]],EV_DB[[#This Row],[SC Vehicle Rebates]]),PRODUCT(EV_DB[[#This Row],[Cost, $MSRP CAD]],0.75)) -> 0.75 | AK35: =MIN(MAX(EV_DB[[#This Row],[Federal Rebates (iMHZEV) ]],EV_DB[[#This Row],[NS Vehicle Rebates]]),PRODUCT(EV_DB[[#This Row],[Cost, $MSRP CAD]],0.75)) -> 0.75 | AL35: =MIN(MAX(EV_DB[[#This Row],[Federal Rebates (iMHZEV) ]],EV_DB[[#This Row],[NB Vehicle Rebates]]),PRODUCT(EV_DB[[#This Row],[Cost, $MSRP CAD]],0.75)) -> 0.75 | AM35: =MIN(MAX(EV_DB[[#This Row],[Federal Rebates (iMHZEV) ]],EV_DB[[#This Row],[MB Vehicle Rebates]]),PRODUCT(EV_DB[[#This Row],[Cost, $MSRP CAD]],0.75)) -> 0.75 | AN35: =MIN(MAX(EV_DB[[#This Row],[Federal Rebates (iMHZEV) ]],EV_DB[[#This Row],[PEI Vehicle Rebates]]),PRODUCT(EV_DB[[#This Row],[Cost, $MSRP CAD]],0.75)) -> 0.75 | AO35: =MIN(MAX(EV_DB[[#This Row],[Federal Rebates (iMHZEV) ]],EV_DB[[#This Row],[NL Vehicle Rebates]]),PRODUCT(EV_DB[[#This Row],[Cost, $MSRP CAD]],0.75)) -> 0.75 | AP35: =MIN(MAX(EV_DB[[#This Row],[Federal Rebates (iMHZEV) ]]+EV_DB[[#This Row],[YT Vehicle Rebates]]),PRODUCT(EV_DB[[#This Row],[Cost, $MSRP CAD]],0.75)) -> 0.75 | AQ35: =MIN(MAX(EV_DB[[#This Row],[Federal Rebates (iMHZEV) ]],EV_DB[[#This Row],[NU Vehicle Rebates]]),PRODUCT(EV_DB[[#This Row],[Cost, $MSRP CAD]],0.75)) -> 0.75 | AR35: =MIN(MAX(EV_DB[[#This Row],[Federal Rebates (iMHZEV) ]],EV_DB[[#This Row],[NT Vehicle Rebates]]),PRODUCT(EV_DB[[#This Row],[Cost, $MSRP CAD]],0.75)) -> 0.75
A36: Mercedes-Benz | B36: Daimler eActros 600 | C36: =EV_DB[[#This Row],[Manufacturer ]]& " " &EV_DB[[#This Row],[Model]] -> Mercedes-Benz Daimler eActros 600 | D36: Semi trailer tractor | E36: 2025 | F36: 6 | G36: {=_xlfn.IFS(OR(EV_DB[[#This Row],[FHWA Class (2B - 8)]]= "2B", EV_DB[[#This Row],[FHWA Class (2B - 8)]]=3), "Light Duty",OR(EV_DB[[#This Row],[FHWA Class (2B - 8)]]=4,EV_DB[[#This Row],[FHWA Class (2B - 8)]]=5,EV_DB[[#This Row],[FHWA Class (2B - 8)]]=6),"Medium Duty",OR(EV_DB[[#This Row],[FHWA Class (2B - 8)]]=7,EV_DB[[#This Row],[FHWA Class (2B - 8)]]=8), "Heavy Duty")} -> Medium Duty | H36: GCW ~ 44,000 | I36: 48501 | J36: 500000 | K36: {=_xlfn.IFS(EV_DB[[#This Row],[Category]]="Light Duty",'Maintenance costs table'!$D$4,EV_DB[[#This Row],[Category]]="Medium Duty",'Maintenance costs table'!$D$8,EV_DB[[#This Row],[Category]]="Heavy Duty",'Maintenance costs table'!$D$6)} -> 0.25 | L36: No | M36: 621 kWh | N36: 0.22 | O36: max 160 kW DC 20% to 80% in around 30 minutes | Q36: 500 | R36: {=_xlfn.IFS(EV_DB[[#This Row],[Battery Size, kWh]]>350 & EV_DB[[#This Row],[FHWA Class (2B - 8)]]=8,'iMHZEV table'!$D$4,EV_DB[[#This Row],[Battery Size, kWh]]<=350 & EV_DB[[#This Row],[FHWA Class (2B - 8)]]=8,'iMHZEV table'!$D$5, TRUE, _xlfn.XLOOKUP(EV_DB[[#This Row],[FHWA Class (2B - 8)]],'iMHZEV table'!$A$3:$A$11,'iMHZEV table'!$D$3:$D$11))} -> 100000 | T36: {=_xlfn.IFS(EV_DB[[#This Row],[FHWA Class (2B - 8)]]= "2B",10000,EV_DB[[#This Row],[FHWA Class (2B - 8)]]=3,55000,OR(EV_DB[[#This Row],[FHWA Class (2B - 8)]]=4,EV_DB[[#This Row],[FHWA Class (2B - 8)]]=5), 75000,OR(EV_DB[[#This Row],[FHWA Class (2B - 8)]]=6,EV_DB[[#This Row],[FHWA Class (2B - 8)]]=7),100000,EV_DB[[#This Row],[FHWA Class (2B - 8)]]=8, 150000)} -> 100000 | AF36: =MIN(MAX(EV_DB[[#This Row],[Federal Rebates (iMHZEV) ]],EV_DB[[#This Row],[ON Vehicle Rebates]]),PRODUCT(EV_DB[[#This Row],[Cost, $MSRP CAD]],0.75)) -> 100000 | AG36: =MIN(EV_DB[[#This Row],[Federal Rebates (iMHZEV) ]]+EV_DB[[#This Row],[BC Vehicle Rebates]],PRODUCT(EV_DB[[#This Row],[Cost, $MSRP CAD]],0.75)) -> 200000 | AH36: =MIN(EV_DB[[#This Row],[Federal Rebates (iMHZEV) ]]+EV_DB[[#This Row],[QC Vehicle Rebates]],PRODUCT(EV_DB[[#This Row],[Cost, $MSRP CAD]],0.75)) -> 100000 | AI36: =MIN(MAX(EV_DB[[#This Row],[Federal Rebates (iMHZEV) ]],EV_DB[[#This Row],[AB Vehicle Rebates]]),PRODUCT(EV_DB[[#This Row],[Cost, $MSRP CAD]],0.75)) -> 100000 | AJ36: =MIN(MAX(EV_DB[[#This Row],[Federal Rebates (iMHZEV) ]],EV_DB[[#This Row],[SC Vehicle Rebates]]),PRODUCT(EV_DB[[#This Row],[Cost, $MSRP CAD]],0.75)) -> 100000 | AK36: =MIN(MAX(EV_DB[[#This Row],[Federal Rebates (iMHZEV) ]],EV_DB[[#This Row],[NS Vehicle Rebates]]),PRODUCT(EV_DB[[#This Row],[Cost, $MSRP CAD]],0.75)) -> 100000 | AL36: =MIN(MAX(EV_DB[[#This Row],[Federal Rebates (iMHZEV) ]],EV_DB[[#This Row],[NB Vehicle Rebates]]),PRODUCT(EV_DB[[#This Row],[Cost, $MSRP CAD]],0.75)) -> 100000 | AM36: =MIN(MAX(EV_DB[[#This Row],[Federal Rebates (iMHZEV) ]],EV_DB[[#This Row],[MB Vehicle Rebates]]),PRODUCT(EV_DB[[#This Row],[Cost, $MSRP CAD]],0.75)) -> 100000 | AN36: =MIN(MAX(EV_DB[[#This Row],[Federal Rebates (iMHZEV) ]],EV_DB[[#This Row],[PEI Vehicle Rebates]]),PRODUCT(EV_DB[[#This Row],[Cost, $MSRP CAD]],0.75)) -> 100000 | AO36: =MIN(MAX(EV_DB[[#This Row],[Federal Rebates (iMHZEV) ]],EV_DB[[#This Row],[NL Vehicle Rebates]]),PRODUCT(EV_DB[[#This Row],[Cost, $MSRP CAD]],0.75)) -> 100000 | AP36: =MIN(MAX(EV_DB[[#This Row],[Federal Rebates (iMHZEV) ]]+EV_DB[[#This Row],[YT Vehicle Rebates]]),PRODUCT(EV_DB[[#This Row],[Cost, $MSRP CAD]],0.75)) -> 100000 | AQ36: =MIN(MAX(EV_DB[[#This Row],[Federal Rebates (iMHZEV) ]],EV_DB[[#This Row],[NU Vehicle Rebates]]),PRODUCT(EV_DB[[#This Row],[Cost, $MSRP CAD]],0.75)) -> 100000 | AR36: =MIN(MAX(EV_DB[[#This Row],[Federal Rebates (iMHZEV) ]],EV_DB[[#This Row],[NT Vehicle Rebates]]),PRODUCT(EV_DB[[#This Row],[Cost, $MSRP CAD]],0.75)) -> 100000
A37: Lightning eMotors | B37: 6500XD Cab | C37: =EV_DB[[#This Row],[Manufacturer ]]& " " &EV_DB[[#This Row],[Model]] -> Lightning eMotors 6500XD Cab | D37: Forward Truck | E37: 2023 | F37: 6 | G37: {=_xlfn.IFS(OR(EV_DB[[#This Row],[FHWA Class (2B - 8)]]= "2B", EV_DB[[#This Row],[FHWA Class (2B - 8)]]=3), "Light Duty",OR(EV_DB[[#This Row],[FHWA Class (2B - 8)]]=4,EV_DB[[#This Row],[FHWA Class (2B - 8)]]=5,EV_DB[[#This Row],[FHWA Class (2B - 8)]]=6),"Medium Duty",OR(EV_DB[[#This Row],[FHWA Class (2B - 8)]]=7,EV_DB[[#This Row],[FHWA Class (2B - 8)]]=8), "Heavy Duty")} -> Medium Duty | H37: 11,770 kg (25,950) | I37: 15000 | J37: 341678 | K37: {=_xlfn.IFS(EV_DB[[#This Row],[Category]]="Light Duty",'Maintenance costs table'!$D$4,EV_DB[[#This Row],[Category]]="Medium Duty",'Maintenance costs table'!$D$8,EV_DB[[#This Row],[Category]]="Heavy Duty",'Maintenance costs table'!$D$6)} -> 0.25 | L37: No | M37: 150 kWh - 160 kWh | N37: 0.3 | O37: DC Fast Charge (up to 80 kW) with J1772 CCS1 Combo | Q37: 210 | R37: {=_xlfn.IFS(EV_DB[[#This Row],[Battery Size, kWh]]>350 & EV_DB[[#This Row],[FHWA Class (2B - 8)]]=8,'iMHZEV table'!$D$4,EV_DB[[#This Row],[Battery Size, kWh]]<=350 & EV_DB[[#This Row],[FHWA Class (2B - 8)]]=8,'iMHZEV table'!$D$5, TRUE, _xlfn.XLOOKUP(EV_DB[[#This Row],[FHWA Class (2B - 8)]],'iMHZEV table'!$A$3:$A$11,'iMHZEV table'!$D$3:$D$11))} -> 100000 | T37: {=_xlfn.IFS(EV_DB[[#This Row],[FHWA Class (2B - 8)]]= "2B",10000,EV_DB[[#This Row],[FHWA Class (2B - 8)]]=3,55000,OR(EV_DB[[#This Row],[FHWA Class (2B - 8)]]=4,EV_DB[[#This Row],[FHWA Class (2B - 8)]]=5), 75000,OR(EV_DB[[#This Row],[FHWA Class (2B - 8)]]=6,EV_DB[[#This Row],[FHWA Class (2B - 8)]]=7),100000,EV_DB[[#This Row],[FHWA Class (2B - 8)]]=8, 150000)} -> 100000 | AF37: =MIN(MAX(EV_DB[[#This Row],[Federal Rebates (iMHZEV) ]],EV_DB[[#This Row],[ON Vehicle Rebates]]),PRODUCT(EV_DB[[#This Row],[Cost, $MSRP CAD]],0.75)) -> 100000 | AG37: =MIN(EV_DB[[#This Row],[Federal Rebates (iMHZEV) ]]+EV_DB[[#This Row],[BC Vehicle Rebates]],PRODUCT(EV_DB[[#This Row],[Cost, $MSRP CAD]],0.75)) -> 200000 | AH37: =MIN(EV_DB[[#This Row],[Federal Rebates (iMHZEV) ]]+EV_DB[[#This Row],[QC Vehicle Rebates]],PRODUCT(EV_DB[[#This Row],[Cost, $MSRP CAD]],0.75)) -> 100000 | AI37: =MIN(MAX(EV_DB[[#This Row],[Federal Rebates (iMHZEV) ]],EV_DB[[#This Row],[AB Vehicle Rebates]]),PRODUCT(EV_DB[[#This Row],[Cost, $MSRP CAD]],0.75)) -> 100000 | AJ37: =MIN(MAX(EV_DB[[#This Row],[Federal Rebates (iMHZEV) ]],EV_DB[[#This Row],[SC Vehicle Rebates]]),PRODUCT(EV_DB[[#This Row],[Cost, $MSRP CAD]],0.75)) -> 100000 | AK37: =MIN(MAX(EV_DB[[#This Row],[Federal Rebates (iMHZEV) ]],EV_DB[[#This Row],[NS Vehicle Rebates]]),PRODUCT(EV_DB[[#This Row],[Cost, $MSRP CAD]],0.75)) -> 100000 | AL37: =MIN(MAX(EV_DB[[#This Row],[Federal Rebates (iMHZEV) ]],EV_DB[[#This Row],[NB Vehicle Rebates]]),PRODUCT(EV_DB[[#This Row],[Cost, $MSRP CAD]],0.75)) -> 100000 | AM37: =MIN(MAX(EV_DB[[#This Row],[Federal Rebates (iMHZEV) ]],EV_DB[[#This Row],[MB Vehicle Rebates]]),PRODUCT(EV_DB[[#This Row],[Cost, $MSRP CAD]],0.75)) -> 100000 | AN37: =MIN(MAX(EV_DB[[#This Row],[Federal Rebates (iMHZEV) ]],EV_DB[[#This Row],[PEI Vehicle Rebates]]),PRODUCT(EV_DB[[#This Row],[Cost, $MSRP CAD]],0.75)) -> 100000 | AO37: =MIN(MAX(EV_DB[[#This Row],[Federal Rebates (iMHZEV) ]],EV_DB[[#This Row],[NL Vehicle Rebates]]),PRODUCT(EV_DB[[#This Row],[Cost, $MSRP CAD]],0.75)) -> 100000 | AP37: =MIN(MAX(EV_DB[[#This Row],[Federal Rebates (iMHZEV) ]]+EV_DB[[#This Row],[YT Vehicle Rebates]]),PRODUCT(EV_DB[[#This Row],[Cost, $MSRP CAD]],0.75)) -> 100000 | AQ37: =MIN(MAX(EV_DB[[#This Row],[Federal Rebates (iMHZEV) ]],EV_DB[[#This Row],[NU Vehicle Rebates]]),PRODUCT(EV_DB[[#This Row],[Cost, $MSRP CAD]],0.75)) -> 100000 | AR37: =MIN(MAX(EV_DB[[#This Row],[Federal Rebates (iMHZEV) ]],EV_DB[[#This Row],[NT Vehicle Rebates]]),PRODUCT(EV_DB[[#This Row],[Cost, $MSRP CAD]],0.75)) -> 100000
